Workbook

Sheet SUMMARY
A14: Project name : | B14: PROPOSED THREE STORY RESIDENCE
A15: Location : | B15: GRAND CENTENIAL HOMES KAWIT CAVITE
A16: Date : | B16: =TODAY() -> 46251
C18: Total Area: | D18: 387.9 | E18: sq.m | Q18: 3500 | R18: water cs
A19: ITEM NO | B19: WORK ITEM DESCRIPTION | C19: Total Amount Php | D19: Cost per Sq.m | E19: Weighted % age | F19: AMOUNT | L19: PERCENTAGE ACCOMPLISHMENT | O19: BALANCE AMOUNT | Q19: 2000 | R19: shower
A20: A | B20: GENERAL REQUIREMENTS | F20: THIS DATE | G20: 1900000 | L20: PREVIOUS | M20: THIS DATE | N20: TO DATE
B21: General Requirements Sub-total: | C21: =BOQ!I31 -> 599000 | D21: =C21/$D$18 -> 1544.2124 | E21: =C21/$C$39 -> 0.065068215 | F21: =BOQ!V31 -> 157250 | L21: =SUM(BOQ!AU31:BB31) -> 0.5 | M21: =F21/C21 -> 0.26252087 | N21: =L21+M21 -> 0.76252087 | O21: =C21-(N21*C21) -> 142250
A22: B | B22: ARCHITECTURAL WORKS
B23: Ceiling Finish | C23: =BOQ!$I$167 -> 942300.44 | D23: =C23/$D$18 -> 2429.2355 | E23: =C23/$C$39 -> 0.10236028 | F23: =BOQ!V167 -> 134756.63 | G23: =G20/C26 -> 0.78448388 | H23: =1-G23 -> 0.21551612 | J23: =SUM(C23:C27)*0.15 -> 1100379.8 | L23: =SUM(BOQ!AU167:BB167) -> 0.86075455 | M23: =BOQ!Y167 -> 0.13920009 | N23: =M23+L23 -> 0.99995465 | O23: =C23-(N23*C23) -> 42.734714
B24: Floor Finish | C24: =BOQ!I232 -> 368899.08 | D24: =C24/$D$18 -> 951.01593 | E24: =C24/$C$39 -> 0.040072796 | F24: =BOQ!V232 -> 77840.03 | L24: =SUM(BOQ!AU232:BB232) -> 0.8425 | M24: 0.09 | N24: =M24+L24 -> 0.9325 | O24: =C24-(N24*C24) -> 24900.688
B25: Wall Finish | C25: =wall!I127 -> 2040984.2 | D25: =C25/$D$18 -> 5261.6246 | E25: =C25/$C$39 -> 0.22170818 | F25: =wall!V127 -> 655611.9 | G25: =C26*H23 -> 521974.57 | L25: =SUM(wall!BB127:BI127) -> 0.32323129 | M25: =wall!Y127 -> 0.34305442 | N25: =M25+L25 -> 0.66628571 | O25: =C25-(N25*C25) -> 681105.58
B26: Cabinet's | C26: =SUM(CABINETS!I68,CABINETS!I155,CABINETS!I238) -> 2421974.6 | D26: =C26/$D$18 -> 6243.8117 | E26: =C26/$C$39 -> 0.26309443 | F26: =CABINETS!AD239 -> 996590.5 | L26: =SUM(CABINETS!BC239:BJ239) -> 0.12028571 | M26: =CABINETS!AG239 -> 0.36208466 | N26: =M26+L26 -> 0.48237037 | O26: =C26-(N26*C26) -> 1253685.8
B27: Door's and Window's | C27: ='DOORS & WINDOW, PLUMBING, WOODE'!H56 -> 1561707.2 | D27: =C27/$D$18 -> 4026.0562 | E27: =C27/$C$39 -> 0.16964524 | F27: ='DOORS & WINDOW, PLUMBING, WOODE'!O56 -> 241863.6 | L27: =SUM('DOORS & WINDOW, PLUMBING, WOODE'!AN56:AU56) -> 0.54761905 | M27: ='DOORS & WINDOW, PLUMBING, WOODE'!R56 -> 0.047619048 | N27: =M27+L27 -> 0.5952381 | O27: =C27-(N27*C27) -> 632119.58
B28: Architectural Sub-total: | C28: =SUM(C23:C27) -> 7335865.5 | D28: =SUM(D23:D27) -> 18911.744 | E28: =SUM(E23:E27) -> 0.79688092 | F28: =SUM(F23:F27) -> 2106662.7 | G28: =SUM(G23:G27) -> 521975.36 | H28: =SUM(H23:H27) -> 0.21551612 | I28: =SUM(I23:I27) -> 0 | J28: =SUM(J23:J27) -> 1100379.8 | K28: =SUM(K23:K27) -> 0 | L28: =SUM(L23:L27)/COUNT(L23:L27) -> 0.53887812 | M28: =SUM(M23:M27)/COUNT(M23:M27) -> 0.19639164 | N28: =SUM(N23:N27)/COUNT(N23:N27) -> 0.73526977 | O28: =SUM(O23:O27) -> 2591854.4
A29: C | B29: PLUMBING WORKS
B30: Plumbing Fixtures | C30: ='DOORS & WINDOW, PLUMBING, WOODE'!H66 -> 56500 | D30: =C30/$D$18 -> 145.6561 | E30: =C30/$C$39 -> 0.0061374861 | F30: ='DOORS & WINDOW, PLUMBING, WOODE'!O66 -> 0 | L30: =SUM('DOORS & WINDOW, PLUMBING, WOODE'!AN66:AU66) -> 0 | M30: ='DOORS & WINDOW, PLUMBING, WOODE'!R66/C30 -> 0 | N30: =M30+L30 -> 0 | O30: =C30-(N30*C30) -> 56500
B31: Plumbing Sub-total: | C31: =SUM(C30) -> 56500 | D31: =SUM(D30) -> 145.6561 | E31: =SUM(E30) -> 0.0061374861 | F31: =SUM(F30) -> 0 | G31: =SUM(G30) -> 0 | H31: =SUM(H30) -> 0 | I31: =SUM(I30) -> 0 | J31: =SUM(J30) -> 0 | ... O31: =SUM(O30) -> 56500
A32: D | B32: ELECTRICAL WORKS
B33: Lighting Fixtures | C33: =ELECTRICAL!I41 -> 607624 | D33: =C33/$D$18 -> 1566.445 | E33: =C33/$C$39 -> 0.066005024 | F33: =ELECTRICAL!Z41 -> 121524.8 | L33: =SUM(ELECTRICAL!AY41:BF41) -> 0 | M33: =ELECTRICAL!AC41 -> 0.2 | N33: =M33+L33 -> 0.2 | O33: =C33-(N33*C33) -> 486099.2
B34: Switches | C34: =ELECTRICAL!I29 -> 38841 | D34: =C34/$D$18 -> 100.13148 | E34: =C34/$C$39 -> 0.0042192229 | F34: =ELECTRICAL!Z29 -> 14368.75 | L34: =SUM(ELECTRICAL!AY29:BF29) -> 0 | M34: =ELECTRICAL!AC29 -> 0.36666667 | N34: =M34+L34 -> 0.36666667 | O34: =C34-(N34*C34) -> 24599.3
B35: Outlets | C35: =ELECTRICAL!I24 -> 66825 | D35: =C35/$D$18 -> 172.27378 | E35: =C35/$C$39 -> 0.0072590709 | F35: =ELECTRICAL!Z24 -> 26730 | G35: =C26+C23+C24+C25+C27 -> 7335865.5 | L35: =SUM(ELECTRICAL!AY24:BF24) -> 0 | M35: =ELECTRICAL!AC24 -> 0.4 | N35: =M35+L35 -> 0.4 | O35: =C35-(N35*C35) -> 40095
B36: Wires | C36: =ELECTRICAL!I49 -> 375412.68 | D36: =C36/$D$18 -> 967.80788 | E36: =C36/$C$39 -> 0.040780355 | F36: =ELECTRICAL!Z49 -> 96533.403 | L36: =SUM(ELECTRICAL!AY49:BF49) -> 0.6975 | M36: =ELECTRICAL!AC49 -> 0.2125 | N36: =M36+L36 -> 0.91 | O36: =C36-(N36*C36) -> 33787.141
B37: Panel Board | C37: =ELECTRICAL!I77 -> 125655.42 | D37: =C37/$D$18 -> 323.93766 | E37: =C37/$C$39 -> 0.013649706 | F37: =ELECTRICAL!Z77 -> 13471.7 | L37: =SUM(ELECTRICAL!AY77:BF77) -> 0 | M37: =ELECTRICAL!AC77 -> 0.083333333 | N37: =M37+L37 -> 0.083333333 | O37: =C37-(N37*C37) -> 115184.13
B38: Electrical Sub-total: | C38: =SUM(C33:C37) -> 1214358.1 | D38: =C38/$D$18 -> 3130.5958 | E38: =SUM(E33:E37) -> 0.13191338 | F38: =ELECTRICAL!Z78 -> 272628.65 | G38: =ELECTRICAL!AA78 -> 272628.65 | H38: =ELECTRICAL!AB78 -> 941729.44 | I38: =ELECTRICAL!AC78 -> 0.2525 | J38: =ELECTRICAL!AD78 -> 0 | K38: =ELECTRICAL!AE78 -> 0 | L38: =SUM(L33:L37)/COUNT(L33:L37) -> 0.1395 | M38: =SUM(M33:M37)/COUNT(M33:M37) -> 0.2525 | N38: =SUM(N33:N37)/COUNT(N33:N37) -> 0.392 | O38: =SUM(O33:O37) -> 699764.78
B39: Direct Sub-Total: | C39: =SUM(C31,C38,C28,C21) -> 9205723.6 | D39: =SUM(D31,D38,D28,D21) -> 23732.208 | E39: =SUM(E31,E38,E28,E21) -> 1 | F39: =SUM(F31,F38,F28,F21) -> 2536541.3 | G39: =SUM(G31,G38,G28,G21) -> 794604.01 | H39: =SUM(H31,H38,H28,H21) -> 941729.66 | I39: =SUM(I31,I38,I28,I21) -> 0.2525 | J39: =SUM(J31,J38,J28,J21) -> 1100379.8 | K39: =SUM(K31,K38,K28,K21) -> 0 | L39: =SUM(L31,L38,L28,L21)/4 -> 0.29459453 | M39: =SUM(M31,M38,M28,M21)/4 -> 0.17785313 | N39: =SUM(N31,N38,N28,N21)/4 -> 0.47244766 | O39: =SUM(O31,O38,O28,O21) -> 3490369.2
B40: Profit 7%: | C40: =C39*0.07 -> 644400.65 | F40: =M40*C40 -> 114608.67 | L40: =$L$39 -> 0.29459453 | M40: =$M$39 -> 0.17785313 | N40: =$N$39 -> 0.47244766 | O40: =C40-(N40*C40) -> 339955.07
B41: OCM 8%: | C41: =C39*0.08 -> 736457.88 | F41: =M41*C41 -> 130981.34 | J41: =(C40+C41)*0.92 -> 1270389.9 | L41: =$L$39 -> 0.29459453 | M41: =$M$39 -> 0.17785313 | N41: =$N$39 -> 0.47244766 | O41: =C41-(N41*C41) -> 388520.08
B42: Indirect Total Cost: | C42: =SUM(C39:C41) -> 10586582 | D42: =C42/$D$18 -> 27292.039 | E42: =SUM($E$38,$E$31,$E$28,$E$21) -> 1 | F42: =M42*C42 -> 1882856.7 | G42: =SUM(G39:G41) -> 794604.01 | H42: =SUM(H39:H41) -> 941729.66 | I42: =SUM(I39:I41) -> 0.2525 | J42: =SUM(J39:J41) -> 2370769.7 | K42: =SUM(K39:K41) -> 0 | L42: =L39 -> 0.29459453 | M42: =M39 -> 0.17785313 | N42: =N39 -> 0.47244766 | O42: =SUM(O39:O41) -> 4218844.3
B43: DISCOUNTED AMOUNT: | C43: 10300000 | D43: =C43/$D$18 -> 26553.235 | E43: =SUM($E$38,$E$31,$E$28,$E$21) -> 1 | F43: =M43*C43 -> 1831887.2 | G43: Overall Profit: | I43: =I40+J42 -> 2370769.7 | L43: =L39 -> 0.29459453 | M43: =M39 -> 0.17785313 | N43: =N39 -> 0.47244766 | O43: =C43-(N43*C43) -> 5433789.1
A45: BILLING SUMMARY
B46: PREVIOUS | C46: THIS DATE | D46: TO DATE | AB46: =C43*0.3 -> 3090000
A47: CONTRACT AMOUNT | B47: =C43*L43 -> 3034323.7 | C47: =F43 -> 1831887.2 | D47: =SUM(B47:C47) -> 4866210.9
A48: DEDUCTIONS | AB48: =D47+E47 -> 4866210.9
A49: RETENTION 5% | B49: =-$B$47*0.05 -> -151716.18 | C49: =-C47*0.05 -> -91594.361 | D49: =SUM(B49:C49) -> -243310.54 | AB49: =C43-AB48 -> 5433789.1
A50: RECOUPMENT 30% | B50: =-$B$47*0.3 -> -910297.1 | C50: =-C47*0.3 -> -549566.17 | D50: =SUM(B50:C50) -> -1459863.3
A51: TOTAL BILLING THIS DATE | B51: =SUM(B47:B50) -> 1972310.4 | C51: =SUM(C47:C50) -> 1190726.7 | D51: =SUM(B51:C51) -> 3163037.1
A52: %AGE BILLING THIS DATE | B52: =B47/$C$43 -> 0.29459453 | C52: =C47/$C$43 -> 0.17785313 | D52: =SUM(B52:C52) -> 0.47244766
A54: Remaining To Bill
A55: Billing no. 2 | B55: 21759.23
A56: Total : | B56: =SUM(B55:B55) -> 21759.23
A59: BANK DETAILS:
A60: BANK NAME: | B60: Saiko Builders Construction Services
A61: BPI ACCOUNT NUMBER: | B61: 8930- 0154 -83
A62: TOTAL AMOUNT: | B62: =C51+B56 -> 1212485.9
A64: Prepared By: | F64: Approved By:
B66: ENGR. Nadine D. Usman
B67: QUANTITY SURVEYOR
B69: ENGR. Kiel Caryl Buscayno
B70: QUANTITY SURVEYOR
B72: John Karl S. Quizon
B73: QUANTITY SURVEYOR
B75: Aljohn A. David
B76: QUANTITY SURVEYOR
A77: Reviewed By :
B78: ENGR. John Mark Evangelista
B79: VICE PRESIDENT-COO

Sheet BOQ
A15: Project name : | B15: PROPOSED THREE STORY RESIDENCE
A16: Location : | B16: GRAND CENTENIAL HOMES KAWIT CAVITE
A17: Date : | B17: =TODAY() -> 46251
AA18: QUANTITY | AJ18: AMOUNT | AS18: ACCOMPLISHMENT | AU18: PREVIOUS ACCOMPLISHMENT
A19: ITEM NO | B19: Description | C19: QUANTITY | D19: QUANTITY | E19: UNIT | F19: Material Cost Php/unit | G19: Labor and Equipment Cost Php/unit | H19: Total Cost Php/Unit | I19: Total Amount Php | Q19: QUANTITY | U19: AMOUNT | Y19: PERCENTAGE | AA19: BILLING 1 | AB19: BILLING 2 | AC19: BILLING 3 | AD19: BILLING 4 | AE19: BILLING 5 | AF19: BILLING 6 | AG19: BILLING 7 | AH19: BILLING 8 | AJ19: BILLING 1 | AK19: BILLING 2 | AL19: BILLING 3 | AM19: BILLING 4 | AN19: BILLING 5 | AO19: BILLING 6 | AP19: BILLING 7 | AQ19: BILLING 8 | AS19: BILLING 1 | AU19: BILLING 1 | AV19: BILLING 2 | AW19: BILLING 3 | AX19: BILLING 4 | AY19: BILLING 5 | AZ19: BILLING 6 | BA19: BILLING 7 | BB19: BILLING 8
A20: A | B20: GENERAL REQUIREMENTS | Q20: PREVIOUS | R20: THIS DATE | S20: TO DATE | T20: BALANCE | U20: PREVIOUS | V20: THIS DATE | W20: TO DATE | X20: BALANCE | Y20: Accomplishment
B21: Mobilization/Demobilization | C21: 1 | D21: 1 | E21: lot
B22: Site Management | C22: 10 | D22: 8 | E22: month/s | G22: 35000 | H22: =SUM(F22:G22) -> 35000 | I22: =H22*D22 -> 280000 | Q22: =SUM(AA22:AH22) -> 2.4 | R22: =Y22*D22 -> 2 | S22: =SUM(Q22:R22) -> 4.4 | T22: =D22-S22 -> 3.6 | U22: =SUM(AJ21:AQ21) -> 0 | V22: =Y22*I22 -> 70000 | W22: =SUM(U22:V22) -> 70000 | X22: =I22-W22 -> 210000 | Y22: =SUM(AS22) -> 0.25 | AA22: 2.4 | AJ22: 84000 | AS22: 0.25 | AU22: 0.3 | AV22: 0.2
B23: Government Permits and Taxes | C23: 1 | E23: lot | G23: by owner | H23: by owner
B24: Services and Utilities | C24: 10 | D24: 8 | E24: month/s | G24: 8000 | H24: =SUM(F24:G24) -> 8000 | I24: =H24*D24 -> 64000 | Q24: =SUM(AA24:AH24) -> 2.4 | R24: =Y24*D24 -> 2 | S24: =SUM(Q24:R24) -> 4.4 | T24: =D24-S24 -> 3.6 | U24: =SUM(AJ23:AQ23) -> 0 | V24: =Y24*I24 -> 16000 | W24: =SUM(U24:V24) -> 16000 | X24: =I24-W24 -> 48000 | Y24: =SUM(AS24) -> 0.25 | AA24: 2.4 | AJ24: 19200 | AS24: 0.25 | AU24: 0.3 | AV24: 0.2
B25: Temporary Facilities | C25: 10 | D25: 8 | E25: month/s | G25: 15000 | H25: =SUM(F25:G25) -> 15000 | I25: =H25*D25 -> 120000 | Q25: =SUM(AA25:AH25) -> 2.4 | R25: =Y25*D25 -> 2 | S25: =SUM(Q25:R25) -> 4.4 | T25: =D25-S25 -> 3.6 | U25: =SUM(AJ24:AQ24) -> 19200 | V25: =Y25*I25 -> 30000 | W25: =SUM(U25:V25) -> 49200 | X25: =I25-W25 -> 70800 | Y25: =SUM(AS25) -> 0.25 | AA25: 2.4 | AJ25: 36000 | AS25: 0.25 | AU25: 0.3 | AV25: 0.2
B26: Engineering plans, Shop Drawings & Asbuilt | C26: 1 | D26: 1 | E26: lot | G26: - | H26: DISCOUNTED
B27: Hauling and Disposal | C27: 1 | D27: 1 | E27: lot | G27: 60000 | H27: =SUM(F27:G27) -> 60000 | I27: =H27*D27 -> 60000 | Q27: =SUM(AA27:AH27) -> 0.3 | R27: =Y27*D27 -> 0.25 | S27: =SUM(Q27:R27) -> 0.55 | T27: =D27-S27 -> 0.45 | U27: =SUM(AJ26:AQ26) -> 0 | V27: =Y27*I27 -> 15000 | W27: =SUM(U27:V27) -> 15000 | X27: =I27-W27 -> 45000 | Y27: =SUM(AS27) -> 0.25 | AA27: 0.3 | AJ27: 18000 | AS27: 0.25 | AU27: 0.3 | AV27: 0.2
B28: Housekeeping | C28: 1 | D28: 1 | E28: lot | H28: Included
B29: Safety | C29: 1 | D29: 1 | E29: lot | H29: Included
B30: Scaffolding | C30: 1 | D30: 1 | E30: lot | G30: 75000 | H30: =SUM(F30:G30) -> 75000 | I30: =H30*D30 -> 75000 | Q30: =SUM(AA30:AH30) -> 0.3 | R30: =Y30*D30 -> 0.35 | S30: =SUM(Q30:R30) -> 0.65 | T30: =D30-S30 -> 0.35 | U30: =SUM(AJ29:AQ29) -> 0 | V30: =Y30*I30 -> 26250 | W30: =SUM(U30:V30) -> 26250 | X30: =I30-W30 -> 48750 | Y30: =SUM(AS30) -> 0.35 | AA30: 0.3 | AJ30: 22500 | AS30: 0.35 | AU30: 0.3 | AV30: 0.2
B31: General Requirements Sub-total: | I31: =SUM(I21:I30) -> 599000 | Q31: =SUM(Q22:Q30) -> 7.8 | R31: =SUM(R22:R30) -> 6.6 | S31: =SUM(S22:S30) -> 14.4 | T31: =SUM(T22:T30) -> 11.6 | U31: =SUM(U22:U30) -> 19200 | V31: =SUM(V22:V30) -> 157250 | W31: =SUM(W22:W30) -> 176450 | X31: =SUM(X22:X30) -> 422550 | Y31: =SUM(Y22:Y30)/COUNT(Y22:Y30) -> 0.27 | AA31: 7.8 | AJ31: 179700 | AU31: 0.3 | AV31: =SUM(AV22:AV30)/COUNT(AV22:AV30) -> 0.2
A32: B | B32: ARCHITECTURAL WORKS
B33: Ceiling Finish
B34: Ground Floor (Interior)
B35: HALLWAY, LIVING, DINING TO KITCHEN AREA | M35: 60.4
B36: Gypsum Board | C36: 88.72 | D36: =C36*$K$39 -> 97.592 | E36: sq.m | F36: ='Material and Labor Cost'!$D$8 -> 250 | G36: ='Material and Labor Cost'!$F$8 -> 350 | H36: =SUM(F36:G36) -> 600 | I36: =H36*D36 -> 58555.2 | M36: =C36/M35 -> 1.4688742 | Q36: =SUM(AA36:AH36) -> 48.796 | R36: =Y36*D36 -> 9.7592 | S36: =SUM(Q36:R36) -> 58.5552 | T36: =D36-S36 -> 39.0368 | U36: =SUM(AJ35:AQ35) -> 0 | V36: =Y36*I36 -> 5855.52 | W36: =SUM(U36:V36) -> 5855.52 | X36: =I36-W36 -> 52699.68 | Y36: =SUM(AS36) -> 0.1 | AA36: 48.796 | AJ36: 29277.6 | AS36: 0.1 | AU36: 0.5 | AV36: 0.4
B37: CARRYING channel | C37: =45*$M$36 -> 66.099338 | D37: =C37*$K$39 -> 72.709272 | E37: l.m | F37: ='Material and Labor Cost'!$D$9 -> 126.5 | G37: ='Material and Labor Cost'!$F$9 -> 70 | H37: =SUM(F37:G37) -> 196.5 | I37: =H37*D37 -> 14287.372 | N37: 85 | Q37: =SUM(AA37:AH37) -> 36.354636 | R37: =Y37*D37 -> 7.2709272 | S37: =SUM(Q37:R37) -> 43.625563 | T37: =D37-S37 -> 29.083709 | U37: =SUM(AJ36:AQ36) -> 29277.6 | V37: =Y37*I37 -> 1428.7372 | W37: =SUM(U37:V37) -> 30706.337 | X37: =I37-W37 -> -16418.965 | Y37: =SUM(AS37) -> 0.1 | AA37: 36.354636 | AJ37: 7143.6859 | AS37: 0.1 | AU37: 0.5 | AV37: 0.4
B38: Metal Furring | C38: =N37*$M$36 -> 124.8543 | D38: =C38*$K$39 -> 137.33974 | E38: l.m | F38: ='Material and Labor Cost'!$D$10 -> 126.5 | G38: ='Material and Labor Cost'!$F$10 -> 70 | H38: =SUM(F38:G38) -> 196.5 | I38: =H38*D38 -> 26987.258 | K38: Multiplier Mark up | N38: 30 | Q38: =SUM(AA38:AH38) -> 68.669868 | R38: =Y38*D38 -> 13.733974 | S38: =SUM(Q38:R38) -> 82.403841 | T38: =D38-S38 -> 54.935894 | U38: =SUM(AJ37:AQ37) -> 7143.6859 | V38: =Y38*I38 -> 2698.7258 | W38: =SUM(U38:V38) -> 9842.4117 | X38: =I38-W38 -> 17144.846 | Y38: =SUM(AS38) -> 0.1 | AA38: 68.669868 | AJ38: 13493.629 | AS38: 0.1 | AU38: 0.5 | AV38: 0.4
B39: Hanger clips | C39: =N38*$M$36 -> 44.066225 | D39: =ROUNDUP(C39*$K$39,0) -> 49 | E39: pcs | F39: ='Material and Labor Cost'!$D$11 -> 30 | G39: ='Material and Labor Cost'!$F$11 -> 20 | H39: =SUM(F39:G39) -> 50 | I39: =H39*D39 -> 2450 | K39: 1.1 | N39: 110 | Q39: =SUM(AA39:AH39) -> 24.5 | R39: =Y39*D39 -> 4.9 | S39: =SUM(Q39:R39) -> 29.4 | T39: =D39-S39 -> 19.6 | U39: =SUM(AJ38:AQ38) -> 13493.629 | V39: =Y39*I39 -> 245 | W39: =SUM(U39:V39) -> 13738.629 | X39: =I39-W39 -> -11288.629 | Y39: =SUM(AS39) -> 0.1 | AA39: 24.5 | AJ39: 1225 | AS39: 0.1 | AU39: 0.5 | AV39: 0.4
B40: W clips | C40: =N39*$M$36 -> 161.57616 | D40: =ROUNDUP(C40*$K$39,0) -> 178 | E40: pcs | F40: ='Material and Labor Cost'!$D$12 -> 10 | G40: ='Material and Labor Cost'!$F$12 -> 20 | H40: =SUM(F40:G40) -> 30 | I40: =H40*D40 -> 5340 | N40: 46.32 | Q40: =SUM(AA40:AH40) -> 89 | R40: =Y40*D40 -> 17.8 | S40: =SUM(Q40:R40) -> 106.8 | T40: =D40-S40 -> 71.2 | U40: =SUM(AJ39:AQ39) -> 1225 | V40: =Y40*I40 -> 534 | W40: =SUM(U40:V40) -> 1759 | X40: =I40-W40 -> 3581 | Y40: =SUM(AS40) -> 0.1 | AA40: 89 | AJ40: 2670 | AS40: 0.1 | AU40: 0.5 | AV40: 0.4
B41: Wall Angle | C41: =N40*$M$36 -> 68.038252 | D41: =ROUNDUP(C41*$K$39,0) -> 75 | E41: l.m | F41: ='Material and Labor Cost'!$D$13 -> 110 | G41: ='Material and Labor Cost'!$F$13 -> 60 | H41: =SUM(F41:G41) -> 170 | I41: =H41*D41 -> 12750 | Q41: =SUM(AA41:AH41) -> 37.5 | R41: =Y41*D41 -> 7.5 | S41: =SUM(Q41:R41) -> 45 | T41: =D41-S41 -> 30 | U41: =SUM(AJ40:AQ40) -> 2670 | V41: =Y41*I41 -> 1275 | W41: =SUM(U41:V41) -> 3945 | X41: =I41-W41 -> 8805 | Y41: =SUM(AS41) -> 0.1 | AA41: 37.5 | AJ41: 6375 | AS41: 0.1 | AU41: 0.5 | AV41: 0.4
K42: Miscellaneous
B43: POWDER ROOM
B44: Ficem Board | C44: 4 | D44: =C44*$K$39 -> 4.4 | E44: sq.m | F44: ='Material and Labor Cost'!$D$18 -> 250 | G44: ='Material and Labor Cost'!$F$18 -> 350 | H44: =SUM(F44:G44) -> 600 | I44: =H44*D44 -> 2640 | K44: 0.05 | Q44: =SUM(AA44:AH44) -> 1.32 | R44: =Y44*D44 -> 1.276 | S44: =SUM(Q44:R44) -> 2.596 | T44: =D44-S44 -> 1.804 | U44: =SUM(AJ43:AQ43) -> 0 | V44: =Y44*I44 -> 765.6 | W44: =SUM(U44:V44) -> 765.6 | X44: =I44-W44 -> 1874.4 | Y44: =SUM(AS44) -> 0.29 | AA44: 1.32 | AJ44: 792 | AS44: 0.29 | AU44: 0.3 | AV44: 0.4
B45: CARRYING channel | C45: 3.3333333 | D45: =C45*$K$39 -> 3.6666667 | E45: l.m | F45: ='Material and Labor Cost'!$D$9 -> 126.5 | G45: ='Material and Labor Cost'!$F$9 -> 70 | H45: =SUM(F45:G45) -> 196.5 | I45: =H45*D45 -> 720.5 | Q45: =SUM(AA45:AH45) -> 1.1 | R45: =Y45*D45 -> 1.0633333 | S45: =SUM(Q45:R45) -> 2.1633333 | T45: =D45-S45 -> 1.5033333 | U45: =SUM(AJ44:AQ44) -> 792 | V45: =Y45*I45 -> 208.945 | W45: =SUM(U45:V45) -> 1000.945 | X45: =I45-W45 -> -280.445 | Y45: =SUM(AS45) -> 0.29 | AA45: 1.1 | AJ45: 216.15 | AS45: 0.29 | AU45: 0.3 | AV45: 0.4
B46: Metal Furring | C46: 6.6666667 | D46: =C46*$K$39 -> 7.3333333 | E46: l.m | F46: ='Material and Labor Cost'!$D$10 -> 126.5 | G46: ='Material and Labor Cost'!$F$10 -> 70 | H46: =SUM(F46:G46) -> 196.5 | I46: =H46*D46 -> 1441 | Q46: =SUM(AA46:AH46) -> 2.2 | R46: =Y46*D46 -> 2.1266667 | S46: =SUM(Q46:R46) -> 4.3266667 | T46: =D46-S46 -> 3.0066667 | U46: =SUM(AJ45:AQ45) -> 216.15 | V46: =Y46*I46 -> 417.89 | W46: =SUM(U46:V46) -> 634.04 | X46: =I46-W46 -> 806.96 | Y46: =SUM(AS46) -> 0.29 | AA46: 2.2 | AJ46: 432.3 | AS46: 0.29 | AU46: 0.3 | AV46: 0.4
B47: Hanger clips | C47: 4 | D47: =ROUNDUP(C47*$K$39,0) -> 5 | E47: pcs | F47: ='Material and Labor Cost'!$D$11 -> 30 | G47: ='Material and Labor Cost'!$F$11 -> 20 | H47: =SUM(F47:G47) -> 50 | I47: =H47*D47 -> 250 | Q47: =SUM(AA47:AH47) -> 1.5 | R47: =Y47*D47 -> 1.45 | S47: =SUM(Q47:R47) -> 2.95 | T47: =D47-S47 -> 2.05 | U47: =SUM(AJ46:AQ46) -> 432.3 | V47: =Y47*I47 -> 72.5 | W47: =SUM(U47:V47) -> 504.8 | X47: =I47-W47 -> -254.8 | Y47: =SUM(AS47) -> 0.29 | AA47: 1.5 | AJ47: 75 | AS47: 0.29 | AU47: 0.3 | AV47: 0.4
B48: W clips | C48: 12 | D48: =ROUNDUP(C48*$K$39,0) -> 14 | E48: pcs | F48: ='Material and Labor Cost'!$D$12 -> 10 | G48: ='Material and Labor Cost'!$F$12 -> 20 | H48: =SUM(F48:G48) -> 30 | I48: =H48*D48 -> 420 | Q48: =SUM(AA48:AH48) -> 4.2 | R48: =Y48*D48 -> 4.06 | S48: =SUM(Q48:R48) -> 8.26 | T48: =D48-S48 -> 5.74 | U48: =SUM(AJ47:AQ47) -> 75 | V48: =Y48*I48 -> 121.8 | W48: =SUM(U48:V48) -> 196.8 | X48: =I48-W48 -> 223.2 | Y48: =SUM(AS48) -> 0.29 | AA48: 4.2 | AJ48: 126 | AS48: 0.29 | AU48: 0.3 | AV48: 0.4
B49: Wall Angle | C49: 7 | D49: =ROUNDUP(C49*$K$39,0) -> 8 | E49: l.m | F49: ='Material and Labor Cost'!$D$13 -> 110 | G49: ='Material and Labor Cost'!$F$13 -> 60 | H49: =SUM(F49:G49) -> 170 | I49: =H49*D49 -> 1360 | Q49: =SUM(AA49:AH49) -> 2.4 | R49: =Y49*D49 -> 2.32 | S49: =SUM(Q49:R49) -> 4.72 | T49: =D49-S49 -> 3.28 | U49: =SUM(AJ48:AQ48) -> 126 | V49: =Y49*I49 -> 394.4 | W49: =SUM(U49:V49) -> 520.4 | X49: =I49-W49 -> 839.6 | Y49: =SUM(AS49) -> 0.29 | AA49: 2.4 | AJ49: 408 | AS49: 0.29 | AU49: 0.3 | AV49: 0.4
B51: Paint flat finish | C51: =(C36+C44)*2 -> 185.44 | D51: =C51*$K$39 -> 203.984 | E51: sq.m | F51: ='Material and Labor Cost'!$D$14 -> 250 | G51: ='Material and Labor Cost'!$F$14 -> 350 | H51: =SUM(F51:G51) -> 600 | I51: =H51*D51 -> 122390.4 | Q51: =SUM(AA51:AH51) -> 61.1952 | R51: =Y51*D51 -> 59.15536 | S51: =SUM(Q51:R51) -> 120.35056 | T51: =D51-S51 -> 83.63344 | U51: =SUM(AJ50:AQ50) -> 0 | V51: =Y51*I51 -> 35493.216 | W51: =SUM(U51:V51) -> 35493.216 | X51: =I51-W51 -> 86897.184 | Y51: =SUM(AS51) -> 0.29 | AA51: 61.1952 | AJ51: 36717.12 | AS51: 0.29 | AU51: 0.3 | AV51: 0.4
B53: Ground Floor (Exterior)
B54: PVC ceiling Panel | C54: 39 | D54: =C54*$K$39 -> 42.9 | E54: sq.m | F54: ='Material and Labor Cost'!$D$15 -> 250 | G54: ='Material and Labor Cost'!$F$15 -> 350 | H54: =SUM(F54:G54) -> 600 | I54: =H54*D54 -> 25740 | M54: 39 | N54: 24.5 | Q54: =SUM(AA54:AH54) -> 21.45 | R54: =Y54*D54 -> 3.861 | S54: =SUM(Q54:R54) -> 25.311 | T54: =D54-S54 -> 17.589 | U54: =SUM(AJ53:AQ53) -> 0 | V54: =Y54*I54 -> 2316.6 | W54: =SUM(U54:V54) -> 2316.6 | X54: =I54-W54 -> 23423.4 | Y54: =SUM(AS54) -> 0.09 | AA54: 21.45 | AJ54: 12870 | AS54: 0.09 | AU54: 0.5 | AV54: 0.4
B55: CARRYING channel | C55: =N55*$M$55 -> 44.770408 | D55: =C55*$K$39 -> 49.247449 | E55: l.m | F55: ='Material and Labor Cost'!$D$9 -> 126.5 | G55: ='Material and Labor Cost'!$F$9 -> 70 | H55: =SUM(F55:G55) -> 196.5 | I55: =H55*D55 -> 9677.1237 | M55: =M54/N54 -> 1.5918367 | N55: 28.125 | Q55: =SUM(AA55:AH55) -> 24.623724 | R55: =Y55*D55 -> 4.4322704 | S55: =SUM(Q55:R55) -> 29.055995 | T55: =D55-S55 -> 20.191454 | U55: =SUM(AJ54:AQ54) -> 12870 | V55: =Y55*I55 -> 870.94114 | W55: =SUM(U55:V55) -> 13740.941 | X55: =I55-W55 -> -4063.8174 | Y55: =SUM(AS55) -> 0.09 | AA55: 24.623724 | AJ55: 4838.5619 | AS55: 0.09 | AU55: 0.5 | AV55: 0.4
B56: Metal Furring | C56: =N56*$M$55 -> 72.136735 | D56: =C56*$K$39 -> 79.350408 | E56: l.m | F56: ='Material and Labor Cost'!$D$10 -> 126.5 | G56: ='Material and Labor Cost'!$F$10 -> 70 | H56: =SUM(F56:G56) -> 196.5 | I56: =H56*D56 -> 15592.355 | N56: 45.316667 | Q56: =SUM(AA56:AH56) -> 39.675204 | R56: =Y56*D56 -> 7.1415367 | S56: =SUM(Q56:R56) -> 46.816741 | T56: =D56-S56 -> 32.533667 | U56: =SUM(AJ55:AQ55) -> 4838.5619 | V56: =Y56*I56 -> 1403.312 | W56: =SUM(U56:V56) -> 6241.8738 | X56: =I56-W56 -> 9350.4814 | Y56: =SUM(AS56) -> 0.09 | AA56: 39.675204 | AJ56: 7796.1776 | AS56: 0.09 | AU56: 0.5 | AV56: 0.4
B57: Hanger clips | C57: =N57*$M$55 -> 14.326531 | D57: =ROUNDUP(C57*$K$39,0) -> 16 | E57: pcs | F57: ='Material and Labor Cost'!$D$11 -> 30 | G57: ='Material and Labor Cost'!$F$11 -> 20 | H57: =SUM(F57:G57) -> 50 | I57: =H57*D57 -> 800 | N57: 9 | Q57: =SUM(AA57:AH57) -> 8 | R57: =Y57*D57 -> 1.44 | S57: =SUM(Q57:R57) -> 9.44 | T57: =D57-S57 -> 6.56 | U57: =SUM(AJ56:AQ56) -> 7796.1776 | V57: =Y57*I57 -> 72 | W57: =SUM(U57:V57) -> 7868.1776 | X57: =I57-W57 -> -7068.1776 | Y57: =SUM(AS57) -> 0.09 | AA57: 8 | AJ57: 400 | AS57: 0.09 | AU57: 0.5 | AV57: 0.4
B58: W clips | C58: =N58*$M$55 -> 216.4898 | D58: =ROUNDUP(C58*$K$39,0) -> 239 | E58: pcs | F58: ='Material and Labor Cost'!$D$12 -> 10 | G58: ='Material and Labor Cost'!$F$12 -> 20 | H58: =SUM(F58:G58) -> 30 | I58: =H58*D58 -> 7170 | N58: 136 | Q58: =SUM(AA58:AH58) -> 119.5 | R58: =Y58*D58 -> 21.51 | S58: =SUM(Q58:R58) -> 141.01 | T58: =D58-S58 -> 97.99 | U58: =SUM(AJ57:AQ57) -> 400 | V58: =Y58*I58 -> 645.3 | W58: =SUM(U58:V58) -> 1045.3 | X58: =I58-W58 -> 6124.7 | Y58: =SUM(AS58) -> 0.09 | AA58: 119.5 | AJ58: 3585 | AS58: 0.09 | AU58: 0.5 | AV58: 0.4
B59: H CLIP | C59: =N59*$M$55 -> 2.0057143 | D59: =C59*$K$39 -> 2.2062857 | E59: l.m | F59: ='Material and Labor Cost'!$D$16 -> 110 | G59: ='Material and Labor Cost'!$F$16 -> 20 | H59: =SUM(F59:G59) -> 130 | I59: =H59*D59 -> 286.81714 | N59: 1.26 | Q59: =SUM(AA59:AH59) -> 1.1031429 | R59: =Y59*D59 -> 0.19856571 | S59: =SUM(Q59:R59) -> 1.3017086 | T59: =D59-S59 -> 0.90457714 | U59: =SUM(AJ58:AQ58) -> 3585 | V59: =Y59*I59 -> 25.813543 | W59: =SUM(U59:V59) -> 3610.8135 | X59: =I59-W59 -> -3323.9964 | Y59: =SUM(AS59) -> 0.09 | AA59: 1.1031429 | AJ59: 143.40857 | AS59: 0.09 | AU59: 0.5 | AV59: 0.4
B60: edging | C60: =N60*$M$55 -> 77.044898 | D60: =C60*$K$39 -> 84.749388 | E60: l.m | F60: ='Material and Labor Cost'!$D$17 -> 110 | G60: ='Material and Labor Cost'!$F$17 -> 20 | H60: =SUM(F60:G60) -> 130 | I60: =H60*D60 -> 11017.42 | N60: 48.4 | Q60: =SUM(AA60:AH60) -> 42.374694 | R60: =Y60*D60 -> 7.6274449 | S60: =SUM(Q60:R60) -> 50.002139 | T60: =D60-S60 -> 34.747249 | U60: =SUM(AJ59:AQ59) -> 143.40857 | V60: =Y60*I60 -> 991.56784 | W60: =SUM(U60:V60) -> 1134.9764 | X60: =I60-W60 -> 9882.444 | Y60: =SUM(AS60) -> 0.09 | AA60: 42.374694 | AJ60: 5508.7102 | AS60: 0.09 | AU60: 0.5 | AV60: 0.4
B62: Miscellaneous and other consumables | D62: 1 | E62: lot | I62: =SUM(I35:I60)*$K$44 -> 15993.772 | Q62: =SUM(AA62:AH62) -> 0.5 | R62: =Y62*D62 -> 0.1 | S62: =SUM(Q62:R62) -> 0.6 | T62: =D62-S62 -> 0.4 | U62: =SUM(AJ61:AQ61) -> 0 | V62: =Y62*I62 -> 1599.3772 | W62: =SUM(U62:V62) -> 1599.3772 | X62: =I62-W62 -> 14394.395 | Y62: =SUM(AS62) -> 0.1 | AA62: 0.5 | AJ62: 7996.8862 | AS62: 0.1 | AU62: 0.5 | AV62: 0.4
B63: Ground Floor Ceiling Sub-total: | I63: =SUM(I36:I62) -> 335869.22 | Q63: =SUM(Q36:Q62) -> 635.96247 | R63: =SUM(R36:R62) -> 178.72628 | S63: =SUM(S36:S62) -> 814.68875 | T63: =SUM(T36:T62) -> 555.78979 | U63: =SUM(U36:U62) -> 85084.513 | V63: =SUM(V36:V62) -> 57436.246 | W63: =SUM(W36:W62) -> 142520.76 | X63: =SUM(X36:X62) -> 193348.46 | Y63: =SUM(Y36:Y62)/COUNT(Y36:Y62) -> 0.16 | AA63: 635.96247 | AJ63: 142090.23 | AU63: =SUM(AU36:AU62)/COUNT(AU36:AU62) -> 0.43333333 | AV63: =SUM(AV36:AV62)/COUNT(AV36:AV62) -> 0.4
B64: Second Floor (Interior)
B65: BEDROOM 1
B66: Gypsum Board | C66: 12.7 | D66: =C66*$K$39 -> 13.97 | E66: sq.m | F66: ='Material and Labor Cost'!$D$8 -> 250 | G66: ='Material and Labor Cost'!$F$8 -> 350 | H66: =SUM(F66:G66) -> 600 | I66: =H66*D66 -> 8382 | Q66: =SUM(AA66:AH66) -> 9.2202 | R66: =Y66*D66 -> 0 | S66: =SUM(Q66:R66) -> 9.2202 | T66: =D66-S66 -> 4.7498 | U66: =SUM(AJ65:AQ65) -> 0 | V66: =Y66*I66 -> 0 | W66: =SUM(U66:V66) -> 0 | X66: =I66-W66 -> 8382 | Y66: =SUM(AS66) -> 0 | AA66: 9.2202 | AJ66: 5532.12 | AS66: 0 | AU66: 0.66 | AV66: 0.4
B67: CARRYING channel | C67: 10.53 | D67: =C67*$K$39 -> 11.583 | E67: l.m | F67: ='Material and Labor Cost'!$D$9 -> 126.5 | G67: ='Material and Labor Cost'!$F$9 -> 70 | H67: =SUM(F67:G67) -> 196.5 | I67: =H67*D67 -> 2276.0595 | Q67: =SUM(AA67:AH67) -> 7.64478 | R67: =Y67*D67 -> 0 | S67: =SUM(Q67:R67) -> 7.64478 | T67: =D67-S67 -> 3.93822 | U67: =SUM(AJ66:AQ66) -> 5532.12 | V67: =Y67*I67 -> 0 | W67: =SUM(U67:V67) -> 5532.12 | X67: =I67-W67 -> -3256.0605 | Y67: =SUM(AS67) -> 0 | AA67: 7.64478 | AJ67: 1502.1993 | AS67: 0 | AU67: 0.66 | AV67: 0.4
B68: Metal Furring | C68: 21.06 | D68: =C68*$K$39 -> 23.166 | E68: l.m | F68: ='Material and Labor Cost'!$D$10 -> 126.5 | G68: ='Material and Labor Cost'!$F$10 -> 70 | H68: =SUM(F68:G68) -> 196.5 | I68: =H68*D68 -> 4552.119 | Q68: =SUM(AA68:AH68) -> 15.28956 | R68: =Y68*D68 -> 0 | S68: =SUM(Q68:R68) -> 15.28956 | T68: =D68-S68 -> 7.87644 | U68: =SUM(AJ67:AQ67) -> 1502.1993 | V68: =Y68*I68 -> 0 | W68: =SUM(U68:V68) -> 1502.1993 | X68: =I68-W68 -> 3049.9197 | Y68: =SUM(AS68) -> 0 | AA68: 15.28956 | AJ68: 3004.3985 | AS68: 0 | AU68: 0.66 | AV68: 0.4
B69: Hanger clips | C69: 6 | D69: =ROUNDUP(C69*$K$39,0) -> 7 | E69: pcs | F69: ='Material and Labor Cost'!$D$11 -> 30 | G69: ='Material and Labor Cost'!$F$11 -> 20 | H69: =SUM(F69:G69) -> 50 | I69: =H69*D69 -> 350 | Q69: =SUM(AA69:AH69) -> 4.62 | R69: =Y69*D69 -> 0 | S69: =SUM(Q69:R69) -> 4.62 | T69: =D69-S69 -> 2.38 | U69: =SUM(AJ68:AQ68) -> 3004.3985 | V69: =Y69*I69 -> 0 | W69: =SUM(U69:V69) -> 3004.3985 | X69: =I69-W69 -> -2654.3985 | Y69: =SUM(AS69) -> 0 | AA69: 4.62 | AJ69: 231 | AS69: 0 | AU69: 0.66 | AV69: 0.4
B70: W clips | C70: 28 | D70: =ROUNDUP(C70*$K$39,0) -> 31 | E70: pcs | F70: ='Material and Labor Cost'!$D$12 -> 10 | G70: ='Material and Labor Cost'!$F$12 -> 20 | H70: =SUM(F70:G70) -> 30 | I70: =H70*D70 -> 930 | Q70: =SUM(AA70:AH70) -> 20.46 | R70: =Y70*D70 -> 0 | S70: =SUM(Q70:R70) -> 20.46 | T70: =D70-S70 -> 10.54 | U70: =SUM(AJ69:AQ69) -> 231 | V70: =Y70*I70 -> 0 | W70: =SUM(U70:V70) -> 231 | X70: =I70-W70 -> 699 | Y70: =SUM(AS70) -> 0 | AA70: 20.46 | AJ70: 613.8 | AS70: 0 | AU70: 0.66 | AV70: 0.4
B71: Wall Angle | C71: 14.2 | D71: =ROUNDUP(C71*$K$39,0) -> 16 | E71: l.m | F71: ='Material and Labor Cost'!$D$13 -> 110 | G71: ='Material and Labor Cost'!$F$13 -> 60 | H71: =SUM(F71:G71) -> 170 | I71: =H71*D71 -> 2720 | Q71: =SUM(AA71:AH71) -> 10.56 | R71: =Y71*D71 -> 0 | S71: =SUM(Q71:R71) -> 10.56 | T71: =D71-S71 -> 5.44 | U71: =SUM(AJ70:AQ70) -> 613.8 | V71: =Y71*I71 -> 0 | W71: =SUM(U71:V71) -> 613.8 | X71: =I71-W71 -> 2106.2 | Y71: =SUM(AS71) -> 0 | AA71: 10.56 | AJ71: 1795.2 | AS71: 0 | AU71: 0.66 | AV71: 0.4
B72: Paint flat finish | C72: =C66*2 -> 25.4 | D72: =C72*$K$39 -> 27.94 | E72: sq.m | F72: ='Material and Labor Cost'!$D$14 -> 250 | G72: ='Material and Labor Cost'!$F$14 -> 350 | H72: =SUM(F72:G72) -> 600 | I72: =H72*D72 -> 16764 | Q72: =SUM(AA72:AH72) -> 18.4404 | R72: =Y72*D72 -> 0 | S72: =SUM(Q72:R72) -> 18.4404 | T72: =D72-S72 -> 9.4996 | U72: =SUM(AJ71:AQ71) -> 1795.2 | V72: =Y72*I72 -> 0 | W72: =SUM(U72:V72) -> 1795.2 | X72: =I72-W72 -> 14968.8 | Y72: =SUM(AS72) -> 0 | AA72: 18.4404 | AJ72: 11064.24 | AS72: 0 | AU72: 0.66 | AV72: 0.4
B74: BEDROOM 2
B75: Gypsum Board | C75: 14.8 | D75: =C75*$K$39 -> 16.28 | E75: sq.m | F75: ='Material and Labor Cost'!$D$8 -> 250 | G75: ='Material and Labor Cost'!$F$8 -> 350 | H75: =SUM(F75:G75) -> 600 | I75: =H75*D75 -> 9768 | Q75: =SUM(AA75:AH75) -> 8.14 | R75: =Y75*D75 -> 1.628 | S75: =SUM(Q75:R75) -> 9.768 | T75: =D75-S75 -> 6.512 | U75: =SUM(AJ74:AQ74) -> 0 | V75: =Y75*I75 -> 976.8 | W75: =SUM(U75:V75) -> 976.8 | X75: =I75-W75 -> 8791.2 | Y75: =SUM(AS75) -> 0.1 | AA75: 8.14 | AJ75: 4884 | AS75: 0.1 | AU75: 0.5 | AV75: 0.4
B76: CARRYING channel | C76: 12.36 | D76: =C76*$K$39 -> 13.596 | E76: l.m | F76: ='Material and Labor Cost'!$D$9 -> 126.5 | G76: ='Material and Labor Cost'!$F$9 -> 70 | H76: =SUM(F76:G76) -> 196.5 | I76: =H76*D76 -> 2671.614 | Q76: =SUM(AA76:AH76) -> 6.798 | R76: =Y76*D76 -> 1.3596 | S76: =SUM(Q76:R76) -> 8.1576 | T76: =D76-S76 -> 5.4384 | U76: =SUM(AJ75:AQ75) -> 4884 | V76: =Y76*I76 -> 267.1614 | W76: =SUM(U76:V76) -> 5151.1614 | X76: =I76-W76 -> -2479.5474 | Y76: =SUM(AS76) -> 0.1 | AA76: 6.798 | AJ76: 1335.807 | AS76: 0.1 | AU76: 0.5 | AV76: 0.4
B77: Metal Furring | C77: 24.72 | D77: =C77*$K$39 -> 27.192 | E77: l.m | F77: ='Material and Labor Cost'!$D$10 -> 126.5 | G77: ='Material and Labor Cost'!$F$10 -> 70 | H77: =SUM(F77:G77) -> 196.5 | I77: =H77*D77 -> 5343.228 | Q77: =SUM(AA77:AH77) -> 13.596 | R77: =Y77*D77 -> 2.7192 | S77: =SUM(Q77:R77) -> 16.3152 | T77: =D77-S77 -> 10.8768 | U77: =SUM(AJ76:AQ76) -> 1335.807 | V77: =Y77*I77 -> 534.3228 | W77: =SUM(U77:V77) -> 1870.1298 | X77: =I77-W77 -> 3473.0982 | Y77: =SUM(AS77) -> 0.1 | AA77: 13.596 | AJ77: 2671.614 | AS77: 0.1 | AU77: 0.5 | AV77: 0.4
B78: Hanger clips | C78: 7 | D78: =ROUNDUP(C78*$K$39,0) -> 8 | E78: pcs | F78: ='Material and Labor Cost'!$D$11 -> 30 | G78: ='Material and Labor Cost'!$F$11 -> 20 | H78: =SUM(F78:G78) -> 50 | I78: =H78*D78 -> 400 | Q78: =SUM(AA78:AH78) -> 4 | R78: =Y78*D78 -> 0.8 | S78: =SUM(Q78:R78) -> 4.8 | T78: =D78-S78 -> 3.2 | U78: =SUM(AJ77:AQ77) -> 2671.614 | V78: =Y78*I78 -> 40 | W78: =SUM(U78:V78) -> 2711.614 | X78: =I78-W78 -> -2311.614 | Y78: =SUM(AS78) -> 0.1 | AA78: 4 | AJ78: 200 | AS78: 0.1 | AU78: 0.5 | AV78: 0.4
B79: W clips | C79: 32 | D79: =ROUNDUP(C79*$K$39,0) -> 36 | E79: pcs | F79: ='Material and Labor Cost'!$D$12 -> 10 | G79: ='Material and Labor Cost'!$F$12 -> 20 | H79: =SUM(F79:G79) -> 30 | I79: =H79*D79 -> 1080 | Q79: =SUM(AA79:AH79) -> 18 | R79: =Y79*D79 -> 3.6 | S79: =SUM(Q79:R79) -> 21.6 | T79: =D79-S79 -> 14.4 | U79: =SUM(AJ78:AQ78) -> 200 | V79: =Y79*I79 -> 108 | W79: =SUM(U79:V79) -> 308 | X79: =I79-W79 -> 772 | Y79: =SUM(AS79) -> 0.1 | AA79: 18 | AJ79: 540 | AS79: 0.1 | AU79: 0.5 | AV79: 0.4
B80: Wall Angle | C80: 15.2 | D80: =ROUNDUP(C80*$K$39,0) -> 17 | E80: l.m | F80: ='Material and Labor Cost'!$D$13 -> 110 | G80: ='Material and Labor Cost'!$F$13 -> 60 | H80: =SUM(F80:G80) -> 170 | I80: =H80*D80 -> 2890 | Q80: =SUM(AA80:AH80) -> 8.5 | R80: =Y80*D80 -> 1.7 | S80: =SUM(Q80:R80) -> 10.2 | T80: =D80-S80 -> 6.8 | U80: =SUM(AJ79:AQ79) -> 540 | V80: =Y80*I80 -> 289 | W80: =SUM(U80:V80) -> 829 | X80: =I80-W80 -> 2061 | Y80: =SUM(AS80) -> 0.1 | AA80: 8.5 | AJ80: 1445 | AS80: 0.1 | AU80: 0.5 | AV80: 0.4
B82: Ficem Board ( T&B ) | C82: 3.8 | D82: =C82*$K$39 -> 4.18 | E82: sq.m | F82: ='Material and Labor Cost'!$D$18 -> 250 | G82: ='Material and Labor Cost'!$F$18 -> 350 | H82: =SUM(F82:G82) -> 600 | I82: =H82*D82 -> 2508 | Q82: =SUM(AA82:AH82) -> 2.09 | R82: =Y82*D82 -> 0.836 | S82: =SUM(Q82:R82) -> 2.926 | T82: =D82-S82 -> 1.254 | U82: =SUM(AJ81:AQ81) -> 0 | V82: =Y82*I82 -> 501.6 | W82: =SUM(U82:V82) -> 501.6 | X82: =I82-W82 -> 2006.4 | Y82: =SUM(AS82) -> 0.2 | AA82: 2.09 | AJ82: 1254 | AS82: 0.2 | AU82: 0.5 | AV82: 0.3
B83: CARRYING channel | C83: 3.1995 | D83: =C83*$K$39 -> 3.51945 | E83: l.m | F83: ='Material and Labor Cost'!$D$9 -> 126.5 | G83: ='Material and Labor Cost'!$F$9 -> 70 | H83: =SUM(F83:G83) -> 196.5 | I83: =H83*D83 -> 691.57193 | Q83: =SUM(AA83:AH83) -> 1.759725 | R83: =Y83*D83 -> 0.70389 | S83: =SUM(Q83:R83) -> 2.463615 | T83: =D83-S83 -> 1.055835 | U83: =SUM(AJ82:AQ82) -> 1254 | V83: =Y83*I83 -> 138.31439 | W83: =SUM(U83:V83) -> 1392.3144 | X83: =I83-W83 -> -700.74246 | Y83: =SUM(AS83) -> 0.2 | AA83: 1.759725 | AJ83: 345.78596 | AS83: 0.2 | AU83: 0.5 | AV83: 0.3
B84: Metal Furring | C84: 6.399 | D84: =C84*$K$39 -> 7.0389 | E84: l.m | F84: ='Material and Labor Cost'!$D$10 -> 126.5 | G84: ='Material and Labor Cost'!$F$10 -> 70 | H84: =SUM(F84:G84) -> 196.5 | I84: =H84*D84 -> 1383.1439 | Q84: =SUM(AA84:AH84) -> 3.51945 | R84: =Y84*D84 -> 1.40778 | S84: =SUM(Q84:R84) -> 4.92723 | T84: =D84-S84 -> 2.11167 | U84: =SUM(AJ83:AQ83) -> 345.78596 | V84: =Y84*I84 -> 276.62877 | W84: =SUM(U84:V84) -> 622.41473 | X84: =I84-W84 -> 760.72912 | Y84: =SUM(AS84) -> 0.2 | AA84: 3.51945 | AJ84: 691.57193 | AS84: 0.2 | AU84: 0.5 | AV84: 0.3
B85: Hanger clips | C85: 5 | D85: =ROUNDUP(C85*$K$39,0) -> 6 | E85: pcs | F85: ='Material and Labor Cost'!$D$11 -> 30 | G85: ='Material and Labor Cost'!$F$11 -> 20 | H85: =SUM(F85:G85) -> 50 | I85: =H85*D85 -> 300 | Q85: =SUM(AA85:AH85) -> 3 | R85: =Y85*D85 -> 1.2 | S85: =SUM(Q85:R85) -> 4.2 | T85: =D85-S85 -> 1.8 | U85: =SUM(AJ84:AQ84) -> 691.57193 | V85: =Y85*I85 -> 60 | W85: =SUM(U85:V85) -> 751.57193 | X85: =I85-W85 -> -451.57193 | Y85: =SUM(AS85) -> 0.2 | AA85: 3 | AJ85: 150 | AS85: 0.2 | AU85: 0.5 | AV85: 0.3
B86: W clips | C86: 12 | D86: =ROUNDUP(C86*$K$39,0) -> 14 | E86: pcs | F86: ='Material and Labor Cost'!$D$12 -> 10 | G86: ='Material and Labor Cost'!$F$12 -> 20 | H86: =SUM(F86:G86) -> 30 | I86: =H86*D86 -> 420 | Q86: =SUM(AA86:AH86) -> 7 | R86: =Y86*D86 -> 2.8 | S86: =SUM(Q86:R86) -> 9.8 | T86: =D86-S86 -> 4.2 | U86: =SUM(AJ85:AQ85) -> 150 | V86: =Y86*I86 -> 84 | W86: =SUM(U86:V86) -> 234 | X86: =I86-W86 -> 186 | Y86: =SUM(AS86) -> 0.2 | AA86: 7 | AJ86: 210 | AS86: 0.2 | AU86: 0.5 | AV86: 0.3
B87: Wall Angle | C87: 8 | D87: =ROUNDUP(C87*$K$39,0) -> 9 | E87: l.m | F87: ='Material and Labor Cost'!$D$13 -> 110 | G87: ='Material and Labor Cost'!$F$13 -> 60 | H87: =SUM(F87:G87) -> 170 | I87: =H87*D87 -> 1530 | Q87: =SUM(AA87:AH87) -> 4.5 | R87: =Y87*D87 -> 1.8 | S87: =SUM(Q87:R87) -> 6.3 | T87: =D87-S87 -> 2.7 | U87: =SUM(AJ86:AQ86) -> 210 | V87: =Y87*I87 -> 306 | W87: =SUM(U87:V87) -> 516 | X87: =I87-W87 -> 1014 | Y87: =SUM(AS87) -> 0.2 | AA87: 4.5 | AJ87: 765 | AS87: 0.2 | AU87: 0.5 | AV87: 0.3
B88: Paint flat finish | C88: =SUM(C75,C82)*2 -> 37.2 | D88: =C88*$K$39 -> 40.92 | E88: sq.m | F88: ='Material and Labor Cost'!$D$14 -> 250 | G88: ='Material and Labor Cost'!$F$14 -> 350 | H88: =SUM(F88:G88) -> 600 | I88: =H88*D88 -> 24552 | Q88: =SUM(AA88:AH88) -> 20.46 | R88: =Y88*D88 -> 8.184 | S88: =SUM(Q88:R88) -> 28.644 | T88: =D88-S88 -> 12.276 | U88: =SUM(AJ87:AQ87) -> 765 | V88: =Y88*I88 -> 4910.4 | W88: =SUM(U88:V88) -> 5675.4 | X88: =I88-W88 -> 18876.6 | Y88: =SUM(AS88) -> 0.2 | AA88: 20.46 | AJ88: 12276 | AS88: 0.2 | AU88: 0.5 | AV88: 0.3
B90: BEDROOM 3
B91: Gypsum Board | C91: 15.5 | D91: =C91*$K$39 -> 17.05 | E91: sq.m | F91: ='Material and Labor Cost'!$D$8 -> 250 | G91: ='Material and Labor Cost'!$F$8 -> 350 | H91: =SUM(F91:G91) -> 600 | I91: =H91*D91 -> 10230 | Q91: =SUM(AA91:AH91) -> 8.525 | R91: =Y91*D91 -> 2.5575 | S91: =SUM(Q91:R91) -> 11.0825 | T91: =D91-S91 -> 5.9675 | U91: =SUM(AJ90:AQ90) -> 0 | V91: =Y91*I91 -> 1534.5 | W91: =SUM(U91:V91) -> 1534.5 | X91: =I91-W91 -> 8695.5 | Y91: =SUM(AS91) -> 0.15 | AA91: 8.525 | AJ91: 5115 | AS91: 0.15 | AU91: 0.5 | AV91: 0.35
B92: CARRYING channel | C92: 12.972 | D92: =C92*$K$39 -> 14.2692 | E92: l.m | F92: ='Material and Labor Cost'!$D$9 -> 126.5 | G92: ='Material and Labor Cost'!$F$9 -> 70 | H92: =SUM(F92:G92) -> 196.5 | I92: =H92*D92 -> 2803.8978 | Q92: =SUM(AA92:AH92) -> 7.1346 | R92: =Y92*D92 -> 2.14038 | S92: =SUM(Q92:R92) -> 9.27498 | T92: =D92-S92 -> 4.99422 | U92: =SUM(AJ91:AQ91) -> 5115 | V92: =Y92*I92 -> 420.58467 | W92: =SUM(U92:V92) -> 5535.5847 | X92: =I92-W92 -> -2731.6869 | Y92: =SUM(AS92) -> 0.15 | AA92: 7.1346 | AJ92: 1401.9489 | AS92: 0.15 | AU92: 0.5 | AV92: 0.35
B93: Metal Furring | C93: 25.944 | D93: =C93*$K$39 -> 28.5384 | E93: l.m | F93: ='Material and Labor Cost'!$D$10 -> 126.5 | G93: ='Material and Labor Cost'!$F$10 -> 70 | H93: =SUM(F93:G93) -> 196.5 | I93: =H93*D93 -> 5607.7956 | Q93: =SUM(AA93:AH93) -> 14.2692 | R93: =Y93*D93 -> 4.28076 | S93: =SUM(Q93:R93) -> 18.54996 | T93: =D93-S93 -> 9.98844 | U93: =SUM(AJ92:AQ92) -> 1401.9489 | V93: =Y93*I93 -> 841.16934 | W93: =SUM(U93:V93) -> 2243.1182 | X93: =I93-W93 -> 3364.6774 | Y93: =SUM(AS93) -> 0.15 | AA93: 14.2692 | AJ93: 2803.8978 | AS93: 0.15 | AU93: 0.5 | AV93: 0.35
B94: Hanger clips | C94: 7 | D94: =ROUNDUP(C94*$K$39,0) -> 8 | E94: pcs | F94: ='Material and Labor Cost'!$D$11 -> 30 | G94: ='Material and Labor Cost'!$F$11 -> 20 | H94: =SUM(F94:G94) -> 50 | I94: =H94*D94 -> 400 | Q94: =SUM(AA94:AH94) -> 4 | R94: =Y94*D94 -> 1.2 | S94: =SUM(Q94:R94) -> 5.2 | T94: =D94-S94 -> 2.8 | U94: =SUM(AJ93:AQ93) -> 2803.8978 | V94: =Y94*I94 -> 60 | W94: =SUM(U94:V94) -> 2863.8978 | X94: =I94-W94 -> -2463.8978 | Y94: =SUM(AS94) -> 0.15 | AA94: 4 | AJ94: 200 | AS94: 0.15 | AU94: 0.5 | AV94: 0.35
B95: W clips | C95: 33 | D95: =ROUNDUP(C95*$K$39,0) -> 37 | E95: pcs | F95: ='Material and Labor Cost'!$D$12 -> 10 | G95: ='Material and Labor Cost'!$F$12 -> 20 | H95: =SUM(F95:G95) -> 30 | I95: =H95*D95 -> 1110 | Q95: =SUM(AA95:AH95) -> 18.5 | R95: =Y95*D95 -> 5.55 | S95: =SUM(Q95:R95) -> 24.05 | T95: =D95-S95 -> 12.95 | U95: =SUM(AJ94:AQ94) -> 200 | V95: =Y95*I95 -> 166.5 | W95: =SUM(U95:V95) -> 366.5 | X95: =I95-W95 -> 743.5 | Y95: =SUM(AS95) -> 0.15 | AA95: 18.5 | AJ95: 555 | AS95: 0.15 | AU95: 0.5 | AV95: 0.35
B96: Wall Angle | C96: 15.8 | D96: =ROUNDUP(C96*$K$39,0) -> 18 | E96: l.m | F96: ='Material and Labor Cost'!$D$13 -> 110 | G96: ='Material and Labor Cost'!$F$13 -> 60 | H96: =SUM(F96:G96) -> 170 | I96: =H96*D96 -> 3060 | Q96: =SUM(AA96:AH96) -> 9 | R96: =Y96*D96 -> 2.7 | S96: =SUM(Q96:R96) -> 11.7 | T96: =D96-S96 -> 6.3 | U96: =SUM(AJ95:AQ95) -> 555 | V96: =Y96*I96 -> 459 | W96: =SUM(U96:V96) -> 1014 | X96: =I96-W96 -> 2046 | Y96: =SUM(AS96) -> 0.15 | AA96: 9 | AJ96: 1530 | AS96: 0.15 | AU96: 0.5 | AV96: 0.35
B97: Paint flat finish | C97: =C91*2 -> 31 | D97: =C97*$K$39 -> 34.1 | E97: sq.m | F97: ='Material and Labor Cost'!$D$14 -> 250 | G97: ='Material and Labor Cost'!$F$14 -> 350 | H97: =SUM(F97:G97) -> 600 | I97: =H97*D97 -> 20460 | Q97: =SUM(AA97:AH97) -> 17.05 | R97: =Y97*D97 -> 5.115 | S97: =SUM(Q97:R97) -> 22.165 | T97: =D97-S97 -> 11.935 | U97: =SUM(AJ96:AQ96) -> 1530 | V97: =Y97*I97 -> 3069 | W97: =SUM(U97:V97) -> 4599 | X97: =I97-W97 -> 15861 | Y97: =SUM(AS97) -> 0.15 | AA97: 17.05 | AJ97: 10230 | AS97: 0.15 | AU97: 0.5 | AV97: 0.35
B99: BEDROOM 4
B100: Gypsum Board | C100: 14.1 | D100: =C100*$K$39 -> 15.51 | E100: sq.m | F100: ='Material and Labor Cost'!$D$8 -> 250 | G100: ='Material and Labor Cost'!$F$8 -> 350 | H100: =SUM(F100:G100) -> 600 | I100: =H100*D100 -> 9306 | Q100: =SUM(AA100:AH100) -> 7.755 | R100: =Y100*D100 -> 1.551 | S100: =SUM(Q100:R100) -> 9.306 | T100: =D100-S100 -> 6.204 | U100: =SUM(AJ99:AQ99) -> 0 | V100: =Y100*I100 -> 930.6 | W100: =SUM(U100:V100) -> 930.6 | X100: =I100-W100 -> 8375.4 | Y100: =SUM(AS100) -> 0.1 | AA100: 7.755 | AJ100: 4653 | AS100: 0.1 | AU100: 0.5 | AV100: 0.4
B101: CARRYING channel | C101: 12.213 | D101: =C101*$K$39 -> 13.4343 | E101: l.m | F101: ='Material and Labor Cost'!$D$9 -> 126.5 | G101: ='Material and Labor Cost'!$F$9 -> 70 | H101: =SUM(F101:G101) -> 196.5 | I101: =H101*D101 -> 2639.84 | Q101: =SUM(AA101:AH101) -> 6.71715 | R101: =Y101*D101 -> 1.34343 | S101: =SUM(Q101:R101) -> 8.06058 | T101: =D101-S101 -> 5.37372 | U101: =SUM(AJ100:AQ100) -> 4653 | V101: =Y101*I101 -> 263.98399 | W101: =SUM(U101:V101) -> 4916.984 | X101: =I101-W101 -> -2277.144 | Y101: =SUM(AS101) -> 0.1 | AA101: 6.71715 | AJ101: 1319.92 | AS101: 0.1 | AU101: 0.5 | AV101: 0.4
B102: Metal Furring | C102: 24.426 | D102: =C102*$K$39 -> 26.8686 | E102: l.m | F102: ='Material and Labor Cost'!$D$10 -> 126.5 | G102: ='Material and Labor Cost'!$F$10 -> 70 | H102: =SUM(F102:G102) -> 196.5 | I102: =H102*D102 -> 5279.6799 | Q102: =SUM(AA102:AH102) -> 13.4343 | R102: =Y102*D102 -> 2.68686 | S102: =SUM(Q102:R102) -> 16.12116 | T102: =D102-S102 -> 10.74744 | U102: =SUM(AJ101:AQ101) -> 1319.92 | V102: =Y102*I102 -> 527.96799 | W102: =SUM(U102:V102) -> 1847.888 | X102: =I102-W102 -> 3431.7919 | Y102: =SUM(AS102) -> 0.1 | AA102: 13.4343 | AJ102: 2639.84 | AS102: 0.1 | AU102: 0.5 | AV102: 0.4
B103: Hanger clips | C103: 7 | D103: =ROUNDUP(C103*$K$39,0) -> 8 | E103: pcs | F103: ='Material and Labor Cost'!$D$11 -> 30 | G103: ='Material and Labor Cost'!$F$11 -> 20 | H103: =SUM(F103:G103) -> 50 | I103: =H103*D103 -> 400 | Q103: =SUM(AA103:AH103) -> 4 | R103: =Y103*D103 -> 0.8 | S103: =SUM(Q103:R103) -> 4.8 | T103: =D103-S103 -> 3.2 | U103: =SUM(AJ102:AQ102) -> 2639.84 | V103: =Y103*I103 -> 40 | W103: =SUM(U103:V103) -> 2679.84 | X103: =I103-W103 -> -2279.84 | Y103: =SUM(AS103) -> 0.1 | AA103: 4 | AJ103: 200 | AS103: 0.1 | AU103: 0.5 | AV103: 0.4
B104: W clips | C104: 32 | D104: =ROUNDUP(C104*$K$39,0) -> 36 | E104: pcs | F104: ='Material and Labor Cost'!$D$12 -> 10 | G104: ='Material and Labor Cost'!$F$12 -> 20 | H104: =SUM(F104:G104) -> 30 | I104: =H104*D104 -> 1080 | Q104: =SUM(AA104:AH104) -> 18 | R104: =Y104*D104 -> 3.6 | S104: =SUM(Q104:R104) -> 21.6 | T104: =D104-S104 -> 14.4 | U104: =SUM(AJ103:AQ103) -> 200 | V104: =Y104*I104 -> 108 | W104: =SUM(U104:V104) -> 308 | X104: =I104-W104 -> 772 | Y104: =SUM(AS104) -> 0.1 | AA104: 18 | AJ104: 540 | AS104: 0.1 | AU104: 0.5 | AV104: 0.4
B105: Wall Angle | C105: 15.36 | D105: =ROUNDUP(C105*$K$39,0) -> 17 | E105: l.m | F105: ='Material and Labor Cost'!$D$13 -> 110 | G105: ='Material and Labor Cost'!$F$13 -> 60 | H105: =SUM(F105:G105) -> 170 | I105: =H105*D105 -> 2890 | Q105: =SUM(AA105:AH105) -> 8.5 | R105: =Y105*D105 -> 1.7 | S105: =SUM(Q105:R105) -> 10.2 | T105: =D105-S105 -> 6.8 | U105: =SUM(AJ104:AQ104) -> 540 | V105: =Y105*I105 -> 289 | W105: =SUM(U105:V105) -> 829 | X105: =I105-W105 -> 2061 | Y105: =SUM(AS105) -> 0.1 | AA105: 8.5 | AJ105: 1445 | AS105: 0.1 | AU105: 0.5 | AV105: 0.4
B106: Paint flat finish | C106: =C100*2 -> 28.2 | D106: =C106*$K$39 -> 31.02 | E106: sq.m | F106: ='Material and Labor Cost'!$D$14 -> 250 | G106: ='Material and Labor Cost'!$F$14 -> 350 | H106: =SUM(F106:G106) -> 600 | I106: =H106*D106 -> 18612 | Q106: =SUM(AA106:AH106) -> 15.51 | R106: =Y106*D106 -> 3.102 | S106: =SUM(Q106:R106) -> 18.612 | T106: =D106-S106 -> 12.408 | U106: =SUM(AJ105:AQ105) -> 1445 | V106: =Y106*I106 -> 1861.2 | W106: =SUM(U106:V106) -> 3306.2 | X106: =I106-W106 -> 15305.8 | Y106: =SUM(AS106) -> 0.1 | AA106: 15.51 | AJ106: 9306 | AS106: 0.1 | AU106: 0.5 | AV106: 0.4
B108: HALLWAY
B109: Gypsum Board | C109: 23 | D109: =C109*$K$39 -> 25.3 | E109: sq.m | F109: ='Material and Labor Cost'!$D$8 -> 250 | G109: ='Material and Labor Cost'!$F$8 -> 350 | H109: =SUM(F109:G109) -> 600 | I109: =H109*D109 -> 15180 | Q109: =SUM(AA109:AH109) -> 12.65 | R109: =Y109*D109 -> 2.53 | S109: =SUM(Q109:R109) -> 15.18 | T109: =D109-S109 -> 10.12 | U109: =SUM(AJ108:AQ108) -> 0 | V109: =Y109*I109 -> 1518 | W109: =SUM(U109:V109) -> 1518 | X109: =I109-W109 -> 13662 | Y109: =SUM(AS109) -> 0.1 | AA109: 12.65 | AJ109: 7590 | AS109: 0.1 | AU109: 0.5 | AV109: 0.4
B110: CARRYING channel | C110: 15 | D110: =C110*$K$39 -> 16.5 | E110: l.m | F110: ='Material and Labor Cost'!$D$9 -> 126.5 | G110: ='Material and Labor Cost'!$F$9 -> 70 | H110: =SUM(F110:G110) -> 196.5 | I110: =H110*D110 -> 3242.25 | Q110: =SUM(AA110:AH110) -> 8.25 | R110: =Y110*D110 -> 1.65 | S110: =SUM(Q110:R110) -> 9.9 | T110: =D110-S110 -> 6.6 | U110: =SUM(AJ109:AQ109) -> 7590 | V110: =Y110*I110 -> 324.225 | W110: =SUM(U110:V110) -> 7914.225 | X110: =I110-W110 -> -4671.975 | Y110: =SUM(AS110) -> 0.1 | AA110: 8.25 | AJ110: 1621.125 | AS110: 0.1 | AU110: 0.5 | AV110: 0.4
B111: Metal Furring | C111: 30 | D111: =C111*$K$39 -> 33 | E111: l.m | F111: ='Material and Labor Cost'!$D$10 -> 126.5 | G111: ='Material and Labor Cost'!$F$10 -> 70 | H111: =SUM(F111:G111) -> 196.5 | I111: =H111*D111 -> 6484.5 | Q111: =SUM(AA111:AH111) -> 16.5 | R111: =Y111*D111 -> 3.3 | S111: =SUM(Q111:R111) -> 19.8 | T111: =D111-S111 -> 13.2 | U111: =SUM(AJ110:AQ110) -> 1621.125 | V111: =Y111*I111 -> 648.45 | W111: =SUM(U111:V111) -> 2269.575 | X111: =I111-W111 -> 4214.925 | Y111: =SUM(AS111) -> 0.1 | AA111: 16.5 | AJ111: 3242.25 | AS111: 0.1 | AU111: 0.5 | AV111: 0.4
B112: Hanger clips | C112: 25 | D112: =ROUNDUP(C112*$K$39,0) -> 28 | E112: pcs | F112: ='Material and Labor Cost'!$D$11 -> 30 | G112: ='Material and Labor Cost'!$F$11 -> 20 | H112: =SUM(F112:G112) -> 50 | I112: =H112*D112 -> 1400 | Q112: =SUM(AA112:AH112) -> 14 | R112: =Y112*D112 -> 2.8 | S112: =SUM(Q112:R112) -> 16.8 | T112: =D112-S112 -> 11.2 | U112: =SUM(AJ111:AQ111) -> 3242.25 | V112: =Y112*I112 -> 140 | W112: =SUM(U112:V112) -> 3382.25 | X112: =I112-W112 -> -1982.25 | Y112: =SUM(AS112) -> 0.1 | AA112: 14 | AJ112: 700 | AS112: 0.1 | AU112: 0.5 | AV112: 0.4
B113: W clips | C113: 54 | D113: =ROUNDUP(C113*$K$39,0) -> 60 | E113: pcs | F113: ='Material and Labor Cost'!$D$12 -> 10 | G113: ='Material and Labor Cost'!$F$12 -> 20 | H113: =SUM(F113:G113) -> 30 | I113: =H113*D113 -> 1800 | Q113: =SUM(AA113:AH113) -> 30 | R113: =Y113*D113 -> 6 | S113: =SUM(Q113:R113) -> 36 | T113: =D113-S113 -> 24 | U113: =SUM(AJ112:AQ112) -> 700 | V113: =Y113*I113 -> 180 | W113: =SUM(U113:V113) -> 880 | X113: =I113-W113 -> 920 | Y113: =SUM(AS113) -> 0.1 | AA113: 30 | AJ113: 900 | AS113: 0.1 | AU113: 0.5 | AV113: 0.4
B114: Wall Angle | C114: 35 | D114: =ROUNDUP(C114*$K$39,0) -> 39 | E114: l.m | F114: ='Material and Labor Cost'!$D$13 -> 110 | G114: ='Material and Labor Cost'!$F$13 -> 60 | H114: =SUM(F114:G114) -> 170 | I114: =H114*D114 -> 6630 | Q114: =SUM(AA114:AH114) -> 19.5 | R114: =Y114*D114 -> 3.9 | S114: =SUM(Q114:R114) -> 23.4 | T114: =D114-S114 -> 15.6 | U114: =SUM(AJ113:AQ113) -> 900 | V114: =Y114*I114 -> 663 | W114: =SUM(U114:V114) -> 1563 | X114: =I114-W114 -> 5067 | Y114: =SUM(AS114) -> 0.1 | AA114: 19.5 | AJ114: 3315 | AS114: 0.1 | AU114: 0.5 | AV114: 0.4
B115: Paint flat finish | C115: =C109*2 -> 46 | D115: =C115*$K$39 -> 50.6 | E115: sq.m | F115: ='Material and Labor Cost'!$D$14 -> 250 | G115: ='Material and Labor Cost'!$F$14 -> 350 | H115: =SUM(F115:G115) -> 600 | I115: =H115*D115 -> 30360 | Q115: =SUM(AA115:AH115) -> 25.3 | R115: =Y115*D115 -> 5.06 | S115: =SUM(Q115:R115) -> 30.36 | T115: =D115-S115 -> 20.24 | U115: =SUM(AJ114:AQ114) -> 3315 | V115: =Y115*I115 -> 3036 | W115: =SUM(U115:V115) -> 6351 | X115: =I115-W115 -> 24009 | Y115: =SUM(AS115) -> 0.1 | AA115: 25.3 | AJ115: 15180 | AS115: 0.1 | AU115: 0.5 | AV115: 0.4
B117: Second Floor (Exterior)
B118: PVC ceiling Panel | C118: 24.5 | D118: =C118*$K$39 -> 26.95 | E118: sq.m | F118: ='Material and Labor Cost'!$D$15 -> 250 | G118: ='Material and Labor Cost'!$F$15 -> 350 | H118: =SUM(F118:G118) -> 600 | I118: =H118*D118 -> 16170 | Q118: =SUM(AA118:AH118) -> 10.78 | R118: =Y118*D118 -> 0 | S118: =SUM(Q118:R118) -> 10.78 | T118: =D118-S118 -> 16.17 | U118: =SUM(AJ117:AQ117) -> 0 | V118: =Y118*I118 -> 0 | W118: =SUM(U118:V118) -> 0 | X118: =I118-W118 -> 16170 | Y118: =SUM(AS118) -> 0 | AA118: 10.78 | AJ118: 6468 | AS118: 0 | AU118: 0.4 | AV118: 0.6
B119: CARRYING channel | C119: 28.125 | D119: =C119*$K$39 -> 30.9375 | E119: l.m | F119: ='Material and Labor Cost'!$D$9 -> 126.5 | G119: ='Material and Labor Cost'!$F$9 -> 70 | H119: =SUM(F119:G119) -> 196.5 | I119: =H119*D119 -> 6079.2188 | Q119: =SUM(AA119:AH119) -> 12.375 | R119: =Y119*D119 -> 0 | S119: =SUM(Q119:R119) -> 12.375 | T119: =D119-S119 -> 18.5625 | U119: =SUM(AJ118:AQ118) -> 6468 | V119: =Y119*I119 -> 0 | W119: =SUM(U119:V119) -> 6468 | X119: =I119-W119 -> -388.78125 | Y119: =SUM(AS119) -> 0 | AA119: 12.375 | AJ119: 2431.6875 | AS119: 0 | AU119: 0.4 | AV119: 0.6
B120: Metal Furring | C120: 45.316667 | D120: =C120*$K$39 -> 49.848333 | E120: l.m | F120: ='Material and Labor Cost'!$D$10 -> 126.5 | G120: ='Material and Labor Cost'!$F$10 -> 70 | H120: =SUM(F120:G120) -> 196.5 | I120: =H120*D120 -> 9795.1975 | Q120: =SUM(AA120:AH120) -> 19.939333 | R120: =Y120*D120 -> 0 | S120: =SUM(Q120:R120) -> 19.939333 | T120: =D120-S120 -> 29.909 | U120: =SUM(AJ119:AQ119) -> 2431.6875 | V120: =Y120*I120 -> 0 | W120: =SUM(U120:V120) -> 2431.6875 | X120: =I120-W120 -> 7363.51 | Y120: =SUM(AS120) -> 0 | AA120: 19.939333 | AJ120: 3918.079 | AS120: 0 | AU120: 0.4 | AV120: 0.6
B121: Hanger clips | C121: 9 | D121: =ROUNDUP(C121*$K$39,0) -> 10 | E121: pcs | F121: ='Material and Labor Cost'!$D$11 -> 30 | G121: ='Material and Labor Cost'!$F$11 -> 20 | H121: =SUM(F121:G121) -> 50 | I121: =H121*D121 -> 500 | Q121: =SUM(AA121:AH121) -> 4 | R121: =Y121*D121 -> 0 | S121: =SUM(Q121:R121) -> 4 | T121: =D121-S121 -> 6 | U121: =SUM(AJ120:AQ120) -> 3918.079 | V121: =Y121*I121 -> 0 | W121: =SUM(U121:V121) -> 3918.079 | X121: =I121-W121 -> -3418.079 | Y121: =SUM(AS121) -> 0 | AA121: 4 | AJ121: 200 | AS121: 0 | AU121: 0.4 | AV121: 0.6
B122: W clips | C122: 136 | D122: =ROUNDUP(C122*$K$39,0) -> 150 | E122: pcs | F122: ='Material and Labor Cost'!$D$12 -> 10 | G122: ='Material and Labor Cost'!$F$12 -> 20 | H122: =SUM(F122:G122) -> 30 | I122: =H122*D122 -> 4500 | Q122: =SUM(AA122:AH122) -> 60 | R122: =Y122*D122 -> 0 | S122: =SUM(Q122:R122) -> 60 | T122: =D122-S122 -> 90 | U122: =SUM(AJ121:AQ121) -> 200 | V122: =Y122*I122 -> 0 | W122: =SUM(U122:V122) -> 200 | X122: =I122-W122 -> 4300 | Y122: =SUM(AS122) -> 0 | AA122: 60 | AJ122: 1800 | AS122: 0 | AU122: 0.4 | AV122: 0.6
B123: H CLIP | C123: 1.26 | D123: =C123*$K$39 -> 1.386 | E123: l.m | F123: ='Material and Labor Cost'!$D$16 -> 110 | G123: ='Material and Labor Cost'!$F$16 -> 20 | H123: =SUM(F123:G123) -> 130 | I123: =H123*D123 -> 180.18 | Q123: =SUM(AA123:AH123) -> 0.5544 | R123: =Y123*D123 -> 0 | S123: =SUM(Q123:R123) -> 0.5544 | T123: =D123-S123 -> 0.8316 | U123: =SUM(AJ122:AQ122) -> 1800 | V123: =Y123*I123 -> 0 | W123: =SUM(U123:V123) -> 1800 | X123: =I123-W123 -> -1619.82 | Y123: =SUM(AS123) -> 0 | AA123: 0.5544 | AJ123: 72.072 | AS123: 0 | AU123: 0.4 | AV123: 0.6
...

Sheet wall
Q10: Unit 6&7 E.M Razon Commercial Building, San Pedro Camuning,
Q11: Mexico, Pampanga, Philippines 2021
Q12: 09951119535 | clients@saikobuilders.com
A14: Project name : | B14: PROPOSED THREE STORY RESIDENCE
A15: Location : | B15: GRAND CENTENIAL HOMES KAWIT CAVITE
A16: Date : | B16: =TODAY() -> 46251
AA17: QUANTITY | AJ17: AMOUNT | AS17: ACCOMPLISHMENT | BB17: PREVIOUS ACCOMPLISHMENT
A18: ITEM NO | B18: Description | C18: QUANTITY | D18: QUANTITY | E18: UNIT | F18: Material Cost Php/unit | G18: Labor and Equipment Cost Php/unit | H18: Total Cost Php/Unit | I18: Total Amount Php | Q18: QUANTITY | U18: AMOUNT | Y18: PERCENTAGE | AA18: BILLING 1 | AB18: BILLING 2 | AC18: BILLING 3 | AD18: BILLING 4 | AE18: BILLING 5 | AF18: BILLING 6 | AG18: BILLING 7 | AH18: BILLING 8 | AJ18: BILLING 1 | AK18: BILLING 2 | AL18: BILLING 3 | AM18: BILLING 4 | AN18: BILLING 5 | AO18: BILLING 6 | AP18: BILLING 7 | AQ18: BILLING 8 | AS18: BILLING 1 | AT18: BILLING 2 | AU18: BILLING 3 | AV18: BILLING 4 | AW18: BILLING 5 | AX18: BILLING 6 | AY18: BILLING 7 | AZ18: BILLING 8 | BB18: BILLING 1 | BC18: BILLING 2 | BD18: BILLING 3 | BE18: BILLING 4 | BF18: BILLING 5 | BG18: BILLING 6 | BH18: BILLING 7 | BI18: BILLING 8
B19: Wall Finish | K19: MARK UP | Q19: PREVIOUS | R19: THIS DATE | S19: TO DATE | T19: BALANCE | U19: PREVIOUS | V19: THIS DATE | W19: TO DATE | X19: BALANCE | Y19: Accomplishment
B20: Ground Floor ( Interior ) | K20: 1.1
B21: FOYER, LIVING, DINING AND KITCHEN | K21: MISS
B22: White Mouldings | C22: 20.3 | D22: =C22*$K$20 -> 22.33 | E22: l.m | F22: ='MATERIAL AND LABOR COST FOR WAL'!$D$7 -> 550 | G22: ='MATERIAL AND LABOR COST FOR WAL'!$F$7 -> 350 | H22: =SUM(F22,G22) -> 900 | I22: =H22*D22 -> 20097 | K22: 0.1 | Q22: =SUM(AA22:AH22) -> 4.466 | R22: =Y22*D22 -> 6.699 | S22: =SUM(Q22:R22) -> 11.165 | T22: =D22-S22 -> 11.165 | U22: =SUM(AJ22:AQ22) -> 4019.4 | V22: =Y22*I22 -> 6029.1 | W22: =SUM(U22:V22) -> 10048.5 | X22: =I22-W22 -> 10048.5 | Y22: =SUM(AS22:AZ22) -> 0.3 | AA22: 4.466 | AJ22: 4019.4 | AS22: 0.3 | BB22: 0.2 | BC22: 0.2
B23: Hidden Door PU Stone Finish Light Beige | C23: 5.8 | D23: =C23*$K$20 -> 6.38 | E23: sqm | F23: ='MATERIAL AND LABOR COST FOR WAL'!$D$8 -> 2150 | G23: ='MATERIAL AND LABOR COST FOR WAL'!$F$8 -> 1200 | H23: =SUM(F23,G23) -> 3350 | I23: =H23*D23 -> 21373 | Q23: =SUM(AA23:AH23) -> 1.276 | R23: =Y23*D23 -> 1.914 | S23: =SUM(Q23:R23) -> 3.19 | T23: =D23-S23 -> 3.19 | U23: =SUM(AJ23:AQ23) -> 4274.6 | V23: =Y23*I23 -> 6411.9 | W23: =SUM(U23:V23) -> 10686.5 | X23: =I23-W23 -> 10686.5 | Y23: =SUM(AS23:AZ23) -> 0.3 | AA23: 1.276 | AJ23: 4274.6 | AS23: 0.3 | BB23: 0.2 | BC23: 0.2
B24: White Fluted | C24: 5.2 | D24: =C24*$K$20 -> 5.72 | E24: sqm | F24: ='MATERIAL AND LABOR COST FOR WAL'!$D$9 -> 880 | G24: ='MATERIAL AND LABOR COST FOR WAL'!$F$9 -> 350 | H24: =SUM(F24,G24) -> 1230 | I24: =H24*D24 -> 7035.6 | Q24: =SUM(AA24:AH24) -> 1.144 | R24: =Y24*D24 -> 1.716 | S24: =SUM(Q24:R24) -> 2.86 | T24: =D24-S24 -> 2.86 | U24: =SUM(AJ24:AQ24) -> 1407.12 | V24: =Y24*I24 -> 2110.68 | W24: =SUM(U24:V24) -> 3517.8 | X24: =I24-W24 -> 3517.8 | Y24: =SUM(AS24:AZ24) -> 0.3 | AA24: 1.144 | AJ24: 1407.12 | AS24: 0.3 | BB24: 0.2 | BC24: 0.2
B25: Laminated Synthetic Marble Finish | C25: 7.4 | D25: =C25*$K$20 -> 8.14 | E25: sqm | F25: ='MATERIAL AND LABOR COST FOR WAL'!$D$10 -> 3300 | G25: ='MATERIAL AND LABOR COST FOR WAL'!$F$10 -> 1650 | H25: =SUM(F25,G25) -> 4950 | I25: =H25*D25 -> 40293 | Q25: =SUM(AA25:AH25) -> 1.628 | R25: =Y25*D25 -> 2.442 | S25: =SUM(Q25:R25) -> 4.07 | T25: =D25-S25 -> 4.07 | U25: =SUM(AJ25:AQ25) -> 8058.6 | V25: =Y25*I25 -> 12087.9 | W25: =SUM(U25:V25) -> 20146.5 | X25: =I25-W25 -> 20146.5 | Y25: =SUM(AS25:AZ25) -> 0.3 | AA25: 1.628 | AJ25: 8058.6 | AS25: 0.3 | BB25: 0.2 | BC25: 0.2
B26: Back Splash Quartz/ White Sintered Stone Terazzo look Finish | C26: 1.1 | D26: =C26*$K$20 -> 1.21 | E26: sqm | F26: ='MATERIAL AND LABOR COST FOR WAL'!$D$11 -> 6600 | G26: ='MATERIAL AND LABOR COST FOR WAL'!$F$11 -> 3300 | H26: =SUM(F26,G26) -> 9900 | I26: =H26*D26 -> 11979 | Q26: =SUM(AA26:AH26) -> 0.242 | R26: =Y26*D26 -> 0.363 | S26: =SUM(Q26:R26) -> 0.605 | T26: =D26-S26 -> 0.605 | U26: =SUM(AJ26:AQ26) -> 2395.8 | V26: =Y26*I26 -> 3593.7 | W26: =SUM(U26:V26) -> 5989.5 | X26: =I26-W26 -> 5989.5 | Y26: =SUM(AS26:AZ26) -> 0.3 | AA26: 0.242 | AJ26: 2395.8 | AS26: 0.3 | BB26: 0.2 | BC26: 0.2
B27: Semi Gloss | C27: 42.3 | D27: =C27*$K$20 -> 46.53 | E27: sqm | F27: ='MATERIAL AND LABOR COST FOR WAL'!$D$12 -> 350 | G27: ='MATERIAL AND LABOR COST FOR WAL'!$F$12 -> 350 | H27: =SUM(F27,G27) -> 700 | I27: =H27*D27 -> 32571 | Q27: =SUM(AA27:AH27) -> 9.306 | R27: =Y27*D27 -> 13.959 | S27: =SUM(Q27:R27) -> 23.265 | T27: =D27-S27 -> 23.265 | U27: =SUM(AJ27:AQ27) -> 6514.2 | V27: =Y27*I27 -> 9771.3 | W27: =SUM(U27:V27) -> 16285.5 | X27: =I27-W27 -> 16285.5 | Y27: =SUM(AS27:AZ27) -> 0.3 | AA27: 9.306 | AJ27: 6514.2 | AS27: 0.3 | BB27: 0.2 | BC27: 0.2
B28: Wood Laminated Finish | C28: 1.6 | D28: =C28*$K$20 -> 1.76 | E28: sqm | F28: ='MATERIAL AND LABOR COST FOR WAL'!$D$13 -> 825 | G28: ='MATERIAL AND LABOR COST FOR WAL'!$F$13 -> 350 | H28: =SUM(F28,G28) -> 1175 | I28: =H28*D28 -> 2068 | Q28: =SUM(AA28:AH28) -> 0.352 | R28: =Y28*D28 -> 0.528 | S28: =SUM(Q28:R28) -> 0.88 | T28: =D28-S28 -> 0.88 | U28: =SUM(AJ28:AQ28) -> 413.6 | V28: =Y28*I28 -> 620.4 | W28: =SUM(U28:V28) -> 1034 | X28: =I28-W28 -> 1034 | Y28: =SUM(AS28:AZ28) -> 0.3 | AA28: 0.352 | AJ28: 413.6 | AS28: 0.3 | BB28: 0.2 | BC28: 0.2
B29: Beveled Clear Mirror 10mm THK | C29: 2.5 | D29: =C29*$K$20 -> 2.75 | E29: sqm | F29: ='MATERIAL AND LABOR COST FOR WAL'!$D$14 -> 1375 | G29: ='MATERIAL AND LABOR COST FOR WAL'!$F$14 -> 700 | H29: =SUM(F29,G29) -> 2075 | I29: =D29*H29 -> 5706.25 | Q29: =SUM(AA29:AH29) -> 0.55 | R29: =Y29*D29 -> 0.825 | S29: =SUM(Q29:R29) -> 1.375 | T29: =D29-S29 -> 1.375 | U29: =SUM(AJ29:AQ29) -> 1141.25 | V29: =Y29*I29 -> 1711.875 | W29: =SUM(U29:V29) -> 2853.125 | X29: =I29-W29 -> 2853.125 | Y29: =SUM(AS29:AZ29) -> 0.3 | AA29: 0.55 | AJ29: 1141.25 | AS29: 0.3 | BB29: 0.2 | BC29: 0.2
B31: OFFICE | F31: ='MATERIAL AND LABOR COST FOR WAL'!D15 -> 0
B32: Biege Textured Wallpaper Finish | C32: 15 | D32: =C32*$K$20 -> 16.5 | E32: sqm | F32: ='MATERIAL AND LABOR COST FOR WAL'!$D$16 -> 825 | G32: ='MATERIAL AND LABOR COST FOR WAL'!$F$16 -> 350 | H32: =SUM(F32,G32) -> 1175 | I32: =H32*D32 -> 19387.5 | Q32: =SUM(AA32:AH32) -> 1.65 | R32: =Y32*D32 -> 4.95 | S32: =SUM(Q32:R32) -> 6.6 | T32: =D32-S32 -> 9.9 | U32: =SUM(AJ32:AQ32) -> 1938.75 | V32: =Y32*I32 -> 5816.25 | W32: =SUM(U32:V32) -> 7755 | X32: =I32-W32 -> 11632.5 | Y32: =SUM(AS32:AZ32) -> 0.3 | AA32: 1.65 | AJ32: 1938.75 | AS32: 0.3 | BB32: 0.1 | BC32: 0.1
B33: PU Stone Textured Light Biege Finish | C33: 3.8 | D33: =C33*$K$20 -> 4.18 | E33: sqm | F33: ='MATERIAL AND LABOR COST FOR WAL'!$D$17 -> 2150 | G33: ='MATERIAL AND LABOR COST FOR WAL'!$F$17 -> 1200 | H33: =SUM(F33,G33) -> 3350 | I33: =H33*D33 -> 14003 | Q33: =SUM(AA33:AH33) -> 0.418 | R33: =Y33*D33 -> 1.254 | S33: =SUM(Q33:R33) -> 1.672 | T33: =D33-S33 -> 2.508 | U33: =SUM(AJ33:AQ33) -> 1400.3 | V33: =Y33*I33 -> 4200.9 | W33: =SUM(U33:V33) -> 5601.2 | X33: =I33-W33 -> 8401.8 | Y33: =SUM(AS33:AZ33) -> 0.3 | AA33: 0.418 | AJ33: 1400.3 | AS33: 0.3 | BB33: 0.1 | BC33: 0.1
B34: 18 mm THK MDF Plywood Wall Cladding in Wood Finish w/ warm strip light | C34: 3.7 | D34: =C34*$K$20 -> 4.07 | E34: sqm | F34: ='MATERIAL AND LABOR COST FOR WAL'!$D$18 -> 1375 | G34: ='MATERIAL AND LABOR COST FOR WAL'!$F$18 -> 700 | H34: =SUM(F34,G34) -> 2075 | I34: =H34*D34 -> 8445.25 | Q34: =SUM(AA34:AH34) -> 0.407 | R34: =Y34*D34 -> 1.221 | S34: =SUM(Q34:R34) -> 1.628 | T34: =D34-S34 -> 2.442 | U34: =SUM(AJ34:AQ34) -> 844.525 | V34: =Y34*I34 -> 2533.575 | W34: =SUM(U34:V34) -> 3378.1 | X34: =I34-W34 -> 5067.15 | Y34: =SUM(AS34:AZ34) -> 0.3 | AA34: 0.407 | AJ34: 844.525 | AS34: 0.3 | BB34: 0.1 | BC34: 0.1
B35: Semi Gloss Off White | C35: 7.1 | D35: =C35*$K$20 -> 7.81 | E35: sqm | F35: ='MATERIAL AND LABOR COST FOR WAL'!$D$19 -> 350 | G35: ='MATERIAL AND LABOR COST FOR WAL'!$F$19 -> 350 | H35: =SUM(F35,G35) -> 700 | I35: =H35*D35 -> 5467 | Q35: =SUM(AA35:AH35) -> 0.781 | R35: =Y35*D35 -> 2.343 | S35: =SUM(Q35:R35) -> 3.124 | T35: =D35-S35 -> 4.686 | U35: =SUM(AJ35:AQ35) -> 546.7 | V35: =Y35*I35 -> 1640.1 | W35: =SUM(U35:V35) -> 2186.8 | X35: =I35-W35 -> 3280.2 | Y35: =SUM(AS35:AZ35) -> 0.3 | AA35: 0.781 | AJ35: 546.7 | AS35: 0.3 | BB35: 0.1 | BC35: 0.1
B37: POWDER ROOM
B38: 60X120 Gray Marble Tiles In High Gloss Finish | C38: 22 | D38: =C38*$K$20 -> 24.2 | E38: sqm | F38: ='MATERIAL AND LABOR COST FOR WAL'!$D$20 -> 550 | G38: ='MATERIAL AND LABOR COST FOR WAL'!$F$20 -> 350 | H38: =SUM(F38,G38) -> 900 | I38: =D38*H38 -> 21780 | Q38: =SUM(AA38:AH38) -> 2.42 | R38: =Y38*D38 -> 14.52 | S38: =SUM(Q38:R38) -> 16.94 | T38: =D38-S38 -> 7.26 | U38: =SUM(AJ38:AQ38) -> 2178 | V38: =Y38*I38 -> 13068 | W38: =SUM(U38:V38) -> 15246 | X38: =I38-W38 -> 6534 | Y38: =SUM(AS38:AZ38) -> 0.6 | AA38: 2.42 | AJ38: 2178 | AS38: 0.6 | BB38: 0.1 | BC38: 0.1
B39: Miscellaneous and other consumables | D39: 1 | E39: lot | I39: =SUM(I22:I38)*$K$22 -> 21020.56 | Q39: =SUM(AA39:AH39) -> 0.1 | R39: =Y39*D39 -> 0.6 | S39: =SUM(Q39:R39) -> 0.7 | T39: =D39-S39 -> 0.3 | U39: =SUM(AJ39:AQ39) -> 2102.056 | V39: =Y39*I39 -> 12612.336 | W39: =SUM(U39:V39) -> 14714.392 | X39: =I39-W39 -> 6306.168 | Y39: =SUM(AS39:AZ39) -> 0.6 | AA39: 0.1 | AJ39: 2102.056 | AS39: 0.6 | BB39: 0.1 | BC39: 0.1
B40: Sub-Total for Ground Floor (Interior) | I40: =SUM(I22:I39) -> 231226.16 | Q40: =SUM(Q22:Q39) -> 24.74 | R40: =SUM(R22:R39) -> 53.334 | S40: =SUM(S22:S39) -> 78.074 | T40: =SUM(T22:T39) -> 74.506 | U40: =SUM(U22:U39) -> 37234.901 | V40: =SUM(V22:V39) -> 82208.016 | W40: =SUM(W22:W39) -> 119442.92 | X40: =SUM(X22:X39) -> 111783.24 | Y40: =SUM(Y22:Y39)/COUNT(Y22:Y39) -> 0.34285714 | AA40: 24.74 | AJ40: 37234.901 | BB40: =SUM(BB22:BB39)/COUNT(BB22:BB39) -> 0.15714286 | BC40: =SUM(BC22:BC39)/COUNT(BC22:BC39) -> 0.15714286
B42: Ground Floor ( Exterior )
B43: Exposed Aggregate Concrete Cladding | C43: 1.6 | D43: =C43*$K$20 -> 1.76 | E43: sqm | F43: ='MATERIAL AND LABOR COST FOR WAL'!$D$22 -> 350 | G43: ='MATERIAL AND LABOR COST FOR WAL'!$F$22 -> 350 | H43: =SUM(F43,G43) -> 700 | I43: =H43*D43 -> 1232 | Q43: =SUM(AA43:AH43) -> 0.176 | R43: =Y43*D43 -> 0.176 | S43: =SUM(Q43:R43) -> 0.352 | T43: =D43-S43 -> 1.408 | U43: =SUM(AJ43:AQ43) -> 123.2 | V43: =Y43*I43 -> 123.2 | W43: =SUM(U43:V43) -> 246.4 | X43: =I43-W43 -> 985.6 | Y43: =SUM(AS43:AZ43) -> 0.1 | AA43: 0.176 | AJ43: 123.2 | AS43: 0.1 | BB43: 0.1 | BC43: 0.1
B44: Wall Flashing ( Dark Gray ) | C44: 46.4 | D44: =C44*$K$20 -> 51.04 | E44: Im | F44: ='MATERIAL AND LABOR COST FOR WAL'!$D$23 -> 550 | G44: ='MATERIAL AND LABOR COST FOR WAL'!$F$23 -> 350 | H44: =SUM(F44,G44) -> 900 | I44: =H44*D44 -> 45936 | Q44: =SUM(AA44:AH44) -> 5.104 | R44: =Y44*D44 -> 28.072 | S44: =SUM(Q44:R44) -> 33.176 | T44: =D44-S44 -> 17.864 | U44: =SUM(AJ44:AQ44) -> 4593.6 | V44: =Y44*I44 -> 25264.8 | W44: =SUM(U44:V44) -> 29858.4 | X44: =I44-W44 -> 16077.6 | Y44: =SUM(AS44:AZ44) -> 0.55 | AA44: 5.104 | AJ44: 4593.6 | AS44: 0.55 | BB44: 0.1 | BC44: 0.1
B45: Wall Piaint Finish ( Off White ) | C45: 69.82 | D45: =C45*$K$20 -> 76.802 | E45: sqm | F45: ='MATERIAL AND LABOR COST FOR WAL'!$D$24 -> 350 | G45: ='MATERIAL AND LABOR COST FOR WAL'!$F$24 -> 350 | H45: =SUM(F45,G45) -> 700 | I45: =H45*D45 -> 53761.4 | Q45: =SUM(AA45:AH45) -> 7.6802 | R45: =Y45*D45 -> 46.0812 | S45: =SUM(Q45:R45) -> 53.7614 | T45: =D45-S45 -> 23.0406 | U45: =SUM(AJ45:AQ45) -> 5376.14 | V45: =Y45*I45 -> 32256.84 | W45: =SUM(U45:V45) -> 37632.98 | X45: =I45-W45 -> 16128.42 | Y45: =SUM(AS45:AZ45) -> 0.6 | AA45: 7.6802 | AJ45: 5376.14 | AS45: 0.6 | BB45: 0.1 | BC45: 0.1
B46: Natural Limestone Tiles Texture Running Ashlar Pattern | C46: 14.8 | D46: =C46*$K$20 -> 16.28 | E46: sqm | F46: ='MATERIAL AND LABOR COST FOR WAL'!$D$25 -> 950 | G46: ='MATERIAL AND LABOR COST FOR WAL'!$F$25 -> 350 | H46: =SUM(F46,G46) -> 1300 | I46: =H46*D46 -> 21164 | Q46: =SUM(AA46:AH46) -> 1.628 | R46: =Y46*D46 -> 6.512 | S46: =SUM(Q46:R46) -> 8.14 | T46: =D46-S46 -> 8.14 | U46: =SUM(AJ46:AQ46) -> 2116.4 | V46: =Y46*I46 -> 8465.6 | W46: =SUM(U46:V46) -> 10582 | X46: =I46-W46 -> 10582 | Y46: =SUM(AS46:AZ46) -> 0.4 | AA46: 1.628 | AJ46: 2116.4 | AS46: 0.4 | BB46: 0.1 | BC46: 0.3
B47: Wall Piaint Finish ( Dark Gray ) | C47: 19.1 | D47: =C47*$K$20 -> 21.01 | E47: sqm | F47: ='MATERIAL AND LABOR COST FOR WAL'!$D$26 -> 350 | G47: ='MATERIAL AND LABOR COST FOR WAL'!$F$26 -> 350 | H47: =SUM(F47,G47) -> 700 | I47: =D47*H47 -> 14707 | Q47: =SUM(AA47:AH47) -> 2.101 | R47: =Y47*D47 -> 12.606 | S47: =SUM(Q47:R47) -> 14.707 | T47: =D47-S47 -> 6.303 | U47: =SUM(AJ47:AQ47) -> 1470.7 | V47: =Y47*I47 -> 8824.2 | W47: =SUM(U47:V47) -> 10294.9 | X47: =I47-W47 -> 4412.1 | Y47: =SUM(AS47:AZ47) -> 0.6 | AA47: 2.101 | AJ47: 1470.7 | AS47: 0.6 | BB47: 0.1 | BC47: 0.1
B48: Miscellaneous and other consumables | D48: 1 | E48: lot | I48: =SUM(I43:I47)*$K$22 -> 13680.04 | Q48: =SUM(AA48:AH48) -> 0.1 | R48: =Y48*D48 -> 0.5 | S48: =SUM(Q48:R48) -> 0.6 | T48: =D48-S48 -> 0.4 | U48: =SUM(AJ48:AQ48) -> 1368.004 | V48: =Y48*I48 -> 6840.02 | W48: =SUM(U48:V48) -> 8208.024 | X48: =I48-W48 -> 5472.016 | Y48: =SUM(AS48:AZ48) -> 0.5 | AA48: 0.1 | AJ48: 1368.004 | AS48: 0.5 | BB48: 0.1 | BC48: 0.15
B49: Sub-total for Ground Floor (Exterior) | I49: =SUM(I43:I48) -> 150480.44 | Q49: =SUM(Q43:Q48) -> 16.7892 | R49: =SUM(R43:R48) -> 93.9472 | S49: =SUM(S43:S48) -> 110.7364 | T49: =SUM(T43:T48) -> 57.1556 | U49: =SUM(U43:U48) -> 15048.044 | V49: =SUM(V43:V48) -> 81774.66 | W49: =SUM(W43:W48) -> 96822.704 | X49: =SUM(X43:X48) -> 53657.736 | Y49: =SUM(Y43:Y48)/COUNT(Y43:Y48) -> 0.45833333 | AA49: 16.7892 | AJ49: 15048.044 | BB49: =SUM(BB43:BB48)/COUNT(BB43:BB48) -> 0.1 | BC49: =SUM(BC43:BC48)/COUNT(BC43:BC48) -> 0.14166667
B51: Second Floor ( Interior )
B52: BEDROOM 1
B53: Wall in Light Biege Semi-Gloss Painted Finish | C53: 39 | D53: =C53*$K$20 -> 42.9 | E53: sqm | F53: ='MATERIAL AND LABOR COST FOR WAL'!$D$29 -> 350 | G53: ='MATERIAL AND LABOR COST FOR WAL'!$F$29 -> 350 | H53: =SUM(F53,G53) -> 700 | I53: =H53*D53 -> 30030 | Q53: =SUM(AA53:AH53) -> 4.29 | R53: =Y53*D53 -> 17.16 | S53: =SUM(Q53:R53) -> 21.45 | T53: =D53-S53 -> 21.45 | U53: =SUM(AJ53:AQ53) -> 3003 | V53: =Y53*I53 -> 12012 | W53: =SUM(U53:V53) -> 15015 | X53: =I53-W53 -> 15015 | Y53: =SUM(AS53:AZ53) -> 0.4 | AA53: 4.29 | AJ53: 3003 | AS53: 0.4 | BB53: 0.1 | BC53: 0.2
B54: Wall in Light Biege Semi-Gloss Painted Finish with mouldings | C54: 22.6 | D54: =C54*$K$20 -> 24.86 | E54: Im | F54: ='MATERIAL AND LABOR COST FOR WAL'!$D$30 -> 550 | G54: ='MATERIAL AND LABOR COST FOR WAL'!$F$30 -> 350 | H54: =SUM(F54,G54) -> 900 | I54: =H54*D54 -> 22374 | Q54: =SUM(AA54:AH54) -> 2.486 | R54: =Y54*D54 -> 9.944 | S54: =SUM(Q54:R54) -> 12.43 | T54: =D54-S54 -> 12.43 | U54: =SUM(AJ54:AQ54) -> 2237.4 | V54: =Y54*I54 -> 8949.6 | W54: =SUM(U54:V54) -> 11187 | X54: =I54-W54 -> 11187 | Y54: =SUM(AS54:AZ54) -> 0.4 | AA54: 2.486 | AJ54: 2237.4 | AS54: 0.4 | BB54: 0.1 | BC54: 0.2
B55: BEDROOM 2 (Room and T&B) | F55: ='MATERIAL AND LABOR COST FOR WAL'!D31 -> 0 | G55: ='MATERIAL AND LABOR COST FOR WAL'!F31 -> 0
B56: Wall in off Light semi gloss Painted Finish | C56: 28 | D56: =C56*$K$20 -> 30.8 | E56: sqm | F56: ='MATERIAL AND LABOR COST FOR WAL'!$D$32 -> 350 | G56: ='MATERIAL AND LABOR COST FOR WAL'!$F$32 -> 350 | H56: =SUM(F56,G56) -> 700 | I56: =H56*D56 -> 21560 | Q56: =SUM(AA56:AH56) -> 3.08 | R56: =Y56*D56 -> 15.4 | S56: =SUM(Q56:R56) -> 18.48 | T56: =D56-S56 -> 12.32 | U56: =SUM(AJ56:AQ56) -> 2156 | V56: =Y56*I56 -> 10780 | W56: =SUM(U56:V56) -> 12936 | X56: =I56-W56 -> 8624 | Y56: =SUM(AS56:AZ56) -> 0.5 | AA56: 3.08 | AJ56: 2156 | AS56: 0.5 | BB56: 0.1 | BC56: 0.1
B57: Wall in Wood in Fluted Panel | C57: 3.5 | D57: =C57*$K$20 -> 3.85 | E57: sqm | F57: ='MATERIAL AND LABOR COST FOR WAL'!$D$33 -> 1100 | G57: ='MATERIAL AND LABOR COST FOR WAL'!$F$33 -> 330 | H57: =SUM(F57,G57) -> 1430 | I57: =H57*D57 -> 5505.5 | Q57: =SUM(AA57:AH57) -> 0.385 | R57: =Y57*D57 -> 1.54 | S57: =SUM(Q57:R57) -> 1.925 | T57: =D57-S57 -> 1.925 | U57: =SUM(AJ57:AQ57) -> 550.55 | V57: =Y57*I57 -> 2202.2 | W57: =SUM(U57:V57) -> 2752.75 | X57: =I57-W57 -> 2752.75 | Y57: =SUM(AS57:AZ57) -> 0.4 | AA57: 0.385 | AJ57: 550.55 | AS57: 0.4 | BB57: 0.1 | BC57: 0.1
B58: Headboard in light brown leatherette | C58: =3.1*2 -> 6.2 | D58: =C58*$K$20 -> 6.82 | E58: sqm | F58: ='MATERIAL AND LABOR COST FOR WAL'!$D$34 -> 350 | G58: ='MATERIAL AND LABOR COST FOR WAL'!$F$34 -> 350 | H58: =SUM(F58,G58) -> 700 | I58: =H58*D58 -> 4774 | Q58: =SUM(AA58:AH58) -> 0.682 | R58: =Y58*D58 -> 1.705 | S58: =SUM(Q58:R58) -> 2.387 | T58: =D58-S58 -> 4.433 | U58: =SUM(AJ58:AQ58) -> 477.4 | V58: =Y58*I58 -> 1193.5 | W58: =SUM(U58:V58) -> 1670.9 | X58: =I58-W58 -> 3103.1 | Y58: =SUM(AS58:AZ58) -> 0.25 | AA58: 0.682 | AJ58: 477.4 | AS58: 0.25 | BB58: 0.1 | BC58: 0.1
B59: 60x120 Gray Tiles Marble look in High Gloss Finish | C59: 22.81 | D59: =C59*$K$20 -> 25.091 | E59: sqm | F59: ='MATERIAL AND LABOR COST FOR WAL'!$D$35 -> 950 | G59: ='MATERIAL AND LABOR COST FOR WAL'!$F$35 -> 350 | H59: =SUM(F59,G59) -> 1300 | I59: =H59*D59 -> 32618.3 | Q59: =SUM(AA59:AH59) -> 2.5091 | R59: =Y59*D59 -> 12.5455 | S59: =SUM(Q59:R59) -> 15.0546 | T59: =D59-S59 -> 10.0364 | U59: =SUM(AJ59:AQ59) -> 3261.83 | V59: =Y59*I59 -> 16309.15 | W59: =SUM(U59:V59) -> 19570.98 | X59: =I59-W59 -> 13047.32 | Y59: =SUM(AS59:AZ59) -> 0.5 | AA59: 2.5091 | AJ59: 3261.83 | AS59: 0.5 | BB59: 0.1 | BC59: 0.3
B60: Mosaic Tiles Light Green Finish | C60: 2.8 | D60: =C60*$K$20 -> 3.08 | E60: sqm | F60: ='MATERIAL AND LABOR COST FOR WAL'!$D$36 -> 770 | G60: ='MATERIAL AND LABOR COST FOR WAL'!$F$36 -> 350 | H60: =SUM(F60,G60) -> 1120 | I60: =H60*D60 -> 3449.6 | Q60: =SUM(AA60:AH60) -> 0.308 | R60: =Y60*D60 -> 1.848 | S60: =SUM(Q60:R60) -> 2.156 | T60: =D60-S60 -> 0.924 | U60: =SUM(AJ60:AQ60) -> 344.96 | V60: =Y60*I60 -> 2069.76 | W60: =SUM(U60:V60) -> 2414.72 | X60: =I60-W60 -> 1034.88 | Y60: =SUM(AS60:AZ60) -> 0.6 | AA60: 0.308 | AJ60: 344.96 | AS60: 0.6 | BB60: 0.1 | BC60: 0.1
B61: Clear Mirror With Warm Light | C61: 3 | D61: =C61*$K$20 -> 3.3 | E61: sqm | F61: ='MATERIAL AND LABOR COST FOR WAL'!$D$37 -> 1450 | G61: ='MATERIAL AND LABOR COST FOR WAL'!$F$37 -> 350 | H61: =SUM(F61,G61) -> 1800 | I61: =D61*H61 -> 5940 | Q61: =SUM(AA61:AH61) -> 0.33 | R61: =Y61*D61 -> 0.33 | S61: =SUM(Q61:R61) -> 0.66 | T61: =D61-S61 -> 2.64 | U61: =SUM(AJ61:AQ61) -> 594 | V61: =Y61*I61 -> 594 | W61: =SUM(U61:V61) -> 1188 | X61: =I61-W61 -> 4752 | Y61: =SUM(AS61:AZ61) -> 0.1 | AA61: 0.33 | AJ61: 594 | AS61: 0.1 | BB61: 0.1 | BC61: 0.1
B62: BEDROOM 3 | F62: ='MATERIAL AND LABOR COST FOR WAL'!D38 -> 0 | G62: ='MATERIAL AND LABOR COST FOR WAL'!F38 -> 0
B63: Wall off White in Semi Gloss Painted Finish | C63: 37.5 | D63: =C63*$K$20 -> 41.25 | E63: sqm | F63: ='MATERIAL AND LABOR COST FOR WAL'!$D$39 -> 350 | G63: ='MATERIAL AND LABOR COST FOR WAL'!$F$39 -> 350 | H63: =SUM(F63,G63) -> 700 | I63: =H63*D63 -> 28875 | Q63: =SUM(AA63:AH63) -> 4.125 | R63: =Y63*D63 -> 12.375 | S63: =SUM(Q63:R63) -> 16.5 | T63: =D63-S63 -> 24.75 | U63: =SUM(AJ63:AQ63) -> 2887.5 | V63: =Y63*I63 -> 8662.5 | W63: =SUM(U63:V63) -> 11550 | X63: =I63-W63 -> 17325 | Y63: =SUM(AS63:AZ63) -> 0.3 | AA63: 4.125 | AJ63: 2887.5 | AS63: 0.3 | BB63: 0.1 | BC63: 0.1
B64: Wall Cladding in Fluted white Painted Finish | C64: 4.2 | D64: =C64*$K$20 -> 4.62 | E64: sqm | F64: ='MATERIAL AND LABOR COST FOR WAL'!$D$40 -> 880 | G64: ='MATERIAL AND LABOR COST FOR WAL'!$F$40 -> 330 | H64: =SUM(F64,G64) -> 1210 | I64: =H64*D64 -> 5590.2 | Q64: =SUM(AA64:AH64) -> 0.462 | R64: =Y64*D64 -> 0.462 | S64: =SUM(Q64:R64) -> 0.924 | T64: =D64-S64 -> 3.696 | U64: =SUM(AJ64:AQ64) -> 559.02 | V64: =Y64*I64 -> 559.02 | W64: =SUM(U64:V64) -> 1118.04 | X64: =I64-W64 -> 4472.16 | Y64: =SUM(AS64:AZ64) -> 0.1 | AA64: 0.462 | AJ64: 559.02 | AS64: 0.1 | BB64: 0.1 | BC64: 0.1
B65: Headboard | C65: 3 | D65: =C65*$K$20 -> 3.3 | E65: sqm | F65: ='MATERIAL AND LABOR COST FOR WAL'!$D$41 -> 330 | G65: ='MATERIAL AND LABOR COST FOR WAL'!$F$41 -> 0 | H65: =SUM(F65,G65) -> 330 | I65: =H65*D65 -> 1089 | Q65: =SUM(AA65:AH65) -> 0.33 | R65: =Y65*D65 -> 0.33 | S65: =SUM(Q65:R65) -> 0.66 | T65: =D65-S65 -> 2.64 | U65: =SUM(AJ65:AQ65) -> 108.9 | V65: =Y65*I65 -> 108.9 | W65: =SUM(U65:V65) -> 217.8 | X65: =I65-W65 -> 871.2 | Y65: =SUM(AS65:AZ65) -> 0.1 | AA65: 0.33 | AJ65: 108.9 | AS65: 0.1 | BB65: 0.1 | BC65: 0.1
B66: Mouldings | C66: 4.3 | D66: =C66*$K$20 -> 4.73 | E66: Im | F66: ='MATERIAL AND LABOR COST FOR WAL'!$D$42 -> 550 | G66: ='MATERIAL AND LABOR COST FOR WAL'!$F$42 -> 330 | H66: =SUM(F66,G66) -> 880 | I66: =D66*H66 -> 4162.4 | Q66: =SUM(AA66:AH66) -> 0.473 | R66: =Y66*D66 -> 0.473 | S66: =SUM(Q66:R66) -> 0.946 | T66: =D66-S66 -> 3.784 | U66: =SUM(AJ66:AQ66) -> 416.24 | V66: =Y66*I66 -> 416.24 | W66: =SUM(U66:V66) -> 832.48 | X66: =I66-W66 -> 3329.92 | Y66: =SUM(AS66:AZ66) -> 0.1 | AA66: 0.473 | AJ66: 416.24 | AS66: 0.1 | BB66: 0.1 | BC66: 0.1
B67: BEDROOM 4 | F67: ='MATERIAL AND LABOR COST FOR WAL'!D43 -> 0 | G67: ='MATERIAL AND LABOR COST FOR WAL'!F43 -> 0
B68: Stucco Cement Finish | C68: 37.4 | D68: =C68*$K$20 -> 41.14 | E68: sqm | F68: ='MATERIAL AND LABOR COST FOR WAL'!$D$44 -> 350 | G68: ='MATERIAL AND LABOR COST FOR WAL'!$F$44 -> 350 | H68: =SUM(F68,G68) -> 700 | I68: =H68*D68 -> 28798 | Q68: =SUM(AA68:AH68) -> 4.114 | R68: =Y68*D68 -> 12.342 | S68: =SUM(Q68:R68) -> 16.456 | T68: =D68-S68 -> 24.684 | U68: =SUM(AJ68:AQ68) -> 2879.8 | V68: =Y68*I68 -> 8639.4 | W68: =SUM(U68:V68) -> 11519.2 | X68: =I68-W68 -> 17278.8 | Y68: =SUM(AS68:AZ68) -> 0.3 | AA68: 4.114 | AJ68: 2879.8 | AS68: 0.3 | BB68: 0.1 | BC68: 0.1
B69: Headboard | C69: =2.6*2 -> 5.2 | D69: =C69*$K$20 -> 5.72 | E69: sqm | F69: ='MATERIAL AND LABOR COST FOR WAL'!$D$45 -> 330 | G69: ='MATERIAL AND LABOR COST FOR WAL'!$F$45 -> 350 | H69: =SUM(F69,G69) -> 680 | I69: =H69*D69 -> 3889.6 | Q69: =SUM(AA69:AH69) -> 0.572 | R69: =Y69*D69 -> 1.716 | S69: =SUM(Q69:R69) -> 2.288 | T69: =D69-S69 -> 3.432 | U69: =SUM(AJ69:AQ69) -> 388.96 | V69: =Y69*I69 -> 1166.88 | W69: =SUM(U69:V69) -> 1555.84 | X69: =I69-W69 -> 2333.76 | Y69: =SUM(AS69:AZ69) -> 0.3 | AA69: 0.572 | AJ69: 388.96 | AS69: 0.3 | BB69: 0.1 | BC69: 0.1
B70: Mouldings | C70: 3.3 | D70: =C70*$K$20 -> 3.63 | E70: Im | F70: ='MATERIAL AND LABOR COST FOR WAL'!$D$46 -> 550 | G70: ='MATERIAL AND LABOR COST FOR WAL'!$F$46 -> 330 | H70: =SUM(F70,G70) -> 880 | I70: =D70*H70 -> 3194.4 | Q70: =SUM(AA70:AH70) -> 0.363 | R70: =Y70*D70 -> 1.089 | S70: =SUM(Q70:R70) -> 1.452 | T70: =D70-S70 -> 2.178 | U70: =SUM(AJ70:AQ70) -> 319.44 | V70: =Y70*I70 -> 958.32 | W70: =SUM(U70:V70) -> 1277.76 | X70: =I70-W70 -> 1916.64 | Y70: =SUM(AS70:AZ70) -> 0.3 | AA70: 0.363 | AJ70: 319.44 | AS70: 0.3 | BB70: 0.1 | BC70: 0.1
B71: HALLWAY | F71: ='MATERIAL AND LABOR COST FOR WAL'!D47 -> 0 | G71: ='MATERIAL AND LABOR COST FOR WAL'!$F$47 -> 0 | H71: =SUM(F71,G71) -> 0 | I71: =H71*D71 -> 0
B72: Wall in Semi Gloss off White | C72: 50.6 | D72: =C72*$K$20 -> 55.66 | E72: sqm | F72: ='MATERIAL AND LABOR COST FOR WAL'!$D$48 -> 350 | G72: ='MATERIAL AND LABOR COST FOR WAL'!$F$48 -> 350 | H72: =SUM(F72,G72) -> 700 | I72: =H72*D72 -> 38962 | Q72: =SUM(AA72:AH72) -> 5.566 | R72: =Y72*D72 -> 33.396 | S72: =SUM(Q72:R72) -> 38.962 | T72: =D72-S72 -> 16.698 | U72: =SUM(AJ72:AQ72) -> 3896.2 | V72: =Y72*I72 -> 23377.2 | W72: =SUM(U72:V72) -> 27273.4 | X72: =I72-W72 -> 11688.6 | Y72: =SUM(AS72:AZ72) -> 0.6 | AA72: 5.566 | AJ72: 3896.2 | AS72: 0.6 | BB72: 0.1 | BC72: 0.1
B73: T&B | F73: ='MATERIAL AND LABOR COST FOR WAL'!D49 -> 0 | G73: ='MATERIAL AND LABOR COST FOR WAL'!F49 -> 0
B74: White Mosaic Tiles In Semi Gloss Finish | C74: 4 | D74: =C74*$K$20 -> 4.4 | E74: sqm | F74: ='MATERIAL AND LABOR COST FOR WAL'!$D$50 -> 770 | G74: ='MATERIAL AND LABOR COST FOR WAL'!$F$50 -> 350 | H74: =SUM(F74,G74) -> 1120 | I74: =H74*D74 -> 4928 | Q74: =SUM(AA74:AH74) -> 0.44 | R74: =Y74*D74 -> 1.76 | S74: =SUM(Q74:R74) -> 2.2 | T74: =D74-S74 -> 2.2 | U74: =SUM(AJ74:AQ74) -> 492.8 | V74: =Y74*I74 -> 1971.2 | W74: =SUM(U74:V74) -> 2464 | X74: =I74-W74 -> 2464 | Y74: =SUM(AS74:AZ74) -> 0.4 | AA74: 0.44 | AJ74: 492.8 | AS74: 0.4 | BB74: 0.1 | BC74: 0.3
B75: 60x60 White Tiles In Marbles in Semi Gloss Finish | C75: 3.7 | D75: =C75*$K$20 -> 4.07 | E75: sqm | F75: ='MATERIAL AND LABOR COST FOR WAL'!$D$51 -> 650 | G75: ='MATERIAL AND LABOR COST FOR WAL'!$F$51 -> 350 | H75: =SUM(F75,G75) -> 1000 | I75: =H75*D75 -> 4070 | Q75: =SUM(AA75:AH75) -> 0.6105 | R75: =Y75*D75 -> 1.4245 | S75: =SUM(Q75:R75) -> 2.035 | T75: =D75-S75 -> 2.035 | U75: =SUM(AJ75:AQ75) -> 610.5 | V75: =Y75*I75 -> 1424.5 | W75: =SUM(U75:V75) -> 2035 | X75: =I75-W75 -> 2035 | Y75: =SUM(AS75:AZ75) -> 0.35 | AA75: 0.6105 | AJ75: 610.5 | AS75: 0.35 | BB75: 0.15 | BC75: 0.3
B76: Texturia Interior Film in Wood Finish or Wood Tiles | C76: 18.8 | D76: =C76*$K$20 -> 20.68 | E76: sqm | F76: ='MATERIAL AND LABOR COST FOR WAL'!$D$52 -> 1320 | G76: ='MATERIAL AND LABOR COST FOR WAL'!$F$52 -> 700 | H76: =SUM(F76,G76) -> 2020 | I76: =H76*D76 -> 41773.6 | Q76: =SUM(AA76:AH76) -> 3.102 | R76: =Y76*D76 -> 8.272 | S76: =SUM(Q76:R76) -> 11.374 | T76: =D76-S76 -> 9.306 | U76: =SUM(AJ76:AQ76) -> 6266.04 | V76: =Y76*I76 -> 16709.44 | W76: =SUM(U76:V76) -> 22975.48 | X76: =I76-W76 -> 18798.12 | Y76: =SUM(AS76:AZ76) -> 0.4 | AA76: 3.102 | AJ76: 6266.04 | AS76: 0.4 | BB76: 0.15 | BC76: 0.15
B77: Gray Quartz or Synthetic Counter Top | C77: 1.5 | D77: =C77*$K$20 -> 1.65 | E77: sqm | F77: ='MATERIAL AND LABOR COST FOR WAL'!$D$53 -> 6600 | G77: ='MATERIAL AND LABOR COST FOR WAL'!$F$53 -> 3300 | H77: =SUM(F77,G77) -> 9900 | I77: =D77*H77 -> 16335 | Q77: =SUM(AA77:AH77) -> 0.2475 | R77: =Y77*D77 -> 0.4125 | S77: =SUM(Q77:R77) -> 0.66 | T77: =D77-S77 -> 0.99 | U77: =SUM(AJ77:AQ77) -> 2450.25 | V77: =Y77*I77 -> 4083.75 | W77: =SUM(U77:V77) -> 6534 | X77: =I77-W77 -> 9801 | Y77: =SUM(AS77:AZ77) -> 0.25 | AA77: 0.2475 | AJ77: 2450.25 | AS77: 0.25 | BB77: 0.15 | BC77: 0.15
B78: Miscellaneous and other consumables | D78: 1 | E78: lot | I78: =SUM(I52:I77)*$K$22 -> 30791.86 | Q78: =SUM(AA78:AH78) -> 0.15 | R78: =Y78*D78 -> 0.6 | S78: =SUM(Q78:R78) -> 0.75 | T78: =D78-S78 -> 0.25 | U78: =SUM(AJ78:AQ78) -> 4618.779 | V78: =Y78*I78 -> 18475.116 | W78: =SUM(U78:V78) -> 23093.895 | X78: =I78-W78 -> 7697.965 | Y78: =SUM(AS78:AZ78) -> 0.6 | AA78: 0.15 | AJ78: 4618.779 | AS78: 0.6 | BB78: 0.15 | BC78: 0.15
B79: Sub-total for Second Floor (Interior) | I79: =SUM(I53:I78) -> 338710.46 | Q79: =SUM(Q53:Q78) -> 34.6251 | R79: =SUM(R53:R78) -> 135.1245 | S79: =SUM(S53:S78) -> 169.7496 | T79: =SUM(T53:T78) -> 162.8014 | U79: =SUM(U53:U78) -> 38519.569 | V79: =SUM(V53:V78) -> 140662.68 | W79: =SUM(W53:W78) -> 179182.24 | X79: =SUM(X53:X78) -> 159528.21 | Y79: =SUM(Y53:Y78)/COUNT(Y53:Y78) -> 0.3452381 | AA79: 34.6251 | AJ79: 38519.569 | BB79: =SUM(BB53:BB78)/COUNT(BB53:BB78) -> 0.10952381 | BC79: =SUM(BC53:BC78)/COUNT(BC53:BC78) -> 0.1452381
B81: Second Floor ( Exterior )
B82: BALCONY
B83: Exposed Aggregate Contcrete Cladding | C83: 4.4 | D83: =C83*$K$20 -> 4.84 | E83: sqm | F83: ='MATERIAL AND LABOR COST FOR WAL'!$D$56 -> 350 | G83: ='MATERIAL AND LABOR COST FOR WAL'!$F$56 -> 350 | H83: =SUM(F83,G83) -> 700 | I83: =H83*D83 -> 3388 | Q83: =SUM(AA83:AH83) -> 0.484 | R83: =Y83*D83 -> 2.904 | S83: =SUM(Q83:R83) -> 3.388 | T83: =D83-S83 -> 1.452 | U83: =SUM(AJ83:AQ83) -> 338.8 | V83: =Y83*I83 -> 2032.8 | W83: =SUM(U83:V83) -> 2371.6 | X83: =I83-W83 -> 1016.4 | Y83: =SUM(AS83:AZ83) -> 0.6 | AA83: 0.484 | AJ83: 338.8 | AS83: 0.6 | BB83: 0.1 | BC83: 0.1
B84: WPC Fluted Panel | C84: 18.2 | D84: =C84*$K$20 -> 20.02 | E84: sqm | F84: ='MATERIAL AND LABOR COST FOR WAL'!$D$57 -> 960 | G84: ='MATERIAL AND LABOR COST FOR WAL'!$F$57 -> 350 | H84: =SUM(F84,G84) -> 1310 | I84: =H84*D84 -> 26226.2 | Q84: =SUM(AA84:AH84) -> 2.002 | R84: =Y84*D84 -> 0 | S84: =SUM(Q84:R84) -> 2.002 | T84: =D84-S84 -> 18.018 | U84: =SUM(AJ84:AQ84) -> 2622.62 | V84: =Y84*I84 -> 0 | W84: =SUM(U84:V84) -> 2622.62 | X84: =I84-W84 -> 23603.58 | Y84: =SUM(AS84:AZ84) -> 0 | AA84: 2.002 | AJ84: 2622.62 | AS84: 0 | BB84: 0.1 | BC84: 0.9
B85: Wall Piaint Finish ( Off White ) | C85: 52.75 | D85: =C85*$K$20 -> 58.025 | E85: sqm | F85: ='MATERIAL AND LABOR COST FOR WAL'!$D$58 -> 350 | G85: ='MATERIAL AND LABOR COST FOR WAL'!$F$58 -> 350 | H85: =SUM(F85,G85) -> 700 | I85: =H85*D85 -> 40617.5 | Q85: =SUM(AA85:AH85) -> 5.8025 | R85: =Y85*D85 -> 31.91375 | S85: =SUM(Q85:R85) -> 37.71625 | T85: =D85-S85 -> 20.30875 | U85: =SUM(AJ85:AQ85) -> 4061.75 | V85: =Y85*I85 -> 22339.625 | W85: =SUM(U85:V85) -> 26401.375 | X85: =I85-W85 -> 14216.125 | Y85: =SUM(AS85:AZ85) -> 0.55 | AA85: 5.8025 | AJ85: 4061.75 | AS85: 0.55 | BB85: 0.1 | BC85: 0.1
B86: Wall Flashing ( Dark Gray ) | C86: 50 | D86: =C86*$K$20 -> 55 | E86: l.m | F86: ='MATERIAL AND LABOR COST FOR WAL'!$D$59 -> 550 | G86: ='MATERIAL AND LABOR COST FOR WAL'!$F$59 -> 350 | H86: =SUM(F86,G86) -> 900 | I86: =H86*D86 -> 49500 | Q86: =SUM(AA86:AH86) -> 5.5 | R86: =Y86*D86 -> 22 | S86: =SUM(Q86:R86) -> 27.5 | T86: =D86-S86 -> 27.5 | U86: =SUM(AJ86:AQ86) -> 4950 | V86: =Y86*I86 -> 19800 | W86: =SUM(U86:V86) -> 24750 | X86: =I86-W86 -> 24750 | Y86: =SUM(AS86:AZ86) -> 0.4 | AA86: 5.5 | AJ86: 4950 | AS86: 0.4 | BB86: 0.1 | BC86: 0.5
B87: Natural Limestone Tiles Texture Running Ashlar Pattern | C87: 12.22 | D87: =C87*$K$20 -> 13.442 | E87: sqm | F87: ='MATERIAL AND LABOR COST FOR WAL'!$D$60 -> 950 | G87: ='MATERIAL AND LABOR COST FOR WAL'!$F$60 -> 350 | H87: =SUM(F87,G87) -> 1300 | I87: =H87*D87 -> 17474.6 | Q87: =SUM(AA87:AH87) -> 1.3442 | R87: =Y87*D87 -> 4.0326 | S87: =SUM(Q87:R87) -> 5.3768 | T87: =D87-S87 -> 8.0652 | U87: =SUM(AJ87:AQ87) -> 1747.46 | V87: =Y87*I87 -> 5242.38 | W87: =SUM(U87:V87) -> 6989.84 | X87: =I87-W87 -> 10484.76 | Y87: =SUM(AS87:AZ87) -> 0.3 | AA87: 1.3442 | AJ87: 1747.46 | AS87: 0.3 | BB87: 0.1 | BC87: 0.4
B88: Glass Railings 10mm THK | C88: 25.26 | D88: =C88*$K$20 -> 27.786 | E88: smq | F88: ='MATERIAL AND LABOR COST FOR WAL'!$D$87 -> 6300 | G88: ='MATERIAL AND LABOR COST FOR WAL'!$F$87 -> 1260 | H88: =SUM(F88,G88) -> 7560 | I88: =D88*H88 -> 210062.16 | Q88: =SUM(AA88:AH88) -> 2.7786 | R88: =Y88*D88 -> 2.7786 | S88: =SUM(Q88:R88) -> 5.5572 | T88: =D88-S88 -> 22.2288 | U88: =SUM(AJ88:AQ88) -> 21006.216 | V88: =Y88*I88 -> 21006.216 | W88: =SUM(U88:V88) -> 42012.432 | X88: =I88-W88 -> 168049.73 | Y88: =SUM(AS88:AZ88) -> 0.1 | AA88: 2.7786 | AJ88: 21006.216 | AS88: 0.1 | BB88: 0.1 | BC88: 0.1
B89: Miscellaneous and other consumables | D89: 1 | E89: lot | I89: =SUM(I83:I88)*$K$22 -> 34726.846 | Q89: =SUM(AA89:AH89) -> 0.1 | R89: =Y89*D89 -> 0.6 | S89: =SUM(Q89:R89) -> 0.7 | T89: =D89-S89 -> 0.3 | U89: =SUM(AJ89:AQ89) -> 3472.6846 | V89: =Y89*I89 -> 20836.108 | W89: =SUM(U89:V89) -> 24308.792 | X89: =I89-W89 -> 10418.054 | Y89: =SUM(AS89:AZ89) -> 0.6 | AA89: 0.1 | AJ89: 3472.6846 | AS89: 0.6 | BB89: 0.1 | BC89: 0.2
B90: Sub-total For Second Floor (Exterior) | I90: =SUM(I83:I89) -> 381995.31 | Q90: =SUM(Q83:Q89) -> 18.0113 | R90: =SUM(R83:R89) -> 64.22895 | S90: =SUM(S83:S89) -> 82.24025 | T90: =SUM(T83:T89) -> 97.87275 | U90: =SUM(U83:U89) -> 38199.531 | V90: =SUM(V83:V89) -> 91257.129 | W90: =SUM(W83:W89) -> 129456.66 | X90: =SUM(X83:X89) -> 252538.65 | Y90: =SUM(Y83:Y89)/COUNT(Y83:Y89) -> 0.36428571 | AA90: 18.0113 | AJ90: 38199.531 | BB90: =SUM(BB83:BB89)/COUNT(BB83:BB89) -> 0.1 | BC90: =SUM(BC83:BC89)/COUNT(BC83:BC89) -> 0.32857143
B92: Third Floor ( Interior )
B93: WALK IN CLOSET
B94: White Semi Gloss | C94: 40.5 | D94: =C94*$K$20 -> 44.55 | E94: sqm | F94: ='MATERIAL AND LABOR COST FOR WAL'!$D$64 -> 350 | G94: ='MATERIAL AND LABOR COST FOR WAL'!$F$64 -> 350 | H94: =SUM(F94,G94) -> 700 | I94: =D94*H94 -> 31185 | Q94: =SUM(AA94:AH94) -> 4.455 | R94: =Y94*D94 -> 13.365 | S94: =SUM(Q94:R94) -> 17.82 | T94: =D94-S94 -> 26.73 | U94: =SUM(AJ94:AQ94) -> 3118.5 | V94: =Y94*I94 -> 9355.5 | W94: =SUM(U94:V94) -> 12474 | X94: =I94-W94 -> 18711 | Y94: =SUM(AS94:AZ94) -> 0.3 | AA94: 4.455 | AJ94: 3118.5 | AS94: 0.3 | BB94: 0.1 | BC94: 0.4
B95: MASTER'S BEDROOM | F95: ='MATERIAL AND LABOR COST FOR WAL'!D65 -> 0 | G95: ='MATERIAL AND LABOR COST FOR WAL'!F65 -> 0 | H95: =SUM(F95,G95) -> 0 | I95: =D95*H95 -> 0 | Q95: =SUM(AA95:AH95) -> 0 | R95: =Y95*D95 -> 0 | S95: =SUM(Q95:R95) -> 0 | T95: =D95-S95 -> 0 | U95: =SUM(AJ95:AQ95) -> 0 | V95: =Y95*I95 -> 0 | W95: =SUM(U95:V95) -> 0 | X95: =I95-W95 -> 0 | Y95: =SUM(AS95:AZ95) -> 0.3 | AA95: 0 | AJ95: 0 | AS95: 0.3 | BB95: 0.15 | BC95: 0.3
B96: Wall in White Textured Wallpaper Finish | C96: 41.6 | D96: =C96*$K$20 -> 45.76 | E96: sqm | F96: ='MATERIAL AND LABOR COST FOR WAL'!$D$66 -> 350 | G96: ='MATERIAL AND LABOR COST FOR WAL'!$F$66 -> 350 | H96: =SUM(F96,G96) -> 700 | I96: =D96*H96 -> 32032 | Q96: =SUM(AA96:AH96) -> 6.864 | R96: =Y96*D96 -> 18.304 | S96: =SUM(Q96:R96) -> 25.168 | T96: =D96-S96 -> 20.592 | U96: =SUM(AJ96:AQ96) -> 4804.8 | V96: =Y96*I96 -> 12812.8 | W96: =SUM(U96:V96) -> 17617.6 | X96: =I96-W96 -> 14414.4 | Y96: =SUM(AS96:AZ96) -> 0.4 | AA96: 6.864 | AJ96: 4804.8 | AS96: 0.4 | BB96: 0.15 | BC96: 0.15
B97: Wall in Wood Fluted Panel Finish | C97: 6.1 | D97: =C97*$K$20 -> 6.71 | E97: sqm | F97: ='MATERIAL AND LABOR COST FOR WAL'!$D$67 -> 1100 | G97: ='MATERIAL AND LABOR COST FOR WAL'!$F$67 -> 330 | H97: =SUM(F97,G97) -> 1430 | I97: =D97*H97 -> 9595.3 | Q97: =SUM(AA97:AH97) -> 1.0065 | R97: =Y97*D97 -> 2.684 | S97: =SUM(Q97:R97) -> 3.6905 | T97: =D97-S97 -> 3.0195 | U97: =SUM(AJ97:AQ97) -> 1439.295 | V97: =Y97*I97 -> 3838.12 | W97: =SUM(U97:V97) -> 5277.415 | X97: =I97-W97 -> 4317.885 | Y97: =SUM(AS97:AZ97) -> 0.4 | AA97: 1.0065 | AJ97: 1439.295 | AS97: 0.4 | BB97: 0.15 | BC97: 0.15
B98: MASTER'S T&B | F98: ='MATERIAL AND LABOR COST FOR WAL'!D68 -> 0 | G98: ='MATERIAL AND LABOR COST FOR WAL'!F68 -> 0 | H98: =SUM(F98,G98) -> 0 | I98: =D98*H98 -> 0 | Q98: =SUM(AA98:AH98) -> 0 | R98: =Y98*D98 -> 0 | S98: =SUM(Q98:R98) -> 0 | T98: =D98-S98 -> 0 | U98: =SUM(AJ98:AQ98) -> 0 | V98: =Y98*I98 -> 0 | W98: =SUM(U98:V98) -> 0 | X98: =I98-W98 -> 0 | Y98: =SUM(AS98:AZ98) -> 0.4 | AA98: 0 | AJ98: 0 | AS98: 0.4 | BB98: 0.15 | BC98: 0.15
B99: 60x120 Marbles Tiles in High Gloss Finish | C99: 30.6 | D99: =C99*$K$20 -> 33.66 | E99: sqm | F99: ='MATERIAL AND LABOR COST FOR WAL'!$D$69 -> 450 | G99: ='MATERIAL AND LABOR COST FOR WAL'!$F$69 -> 350 | H99: =SUM(F99,G99) -> 800 | I99: =D99*H99 -> 26928 | Q99: =SUM(AA99:AH99) -> 5.049 | R99: =Y99*D99 -> 15.147 | S99: =SUM(Q99:R99) -> 20.196 | T99: =D99-S99 -> 13.464 | U99: =SUM(AJ99:AQ99) -> 4039.2 | V99: =Y99*I99 -> 12117.6 | W99: =SUM(U99:V99) -> 16156.8 | X99: =I99-W99 -> 10771.2 | Y99: =SUM(AS99:AZ99) -> 0.45 | AA99: 5.049 | AJ99: 4039.2 | AS99: 0.45 | BB99: 0.15 | BC99: 0.3
B100: 60x120 Light Biege Tiles in High Gloss Finish | C100: 1 | D100: =C100*$K$20 -> 1.1 | E100: sqm | F100: ='MATERIAL AND LABOR COST FOR WAL'!$D$70 -> 330 | G100: ='MATERIAL AND LABOR COST FOR WAL'!$F$70 -> 350 | H100: =SUM(F100,G100) -> 680 | I100: =D100*H100 -> 748 | Q100: =SUM(AA100:AH100) -> 0.165 | R100: =Y100*D100 -> 0.495 | S100: =SUM(Q100:R100) -> 0.66 | T100: =D100-S100 -> 0.44 | U100: =SUM(AJ100:AQ100) -> 112.2 | V100: =Y100*I100 -> 336.6 | W100: =SUM(U100:V100) -> 448.8 | X100: =I100-W100 -> 299.2 | Y100: =SUM(AS100:AZ100) -> 0.45 | AA100: 0.165 | AJ100: 112.2 | AS100: 0.45 | BB100: 0.15 | BC100: 0.3
B101: MEMORABILIA | F101: ='MATERIAL AND LABOR COST FOR WAL'!D71 -> 0 | G101: ='MATERIAL AND LABOR COST FOR WAL'!F71 -> 0 | H101: =SUM(F101,G101) -> 0 | I101: =D101*H101 -> 0 | Q101: =SUM(AA101:AH101) -> 0 | R101: =Y101*D101 -> 0 | S101: =SUM(Q101:R101) -> 0 | T101: =D101-S101 -> 0 | U101: =SUM(AJ101:AQ101) -> 0 | V101: =Y101*I101 -> 0 | W101: =SUM(U101:V101) -> 0 | X101: =I101-W101 -> 0 | Y101: =SUM(AS101:AZ101) -> 0.15 | AA101: 0 | AJ101: 0 | AS101: 0.15 | BB101: 0.15 | BC101: 0.15
B102: Wall Cladding in Wood Laminated Finish | C102: 3.6 | D102: =C102*$K$20 -> 3.96 | E102: sqm | F102: ='MATERIAL AND LABOR COST FOR WAL'!$D$72 -> 1100 | G102: ='MATERIAL AND LABOR COST FOR WAL'!$F$72 -> 350 | H102: =SUM(F102,G102) -> 1450 | I102: =D102*H102 -> 5742 | Q102: =SUM(AA102:AH102) -> 0.594 | R102: =Y102*D102 -> 0.792 | S102: =SUM(Q102:R102) -> 1.386 | T102: =D102-S102 -> 2.574 | U102: =SUM(AJ102:AQ102) -> 861.3 | V102: =Y102*I102 -> 1148.4 | W102: =SUM(U102:V102) -> 2009.7 | X102: =I102-W102 -> 3732.3 | Y102: =SUM(AS102:AZ102) -> 0.2 | AA102: 0.594 | AJ102: 861.3 | AS102: 0.2 | BB102: 0.15 | BC102: 0.15
B103: Wall in Light Biege Semi- Gloss Painted Finish | C103: 24.2 | D103: =C103*$K$20 -> 26.62 | E103: sqm | F103: ='MATERIAL AND LABOR COST FOR WAL'!$D$73 -> 350 | G103: ='MATERIAL AND LABOR COST FOR WAL'!$F$73 -> 350 | H103: =SUM(F103,G103) -> 700 | I103: =D103*H103 -> 18634 | Q103: =SUM(AA103:AH103) -> 3.993 | R103: =Y103*D103 -> 13.31 | S103: =SUM(Q103:R103) -> 17.303 | T103: =D103-S103 -> 9.317 | U103: =SUM(AJ103:AQ103) -> 2795.1 | V103: =Y103*I103 -> 9317 | W103: =SUM(U103:V103) -> 12112.1 | X103: =I103-W103 -> 6521.9 | Y103: =SUM(AS103:AZ103) -> 0.5 | AA103: 3.993 | AJ103: 2795.1 | AS103: 0.5 | BB103: 0.15 | BC103: 0.1
B104: HALLWAY | F104: ='MATERIAL AND LABOR COST FOR WAL'!D74 -> 0 | G104: ='MATERIAL AND LABOR COST FOR WAL'!F74 -> 0 | H104: =SUM(F104,G104) -> 0 | I104: =D104*H104 -> 0 | Q104: =SUM(AA104:AH104) -> 0 | R104: =Y104*D104 -> 0 | S104: =SUM(Q104:R104) -> 0 | T104: =D104-S104 -> 0 | U104: =SUM(AJ104:AQ104) -> 0 | V104: =Y104*I104 -> 0 | W104: =SUM(U104:V104) -> 0 | X104: =I104-W104 -> 0 | Y104: =SUM(AS104:AZ104) -> 0.15 | AA104: 0 | AJ104: 0 | AS104: 0.15 | BB104: 0.15 | BC104: 0.15
B105: Wall in Semi Gloss off White Painted Finish | C105: 27.5 | D105: =C105*$K$20 -> 30.25 | E105: sqm | F105: ='MATERIAL AND LABOR COST FOR WAL'!$D$75 -> 350 | G105: ='MATERIAL AND LABOR COST FOR WAL'!$F$75 -> 350 | H105: =SUM(F105,G105) -> 700 | I105: =D105*H105 -> 21175 | Q105: =SUM(AA105:AH105) -> 4.5375 | R105: =Y105*D105 -> 12.1 | S105: =SUM(Q105:R105) -> 16.6375 | T105: =D105-S105 -> 13.6125 | U105: =SUM(AJ105:AQ105) -> 3176.25 | V105: =Y105*I105 -> 8470 | W105: =SUM(U105:V105) -> 11646.25 | X105: =I105-W105 -> 9528.75 | Y105: =SUM(AS105:AZ105) -> 0.4 | AA105: 4.5375 | AJ105: 3176.25 | AS105: 0.4 | BB105: 0.15 | BC105: 0.25
B106: VIEWDECK | Q106: =SUM(AA106:AH106) -> 0 | R106: =Y106*D106 -> 0 | S106: =SUM(Q106:R106) -> 0 | T106: =D106-S106 -> 0 | U106: =SUM(AJ106:AQ106) -> 0 | V106: =Y106*I106 -> 0 | W106: =SUM(U106:V106) -> 0 | X106: =I106-W106 -> 0 | Y106: =SUM(AS106:AZ106) -> 0.4 | AA106: 0 | AJ106: 0 | AS106: 0.4 | BB106: 0.15 | BC106: 0.15
B107: Wall in Light Biege Semi- Gloss Painted Finish | C107: 30.26 | D107: =C107*$K$20 -> 33.286 | E107: sqm | F107: ='MATERIAL AND LABOR COST FOR WAL'!$D$76 -> 330 | G107: ='MATERIAL AND LABOR COST FOR WAL'!$F$76 -> 350 | H107: =SUM(F107,G107) -> 680 | I107: =D107*H107 -> 22634.48 | Q107: =SUM(AA107:AH107) -> 4.9929 | R107: =Y107*D107 -> 6.6572 | S107: =SUM(Q107:R107) -> 11.6501 | T107: =D107-S107 -> 21.6359 | U107: =SUM(AJ107:AQ107) -> 3395.172 | V107: =Y107*I107 -> 4526.896 | W107: =SUM(U107:V107) -> 7922.068 | X107: =I107-W107 -> 14712.412 | Y107: =SUM(AS107:AZ107) -> 0.2 | AA107: 4.9929 | AJ107: 3395.172 | AS107: 0.2 | BB107: 0.15 | BC107: 0.15
B108: Miscellaneous and other consumables | D108: 1 | E108: lot | I108: =SUM(I94:I105)*$K$22 -> 14603.93 | Q108: =SUM(AA108:AH108) -> 0.15 | R108: =Y108*D108 -> 0.5 | S108: =SUM(Q108:R108) -> 0.65 | T108: =D108-S108 -> 0.35 | U108: =SUM(AJ108:AQ108) -> 2190.5895 | V108: =Y108*I108 -> 7301.965 | W108: =SUM(U108:V108) -> 9492.5545 | X108: =I108-W108 -> 5111.3755 | Y108: =SUM(AS108:AZ108) -> 0.5 | AA108: 0.15 | AJ108: 2190.5895 | AS108: 0.5 | BB108: 0.15 | BC108: 0.25
B109: Sub-total For Third Floor (Interior) | I109: =SUM(I94:I108) -> 183277.71 | Q109: =SUM(Q94:Q108) -> 31.8069 | R109: =SUM(R94:R108) -> 83.3542 | S109: =SUM(S94:S108) -> 115.1611 | T109: =SUM(T94:T108) -> 111.7349 | U109: =SUM(U94:U108) -> 25932.406 | V109: =SUM(V94:V108) -> 69224.881 | W109: =SUM(W94:W108) -> 95157.288 | X109: =SUM(X94:X108) -> 88120.423 | Y109: =SUM(Y94:Y108)/COUNT(Y94:Y108) -> 0.34666667 | AA109: 31.8069 | AJ109: 25932.406 | BB109: =SUM(BB94:BB108)/COUNT(BB94:BB108) -> 0.14666667 | BC109: =SUM(BC94:BC108)/COUNT(BC94:BC108) -> 0.20666667
B111: Third Floor ( Exterior )
B112: BALCONY
B113: Wall Piaint Finish ( Off White ) | C113: 49.9 | D113: =C113*$K$20 -> 54.89 | E113: sqm | F113: ='MATERIAL AND LABOR COST FOR WAL'!$D$79 -> 350 | G113: ='MATERIAL AND LABOR COST FOR WAL'!$F$79 -> 350 | H113: =SUM(F113,G113) -> 700 | I113: =D113*H113 -> 38423 | Q113: =SUM(AA113:AH113) -> 7.1357 | R113: =Y113*D113 -> 16.467 | S113: =SUM(Q113:R113) -> 23.6027 | T113: =D113-S113 -> 31.2873 | U113: =SUM(AJ113:AQ113) -> 4994.99 | V113: =Y113*I113 -> 11526.9 | W113: =SUM(U113:V113) -> 16521.89 | X113: =I113-W113 -> 21901.11 | Y113: =SUM(AS113:AZ113) -> 0.3 | AA113: 7.1357 | AJ113: 4994.99 | AS113: 0.3 | BB113: 0.13 | BC113: 0.17
B114: Natural Limestone Tiles Texture Running Ashlar Pattern | C114: 43.76 | D114: =C114*$K$20 -> 48.136 | E114: sqm | F114: ='MATERIAL AND LABOR COST FOR WAL'!$D$80 -> 950 | G114: ='MATERIAL AND LABOR COST FOR WAL'!$F$80 -> 350 | H114: =SUM(F114,G114) -> 1300 | I114: =D114*H114 -> 62576.8 | Q114: =SUM(AA114:AH114) -> 6.25768 | R114: =Y114*D114 -> 17.81032 | S114: =SUM(Q114:R114) -> 24.068 | T114: =D114-S114 -> 24.068 | U114: =SUM(AJ114:AQ114) -> 8134.984 | V114: =Y114*I114 -> 23153.416 | W114: =SUM(U114:V114) -> 31288.4 | X114: =I114-W114 -> 31288.4 | Y114: =SUM(AS114:AZ114) -> 0.37 | AA114: 6.25768 | AJ114: 8134.984 | AS114: 0.37 | BB114: 0.13 | BC114: 0.5
B115: Concrete Cladding With Groove Lines | C115: 67.8 | D115: =C115*$K$20 -> 74.58 | E115: sqm | F115: ='MATERIAL AND LABOR COST FOR WAL'!$D$81 -> 350 | G115: ='MATERIAL AND LABOR COST FOR WAL'!$F$81 -> 350 | H115: =SUM(F115,G115) -> 700 | I115: =D115*H115 -> 52206 | Q115: =SUM(AA115:AH115) -> 9.6954 | R115: =Y115*D115 -> 14.916 | S115: =SUM(Q115:R115) -> 24.6114 | T115: =D115-S115 -> 49.9686 | U115: =SUM(AJ115:AQ115) -> 6786.78 | V115: =Y115*I115 -> 10441.2 | W115: =SUM(U115:V115) -> 17227.98 | X115: =I115-W115 -> 34978.02 | Y115: =SUM(AS115:AZ115) -> 0.2 | AA115: 9.6954 | AJ115: 6786.78 | AS115: 0.2 | BB115: 0.13 | BC115: 0.13
B116: Glass Railings 10mm THK | C116: 37.5 | D116: =C116*$K$20 -> 41.25 | E116: sqm | F116: ='MATERIAL AND LABOR COST FOR WAL'!$D$88 -> 6300 | G116: ='MATERIAL AND LABOR COST FOR WAL'!$F$88 -> 1260 | H116: =SUM(F116,G116) -> 7560 | I116: =D116*H116 -> 311850 | Q116: =SUM(AA116:AH116) -> 5.3625 | R116: =Y116*D116 -> 8.25 | S116: =SUM(Q116:R116) -> 13.6125 | T116: =D116-S116 -> 27.6375 | U116: =SUM(AJ116:AQ116) -> 40540.5 | V116: =Y116*I116 -> 62370 | W116: =SUM(U116:V116) -> 102910.5 | X116: =I116-W116 -> 208939.5 | Y116: =SUM(AS116:AZ116) -> 0.2 | AA116: 5.3625 | AJ116: 40540.5 | AS116: 0.2 | BB116: 0.13 | BC116: 0.13
B117: Miscellaneous and other consumables | I117: =SUM(I113:I116)*$K$22 -> 46505.58 | Q117: =SUM(AA117:AH117) -> 0 | R117: =Y117*D117 -> 0 | S117: =SUM(Q117:R117) -> 0 | T117: =D117-S117 -> 0 | U117: =SUM(AJ117:AQ117) -> 6045.7254 | V117: =Y117*I117 -> 18602.232 | W117: =SUM(U117:V117) -> 24647.957 | X117: =I117-W117 -> 21857.623 | Y117: =SUM(AS117:AZ117) -> 0.4 | AA117: 0 | AJ117: 6045.7254 | AS117: 0.4 | BB117: 0.13 | BC117: 0.27
...

Sheet CABINETS
A13: Project name : | B13: PROPOSED THREE STORY RESIDENCE
A14: Location : | B14: GRAND CENTENIAL HOMES KAWIT CAVITE
A15: Date : | B15: =TODAY() -> 46251
AI16: QUANTITY | AR16: AMOUNT | BA16: ACCOMPLISHMENT | BC16: PREVIOUS ACCOMPLISHMENT
A17: ITEM NO | B17: Description | C17: QUANTITY | D17: QUANTITY | E17: UNIT | F17: Material Cost Php/unit | G17: Labor and Equipment Cost Php/unit | H17: Total Cost Php/Unit | I17: Total Amount Php | Y17: QUANTITY | AC17: AMOUNT | AG17: PERCENTAGE | AI17: BILLING 1 | AJ17: BILLING 2 | AK17: BILLING 3 | AL17: BILLING 4 | AM17: BILLING 5 | AN17: BILLING 6 | AO17: BILLING 7 | AP17: BILLING 8 | AR17: BILLING 1 | AS17: BILLING 2 | AT17: BILLING 3 | AU17: BILLING 4 | AV17: BILLING 5 | AW17: BILLING 6 | AX17: BILLING 7 | AY17: BILLING 8 | BA17: BILLING | BC17: BILLING 1 | BD17: BILLING 2 | BE17: BILLING 3 | BF17: BILLING 4 | BG17: BILLING 5 | BH17: BILLING 6 | BI17: BILLING 7 | BJ17: BILLING 8
B18: Cabinets | Y18: PREVIOUS | Z18: THIS DATE | AA18: TO DATE | AB18: BALANCE | AC18: PREVIOUS | AD18: THIS DATE | AE18: TO DATE | AF18: BALANCE | AG18: Accomplishment
B19: GROUND FLOOR
B20: LIving Area ( Tv rack with Cabinets )
B21: UV Board Marble | C21: 6.7 | D21: =C21*$L$23 -> 7.37 | E21: sq.m | F21: ='Material and Labor Cost'!$D$20 -> 555 | G21: ='Material and Labor Cost'!$F$20 -> 300 | H21: =SUM(F21:G21) -> 855 | I21: =H21*D21 -> 6301.35 | Y21: =SUM(AI21:AP21) -> 0 | Z21: =D21*AG21 -> 2.211 | AA21: =SUM(Y21:Z21) -> 2.211 | AB21: =D21-AA21 -> 5.159 | AC21: =SUM(AR20:AY20) -> 0 | AD21: =AG21*I21 -> 1890.405 | AE21: =SUM(AC21:AD21) -> 1890.405 | AF21: =I21-AE21 -> 4410.945 | AG21: =BA21 -> 0.3 | AI21: 0 | BA21: 0.3 | BC21: =SUM(BS20:BZ20) -> 0 | BD21: =SUM(BN20:BT20) -> 0 | BE21: =SUM(BU20:CB20) -> 0 | BF21: =SUM(BV20:CC20) -> 0 | BG21: =SUM(BW20:CD20) -> 0 | BH21: =SUM(BX20:CE20) -> 0 | BI21: =SUM(BY20:CF20) -> 0 | BJ21: =SUM(BZ20:CG20) -> 0
B22: 3/4'' Marine Plywood | C22: 45.74 | D22: =C22*$L$23 -> 50.314 | E22: sq.m | F22: ='Material and Labor Cost'!$D$21 -> 576 | G22: ='Material and Labor Cost'!$F$21 -> 300 | H22: =SUM(F22:G22) -> 876 | I22: =H22*D22 -> 44075.064 | L22: Multiplier Mark up | Y22: =SUM(AI22:AP22) -> 0 | Z22: =D22*AG22 -> 15.0942 | AA22: =SUM(Y22:Z22) -> 15.0942 | AB22: =D22-AA22 -> 35.2198 | AC22: =SUM(AR21:AY21) -> 0 | AD22: =AG22*I22 -> 13222.519 | AE22: =SUM(AC22:AD22) -> 13222.519 | AF22: =I22-AE22 -> 30852.545 | AG22: =BA22 -> 0.3 | AI22: 0 | BA22: 0.3 | BC22: =SUM(BS21:BZ21) -> 0 | BD22: =SUM(BN21:BT21) -> 0 | BE22: =SUM(BU21:CB21) -> 0 | BF22: =SUM(BV21:CC21) -> 0 | BG22: =SUM(BW21:CD21) -> 0 | BH22: =SUM(BX21:CE21) -> 0 | BI22: =SUM(BY21:CF21) -> 0 | BJ22: =SUM(BZ21:CG21) -> 0
B23: Pvc Fluted Panels | C23: 5 | D23: =C23*$L$23 -> 5.5 | E23: sq.m | F23: ='Material and Labor Cost'!$D$22 -> 880 | G23: ='Material and Labor Cost'!$F$22 -> 450 | H23: =SUM(F23:G23) -> 1330 | I23: =H23*D23 -> 7315 | L23: 1.1 | Y23: =SUM(AI23:AP23) -> 0 | Z23: =D23*AG23 -> 0 | AA23: =SUM(Y23:Z23) -> 0 | AB23: =D23-AA23 -> 5.5 | AC23: =SUM(AR22:AY22) -> 0 | AD23: =AG23*I23 -> 0 | AE23: =SUM(AC23:AD23) -> 0 | AF23: =I23-AE23 -> 7315 | AG23: =BA23 -> 0 | AI23: 0 | BA23: =SUM(BK22:BQ22) -> 0 | BC23: =SUM(BS22:BZ22) -> 0 | BD23: =SUM(BN22:BT22) -> 0 | BE23: =SUM(BU22:CB22) -> 0 | BF23: =SUM(BV22:CC22) -> 0 | BG23: =SUM(BW22:CD22) -> 0 | BH23: =SUM(BX22:CE22) -> 0 | BI23: =SUM(BY22:CF22) -> 0 | BJ23: =SUM(BZ22:CG22) -> 0
B24: 1/2'' Backing Marine plywood | C24: 12 | D24: =C24*$L$23 -> 13.2 | E24: sq.m | F24: ='Material and Labor Cost'!$D$23 -> 330 | G24: ='Material and Labor Cost'!$F$23 -> 165 | H24: =SUM(F24:G24) -> 495 | I24: =H24*D24 -> 6534 | Y24: =SUM(AI24:AP24) -> 0 | Z24: =D24*AG24 -> 0 | AA24: =SUM(Y24:Z24) -> 0 | AB24: =D24-AA24 -> 13.2 | AC24: =SUM(AR23:AY23) -> 0 | AD24: =AG24*I24 -> 0 | AE24: =SUM(AC24:AD24) -> 0 | AF24: =I24-AE24 -> 6534 | AG24: =BA24 -> 0 | AI24: 0 | BA24: =SUM(BK23:BQ23) -> 0 | BC24: =SUM(BS23:BZ23) -> 0 | BD24: =SUM(BN23:BT23) -> 0 | BE24: =SUM(BU23:CB23) -> 0 | BF24: =SUM(BV23:CC23) -> 0 | BG24: =SUM(BW23:CD23) -> 0 | BH24: =SUM(BX23:CE23) -> 0 | BI24: =SUM(BY23:CF23) -> 0 | BJ24: =SUM(BZ23:CG23) -> 0
B25: Warm Strip Lights | C25: 2.31 | D25: =C25*$L$23 -> 2.541 | E25: l.m | F25: ='Material and Labor Cost'!$D$24 -> 220 | G25: ='Material and Labor Cost'!$F$24 -> 110 | H25: =SUM(F25:G25) -> 330 | I25: =H25*D25 -> 838.53 | Y25: =SUM(AI25:AP25) -> 0 | Z25: =D25*AG25 -> 0 | AA25: =SUM(Y25:Z25) -> 0 | AB25: =D25-AA25 -> 2.541 | AC25: =SUM(AR24:AY24) -> 0 | AD25: =AG25*I25 -> 0 | AE25: =SUM(AC25:AD25) -> 0 | AF25: =I25-AE25 -> 838.53 | AG25: =BA25 -> 0 | AI25: 0 | BA25: =SUM(BK24:BQ24) -> 0 | BC25: =SUM(BS24:BZ24) -> 0 | BD25: =SUM(BN24:BT24) -> 0 | BE25: =SUM(BU24:CB24) -> 0 | BF25: =SUM(BV24:CC24) -> 0 | BG25: =SUM(BW24:CD24) -> 0 | BH25: =SUM(BX24:CE24) -> 0 | BI25: =SUM(BY24:CF24) -> 0 | BJ25: =SUM(BZ24:CG24) -> 0
B26: Paint Finish | C26: 34.04 | D26: =C26*$L$23 -> 37.444 | E26: sq.m | F26: ='Material and Labor Cost'!$D$25 -> 555 | G26: ='Material and Labor Cost'!$F$25 -> 275 | H26: =SUM(F26:G26) -> 830 | I26: =H26*D26 -> 31078.52 | L26: Miscellaneous | Y26: =SUM(AI26:AP26) -> 0 | Z26: =D26*AG26 -> 0 | AA26: =SUM(Y26:Z26) -> 0 | AB26: =D26-AA26 -> 37.444 | AC26: =SUM(AR25:AY25) -> 0 | AD26: =AG26*I26 -> 0 | AE26: =SUM(AC26:AD26) -> 0 | AF26: =I26-AE26 -> 31078.52 | AG26: =BA26 -> 0 | AI26: 0 | BA26: =SUM(BK25:BQ25) -> 0 | BC26: =SUM(BS25:BZ25) -> 0 | BD26: =SUM(BN25:BT25) -> 0 | BE26: =SUM(BU25:CB25) -> 0 | BF26: =SUM(BV25:CC25) -> 0 | BG26: =SUM(BW25:CD25) -> 0 | BH26: =SUM(BX25:CE25) -> 0 | BI26: =SUM(BY25:CF25) -> 0 | BJ26: =SUM(BZ25:CG25) -> 0
B27: Miscellaneous and other Consumables | D27: 1 | E27: lot | I27: =SUM(I21:I26)*$L$27 -> 11537.096 | L27: 0.12 | Y27: =SUM(AI27:AP27) -> 0 | Z27: =D27*AG27 -> 0 | AA27: =SUM(Y27:Z27) -> 0 | AB27: =D27-AA27 -> 1 | AC27: =SUM(AR26:AY26) -> 0 | AD27: =AG27*I27 -> 0 | AE27: =SUM(AC27:AD27) -> 0 | AF27: =I27-AE27 -> 11537.096 | AG27: =BA27 -> 0 | AI27: 0 | BA27: =SUM(BK26:BQ26) -> 0 | BC27: =SUM(BS26:BZ26) -> 0 | BD27: =SUM(BN26:BT26) -> 0 | BE27: =SUM(BU26:CB26) -> 0 | BF27: =SUM(BV26:CC26) -> 0 | BG27: =SUM(BW26:CD26) -> 0 | BH27: =SUM(BX26:CE26) -> 0 | BI27: =SUM(BY26:CF26) -> 0 | BJ27: =SUM(BZ26:CG26) -> 0
B28: LIving Area ( Tv rack with Cabinets ) Sub-total: | I28: =SUM(I21:I27) -> 107679.56 | L28: 0.8 | Y28: =SUM(Y21:Y27) -> 0 | Z28: =SUM(Z21:Z27) -> 17.3052 | AA28: =SUM(AA21:AA27) -> 17.3052 | AB28: =SUM(AB21:AB27) -> 100.0638 | AC28: =SUM(AC21:AC27) -> 0 | AD28: =SUM(AD21:AD27) -> 15112.924 | AE28: =SUM(AE21:AE27) -> 15112.924 | AF28: =SUM(AF21:AF27) -> 92566.635 | AG28: =BA28 -> 0.085714286 | AI28: 0 | BA28: =SUM(BA21:BA27)/COUNT(BA21:BA27) -> 0.085714286 | BC28: =SUM(BC21:BC27)/COUNT(BC21:BC27) -> 0 | BD28: =SUM(BD21:BD27)/COUNT(BD21:BD27) -> 0 | BE28: =SUM(BE21:BE27)/COUNT(BE21:BE27) -> 0 | BF28: =SUM(BF21:BF27)/COUNT(BF21:BF27) -> 0 | BG28: =SUM(BG21:BG27)/COUNT(BG21:BG27) -> 0 | BH28: =SUM(BH21:BH27)/COUNT(BH21:BH27) -> 0 | BI28: =SUM(BI21:BI27)/COUNT(BI21:BI27) -> 0 | BJ28: =SUM(BJ21:BJ27)/COUNT(BJ21:BJ27) -> 0
B29: LIving Area ( Storage Cabinets ) | AG29: =BA29 -> 0
B30: 3/4'' Marine Plywood | C30: 7.9 | D30: =C30*$L$23 -> 8.69 | E30: sq.m | F30: ='Material and Labor Cost'!$D$21 -> 576 | G30: ='Material and Labor Cost'!$F$21 -> 300 | H30: =SUM(F30:G30) -> 876 | I30: =H30*D30 -> 7612.44 | Y30: =SUM(AI30:AP30) -> 0 | Z30: =D30*AG30 -> 2.607 | AA30: =SUM(Y30:Z30) -> 2.607 | AB30: =D30-AA30 -> 6.083 | AC30: =SUM(AR29:AY29) -> 0 | AD30: =AG30*I30 -> 2283.732 | AE30: =SUM(AC30:AD30) -> 2283.732 | AF30: =I30-AE30 -> 5328.708 | AG30: =BA30 -> 0.3 | AI30: 0 | BA30: 0.3 | BC30: =SUM(BS29:BZ29) -> 0 | BD30: =SUM(BN29:BT29) -> 0 | BE30: =SUM(BU29:CB29) -> 0 | BF30: =SUM(BV29:CC29) -> 0 | BG30: =SUM(BW29:CD29) -> 0 | BH30: =SUM(BX29:CE29) -> 0 | BI30: =SUM(BY29:CF29) -> 0 | BJ30: =SUM(BZ29:CG29) -> 0
B31: 1/2'' Backing Marine plywood | C31: 2.1 | D31: =C31*$L$23 -> 2.31 | E31: sq.m | F31: ='Material and Labor Cost'!$D$23 -> 330 | G31: ='Material and Labor Cost'!$F$23 -> 165 | H31: =SUM(F31:G31) -> 495 | I31: =H31*D31 -> 1143.45 | Y31: =SUM(AI31:AP31) -> 0 | Z31: =D31*AG31 -> 0.693 | AA31: =SUM(Y31:Z31) -> 0.693 | AB31: =D31-AA31 -> 1.617 | AC31: =SUM(AR30:AY30) -> 0 | AD31: =AG31*I31 -> 343.035 | AE31: =SUM(AC31:AD31) -> 343.035 | AF31: =I31-AE31 -> 800.415 | AG31: =BA31 -> 0.3 | AI31: 0 | BA31: 0.3 | BC31: =SUM(BS30:BZ30) -> 0 | BD31: =SUM(BN30:BT30) -> 0 | BE31: =SUM(BU30:CB30) -> 0 | BF31: =SUM(BV30:CC30) -> 0 | BG31: =SUM(BW30:CD30) -> 0 | BH31: =SUM(BX30:CE30) -> 0 | BI31: =SUM(BY30:CF30) -> 0 | BJ31: =SUM(BZ30:CG30) -> 0
B32: Paint Finish | C32: 3.94 | D32: =C32*$L$23 -> 4.334 | E32: sq.m | F32: ='Material and Labor Cost'!$D$25 -> 555 | G32: ='Material and Labor Cost'!$F$25 -> 275 | H32: =SUM(F32:G32) -> 830 | I32: =H32*D32 -> 3597.22 | Y32: =SUM(AI32:AP32) -> 0 | Z32: =D32*AG32 -> 0 | AA32: =SUM(Y32:Z32) -> 0 | AB32: =D32-AA32 -> 4.334 | AC32: =SUM(AR31:AY31) -> 0 | AD32: =AG32*I32 -> 0 | AE32: =SUM(AC32:AD32) -> 0 | AF32: =I32-AE32 -> 3597.22 | AG32: =BA32 -> 0 | AI32: 0 | BA32: =SUM(BK31:BQ31) -> 0 | BC32: =SUM(BS31:BZ31) -> 0 | BD32: =SUM(BN31:BT31) -> 0 | BE32: =SUM(BU31:CB31) -> 0 | BF32: =SUM(BV31:CC31) -> 0 | BG32: =SUM(BW31:CD31) -> 0 | BH32: =SUM(BX31:CE31) -> 0 | BI32: =SUM(BY31:CF31) -> 0 | BJ32: =SUM(BZ31:CG31) -> 0
B33: Ducco Finish | C33: 3.96 | D33: =C33*$L$23 -> 4.356 | E33: sq.m | F33: ='Material and Labor Cost'!$D$26 -> 555 | G33: ='Material and Labor Cost'!$F$26 -> 275 | H33: =SUM(F33:G33) -> 830 | I33: =H33*D33 -> 3615.48 | Y33: =SUM(AI33:AP33) -> 0 | Z33: =D33*AG33 -> 0 | AA33: =SUM(Y33:Z33) -> 0 | AB33: =D33-AA33 -> 4.356 | AC33: =SUM(AR32:AY32) -> 0 | AD33: =AG33*I33 -> 0 | AE33: =SUM(AC33:AD33) -> 0 | AF33: =I33-AE33 -> 3615.48 | AG33: =BA33 -> 0 | AI33: 0 | BA33: =SUM(BK32:BQ32) -> 0 | BC33: =SUM(BS32:BZ32) -> 0 | BD33: =SUM(BN32:BT32) -> 0 | BE33: =SUM(BU32:CB32) -> 0 | BF33: =SUM(BV32:CC32) -> 0 | BG33: =SUM(BW32:CD32) -> 0 | BH33: =SUM(BX32:CE32) -> 0 | BI33: =SUM(BY32:CF32) -> 0 | BJ33: =SUM(BZ32:CG32) -> 0
B34: Miscellaneous and other Consumables | D34: 1 | E34: lot | I34: =SUM(I30:I33)*L72 -> 7984.295 | Y34: =SUM(AI34:AP34) -> 0 | Z34: =D34*AG34 -> 0 | AA34: =SUM(Y34:Z34) -> 0 | AB34: =D34-AA34 -> 1 | AC34: =SUM(AR33:AY33) -> 0 | AD34: =AG34*I34 -> 0 | AE34: =SUM(AC34:AD34) -> 0 | AF34: =I34-AE34 -> 7984.295 | AG34: =BA34 -> 0 | AI34: 0 | BA34: =SUM(BK33:BQ33) -> 0 | BC34: =SUM(BS33:BZ33) -> 0 | BD34: =SUM(BN33:BT33) -> 0 | BE34: =SUM(BU33:CB33) -> 0 | BF34: =SUM(BV33:CC33) -> 0 | BG34: =SUM(BW33:CD33) -> 0 | BH34: =SUM(BX33:CE33) -> 0 | BI34: =SUM(BY33:CF33) -> 0 | BJ34: =SUM(BZ33:CG33) -> 0
B35: LIving Area ( Storage Cabinets ) Sub-total: | I35: =SUM(I30:I34) -> 23952.885 | Y35: =SUM(Y30:Y34) -> 0 | Z35: =SUM(Z30:Z34) -> 3.3 | AA35: =SUM(AA30:AA34) -> 3.3 | AB35: =SUM(AB30:AB34) -> 17.39 | AC35: =SUM(AC30:AC34) -> 0 | AD35: =SUM(AD30:AD34) -> 2626.767 | AE35: =SUM(AE30:AE34) -> 2626.767 | AF35: =SUM(AF30:AF34) -> 21326.118 | AG35: =BA35 -> 0.12 | AH35: =SUM(AH30:AH34) -> 0 | AI35: 0 | BA35: =SUM(BA30:BA34)/COUNT(BA30:BA34) -> 0.12 | BC35: =SUM(BC30:BC34)/COUNT(BC30:BC34) -> 0 | BD35: =SUM(BD30:BD34)/COUNT(BD30:BD34) -> 0 | BE35: =SUM(BE30:BE34)/COUNT(BE30:BE34) -> 0 | BF35: =SUM(BF30:BF34)/COUNT(BF30:BF34) -> 0 | BG35: =SUM(BG30:BG34)/COUNT(BG30:BG34) -> 0 | BH35: =SUM(BH30:BH34)/COUNT(BH30:BH34) -> 0 | BI35: =SUM(BI30:BI34)/COUNT(BI30:BI34) -> 0 | BJ35: =SUM(BJ30:BJ34)/COUNT(BJ30:BJ34) -> 0
B36: Kitchen Area ( Storage Cabinets ) | AG36: =BA36 -> 0
B37: 3/4'' Marine Plywood | C37: 62.89 | D37: =C37*$L$23 -> 69.179 | E37: sq.m | F37: ='Material and Labor Cost'!$D$21 -> 576 | G37: ='Material and Labor Cost'!$F$21 -> 300 | H37: =SUM(F37:G37) -> 876 | I37: =H37*D37 -> 60600.804 | Y37: =SUM(AI37:AP37) -> 0 | Z37: =D37*AG37 -> 20.7537 | AA37: =SUM(Y37:Z37) -> 20.7537 | AB37: =D37-AA37 -> 48.4253 | AC37: =SUM(AR36:AY36) -> 0 | AD37: =AG37*I37 -> 18180.241 | AE37: =SUM(AC37:AD37) -> 18180.241 | AF37: =I37-AE37 -> 42420.563 | AG37: =BA37 -> 0.3 | AI37: 0 | BA37: 0.3 | BC37: =SUM(BS36:BZ36) -> 0 | BD37: =SUM(BN36:BT36) -> 0 | BE37: =SUM(BU36:CB36) -> 0 | BF37: =SUM(BV36:CC36) -> 0 | BG37: =SUM(BW36:CD36) -> 0 | BH37: =SUM(BX36:CE36) -> 0 | BI37: =SUM(BY36:CF36) -> 0 | BJ37: =SUM(BZ36:CG36) -> 0
B38: 1/2'' Backing Marine plywood | C38: 7.9 | D38: =C38*$L$23 -> 8.69 | E38: sq.m | F38: ='Material and Labor Cost'!$D$23 -> 330 | G38: ='Material and Labor Cost'!$F$23 -> 165 | H38: =SUM(F38:G38) -> 495 | I38: =H38*D38 -> 4301.55 | Y38: =SUM(AI38:AP38) -> 0 | Z38: =D38*AG38 -> 2.607 | AA38: =SUM(Y38:Z38) -> 2.607 | AB38: =D38-AA38 -> 6.083 | AC38: =SUM(AR37:AY37) -> 0 | AD38: =AG38*I38 -> 1290.465 | AE38: =SUM(AC38:AD38) -> 1290.465 | AF38: =I38-AE38 -> 3011.085 | AG38: =BA38 -> 0.3 | AI38: 0 | BA38: 0.3 | BC38: =SUM(BS37:BZ37) -> 0 | BD38: =SUM(BN37:BT37) -> 0 | BE38: =SUM(BU37:CB37) -> 0 | BF38: =SUM(BV37:CC37) -> 0 | BG38: =SUM(BW37:CD37) -> 0 | BH38: =SUM(BX37:CE37) -> 0 | BI38: =SUM(BY37:CF37) -> 0 | BJ38: =SUM(BZ37:CG37) -> 0
B39: Paint Finish | C39: 50.312 | D39: =C39*$L$23 -> 55.3432 | E39: sq.m | F39: ='Material and Labor Cost'!$D$25 -> 555 | G39: ='Material and Labor Cost'!$F$25 -> 275 | H39: =SUM(F39:G39) -> 830 | I39: =H39*D39 -> 45934.856 | Y39: =SUM(AI39:AP39) -> 0 | Z39: =D39*AG39 -> 0 | AA39: =SUM(Y39:Z39) -> 0 | AB39: =D39-AA39 -> 55.3432 | AC39: =SUM(AR38:AY38) -> 0 | AD39: =AG39*I39 -> 0 | AE39: =SUM(AC39:AD39) -> 0 | AF39: =I39-AE39 -> 45934.856 | AG39: =BA39 -> 0 | AI39: 0 | BA39: =SUM(BK38:BQ38) -> 0 | BC39: =SUM(BS38:BZ38) -> 0 | BD39: =SUM(BN38:BT38) -> 0 | BE39: =SUM(BU38:CB38) -> 0 | BF39: =SUM(BV38:CC38) -> 0 | BG39: =SUM(BW38:CD38) -> 0 | BH39: =SUM(BX38:CE38) -> 0 | BI39: =SUM(BY38:CF38) -> 0 | BJ39: =SUM(BZ38:CG38) -> 0
B40: Quartz White sintered stone | C40: 1.79 | D40: =C40*$L$23 -> 1.969 | E40: sq.m | F40: ='Material and Labor Cost'!$D$27 -> 6600 | G40: ='Material and Labor Cost'!$F$27 -> 3300 | H40: =SUM(F40:G40) -> 9900 | I40: =H40*D40 -> 19493.1 | Y40: =SUM(AI40:AP40) -> 0 | Z40: =D40*AG40 -> 0 | AA40: =SUM(Y40:Z40) -> 0 | AB40: =D40-AA40 -> 1.969 | AC40: =SUM(AR39:AY39) -> 0 | AD40: =AG40*I40 -> 0 | AE40: =SUM(AC40:AD40) -> 0 | AF40: =I40-AE40 -> 19493.1 | AG40: =BA40 -> 0 | AI40: 0 | BA40: =SUM(BK39:BQ39) -> 0 | BC40: =SUM(BS39:BZ39) -> 0 | BD40: =SUM(BN39:BT39) -> 0 | BE40: =SUM(BU39:CB39) -> 0 | BF40: =SUM(BV39:CC39) -> 0 | BG40: =SUM(BW39:CD39) -> 0 | BH40: =SUM(BX39:CE39) -> 0 | BI40: =SUM(BY39:CF39) -> 0 | BJ40: =SUM(BZ39:CG39) -> 0
B41: Miscellaneous and other Consumables | D41: 1 | E41: lot | I41: =SUM(I37:I40)*$L$27 -> 15639.637 | Y41: =SUM(AI41:AP41) -> 0 | Z41: =D41*AG41 -> 0 | AA41: =SUM(Y41:Z41) -> 0 | AB41: =D41-AA41 -> 1 | AC41: =SUM(AR40:AY40) -> 0 | AD41: =AG41*I41 -> 0 | AE41: =SUM(AC41:AD41) -> 0 | AF41: =I41-AE41 -> 15639.637 | AG41: =BA41 -> 0 | AI41: 0 | BA41: =SUM(BK40:BQ40) -> 0 | BC41: =SUM(BS40:BZ40) -> 0 | BD41: =SUM(BN40:BT40) -> 0 | BE41: =SUM(BU40:CB40) -> 0 | BF41: =SUM(BV40:CC40) -> 0 | BG41: =SUM(BW40:CD40) -> 0 | BH41: =SUM(BX40:CE40) -> 0 | BI41: =SUM(BY40:CF40) -> 0 | BJ41: =SUM(BZ40:CG40) -> 0
B42: Kitchen Area ( Storage Cabinets ) Sub-total: | I42: =SUM(I37:I41) -> 145969.95 | Y42: =SUM(Y37:Y41) -> 0 | Z42: =SUM(Z37:Z41) -> 23.3607 | AA42: =SUM(AA37:AA41) -> 23.3607 | AB42: =SUM(AB37:AB41) -> 112.8205 | AC42: =SUM(AC37:AC41) -> 0 | AD42: =SUM(AD37:AD41) -> 19470.706 | AE42: =SUM(AE37:AE41) -> 19470.706 | AF42: =SUM(AF37:AF41) -> 126499.24 | AG42: =BA42 -> 0.12 | AI42: 0 | BA42: =SUM(BA37:BA41)/COUNT(BA37:BA41) -> 0.12 | BC42: =SUM(BC37:BC41)/COUNT(BC37:BC41) -> 0 | BD42: =SUM(BD37:BD41)/COUNT(BD37:BD41) -> 0 | BE42: =SUM(BE37:BE41)/COUNT(BE37:BE41) -> 0 | BF42: =SUM(BF37:BF41)/COUNT(BF37:BF41) -> 0 | BG42: =SUM(BG37:BG41)/COUNT(BG37:BG41) -> 0 | BH42: =SUM(BH37:BH41)/COUNT(BH37:BH41) -> 0 | BI42: =SUM(BI37:BI41)/COUNT(BI37:BI41) -> 0 | BJ42: =SUM(BJ37:BJ41)/COUNT(BJ37:BJ41) -> 0
B43: Kitchen Area ( Counter Top ) | AG43: =BA43 -> 0
B44: 3/4'' Marine Plywood | C44: 18.04 | D44: =C44*$L$23 -> 19.844 | E44: sq.m | F44: ='Material and Labor Cost'!$D$21 -> 576 | G44: ='Material and Labor Cost'!$F$21 -> 300 | H44: =SUM(F44:G44) -> 876 | I44: =H44*D44 -> 17383.344 | Y44: =SUM(AI44:AP44) -> 0 | Z44: =D44*AG44 -> 5.9532 | AA44: =SUM(Y44:Z44) -> 5.9532 | AB44: =D44-AA44 -> 13.8908 | AC44: =SUM(AR43:AY43) -> 0 | AD44: =AG44*I44 -> 5215.0032 | AE44: =SUM(AC44:AD44) -> 5215.0032 | AF44: =I44-AE44 -> 12168.341 | AG44: =BA44 -> 0.3 | AI44: 0 | BA44: 0.3 | BC44: =SUM(BS43:BZ43) -> 0 | BD44: =SUM(BN43:BT43) -> 0 | BE44: =SUM(BU43:CB43) -> 0 | BF44: =SUM(BV43:CC43) -> 0 | BG44: =SUM(BW43:CD43) -> 0 | BH44: =SUM(BX43:CE43) -> 0 | BI44: =SUM(BY43:CF43) -> 0 | BJ44: =SUM(BZ43:CG43) -> 0
B45: 1/2'' Backing Marine plywood | C45: 2.6 | D45: =C45*$L$23 -> 2.86 | E45: sq.m | F45: ='Material and Labor Cost'!$D$23 -> 330 | G45: ='Material and Labor Cost'!$F$23 -> 165 | H45: =SUM(F45:G45) -> 495 | I45: =H45*D45 -> 1415.7 | Y45: =SUM(AI45:AP45) -> 0 | Z45: =D45*AG45 -> 0.858 | AA45: =SUM(Y45:Z45) -> 0.858 | AB45: =D45-AA45 -> 2.002 | AC45: =SUM(AR44:AY44) -> 0 | AD45: =AG45*I45 -> 424.71 | AE45: =SUM(AC45:AD45) -> 424.71 | AF45: =I45-AE45 -> 990.99 | AG45: =BA45 -> 0.3 | AI45: 0 | BA45: 0.3 | BC45: =SUM(BS44:BZ44) -> 0 | BD45: =SUM(BN44:BT44) -> 0 | BE45: =SUM(BU44:CB44) -> 0 | BF45: =SUM(BV44:CC44) -> 0 | BG45: =SUM(BW44:CD44) -> 0 | BH45: =SUM(BX44:CE44) -> 0 | BI45: =SUM(BY44:CF44) -> 0 | BJ45: =SUM(BZ44:CG44) -> 0
B46: Paint Finish | C46: =C44-C45 -> 15.44 | D46: =C46*$L$23 -> 16.984 | E46: sq.m | F46: ='Material and Labor Cost'!$D$25 -> 555 | G46: ='Material and Labor Cost'!$F$25 -> 275 | H46: =SUM(F46:G46) -> 830 | I46: =H46*D46 -> 14096.72 | Y46: =SUM(AI46:AP46) -> 0 | Z46: =D46*AG46 -> 0 | AA46: =SUM(Y46:Z46) -> 0 | AB46: =D46-AA46 -> 16.984 | AC46: =SUM(AR45:AY45) -> 0 | AD46: =AG46*I46 -> 0 | AE46: =SUM(AC46:AD46) -> 0 | AF46: =I46-AE46 -> 14096.72 | AG46: =BA46 -> 0 | AI46: 0 | BA46: =SUM(BK45:BQ45) -> 0 | BC46: =SUM(BS45:BZ45) -> 0 | BD46: =SUM(BN45:BT45) -> 0 | BE46: =SUM(BU45:CB45) -> 0 | BF46: =SUM(BV45:CC45) -> 0 | BG46: =SUM(BW45:CD45) -> 0 | BH46: =SUM(BX45:CE45) -> 0 | BI46: =SUM(BY45:CF45) -> 0 | BJ46: =SUM(BZ45:CG45) -> 0
B47: Quartz White sintered stone | C47: 5.4 | D47: =C47*$L$23 -> 5.94 | E47: sq.m | F47: ='Material and Labor Cost'!$D$27 -> 6600 | G47: ='Material and Labor Cost'!$F$27 -> 3300 | H47: =SUM(F47:G47) -> 9900 | I47: =H47*D47 -> 58806 | Y47: =SUM(AI47:AP47) -> 0 | Z47: =D47*AG47 -> 0 | AA47: =SUM(Y47:Z47) -> 0 | AB47: =D47-AA47 -> 5.94 | AC47: =SUM(AR46:AY46) -> 0 | AD47: =AG47*I47 -> 0 | AE47: =SUM(AC47:AD47) -> 0 | AF47: =I47-AE47 -> 58806 | AG47: =BA47 -> 0 | AI47: 0 | BA47: =SUM(BK46:BQ46) -> 0 | BC47: =SUM(BS46:BZ46) -> 0 | BD47: =SUM(BN46:BT46) -> 0 | BE47: =SUM(BU46:CB46) -> 0 | BF47: =SUM(BV46:CC46) -> 0 | BG47: =SUM(BW46:CD46) -> 0 | BH47: =SUM(BX46:CE46) -> 0 | BI47: =SUM(BY46:CF46) -> 0 | BJ47: =SUM(BZ46:CG46) -> 0
B48: Miscellaneous and other Consumables | D48: 1 | E48: lot | I48: =SUM(I44:I47)*$L$27 -> 11004.212 | Y48: =SUM(AI48:AP48) -> 0 | Z48: =D48*AG48 -> 0 | AA48: =SUM(Y48:Z48) -> 0 | AB48: =D48-AA48 -> 1 | AC48: =SUM(AR47:AY47) -> 0 | AD48: =AG48*I48 -> 0 | AE48: =SUM(AC48:AD48) -> 0 | AF48: =I48-AE48 -> 11004.212 | AG48: =BA48 -> 0 | AI48: 0 | BA48: =SUM(BK47:BQ47) -> 0 | BC48: =SUM(BS47:BZ47) -> 0 | BD48: =SUM(BN47:BT47) -> 0 | BE48: =SUM(BU47:CB47) -> 0 | BF48: =SUM(BV47:CC47) -> 0 | BG48: =SUM(BW47:CD47) -> 0 | BH48: =SUM(BX47:CE47) -> 0 | BI48: =SUM(BY47:CF47) -> 0 | BJ48: =SUM(BZ47:CG47) -> 0
B49: Kitchen Area ( Counter Top ) Sub-total: | I49: =SUM(I44:I48) -> 102705.98 | Y49: =SUM(Y44:Y48) -> 0 | Z49: =SUM(Z44:Z48) -> 6.8112 | AA49: =SUM(AA44:AA48) -> 6.8112 | AB49: =SUM(AB44:AB48) -> 39.8168 | AC49: =SUM(AC44:AC48) -> 0 | AD49: =SUM(AD44:AD48) -> 5639.7132 | AE49: =SUM(AE44:AE48) -> 5639.7132 | AF49: =SUM(AF44:AF48) -> 97066.262 | AG49: =BA49 -> 0.12 | AI49: 0 | BA49: =SUM(BA44:BA48)/COUNT(BA44:BA48) -> 0.12 | BC49: =SUM(BC44:BC48)/COUNT(BC44:BC48) -> 0 | BD49: =SUM(BD44:BD48)/COUNT(BD44:BD48) -> 0 | BE49: =SUM(BE44:BE48)/COUNT(BE44:BE48) -> 0 | BF49: =SUM(BF44:BF48)/COUNT(BF44:BF48) -> 0 | BG49: =SUM(BG44:BG48)/COUNT(BG44:BG48) -> 0 | BH49: =SUM(BH44:BH48)/COUNT(BH44:BH48) -> 0 | BI49: =SUM(BI44:BI48)/COUNT(BI44:BI48) -> 0 | BJ49: =SUM(BJ44:BJ48)/COUNT(BJ44:BJ48) -> 0
B50: Powder Room (Lavatory Cabinets) | AG50: =BA50 -> 0
B51: 3/4'' Marine Plywood | C51: 4.46 | D51: =C51*$L$23 -> 4.906 | E51: sq.m | F51: ='Material and Labor Cost'!$D$21 -> 576 | G51: ='Material and Labor Cost'!$F$21 -> 300 | H51: =SUM(F51:G51) -> 876 | I51: =H51*D51 -> 4297.656 | L51: Miscellaneous | Y51: =SUM(AI51:AP51) -> 0 | Z51: =D51*AG51 -> 3.9248 | AA51: =SUM(Y51:Z51) -> 3.9248 | AB51: =D51-AA51 -> 0.9812 | AC51: =SUM(AR50:AY50) -> 0 | AD51: =AG51*I51 -> 3438.1248 | AE51: =SUM(AC51:AD51) -> 3438.1248 | AF51: =I51-AE51 -> 859.5312 | AG51: =BA51 -> 0.8 | AI51: 0 | BA51: 0.8 | BC51: =SUM(BS50:BZ50) -> 0 | BD51: =SUM(BN50:BT50) -> 0 | BE51: =SUM(BU50:CB50) -> 0 | BF51: =SUM(BV50:CC50) -> 0 | BG51: =SUM(BW50:CD50) -> 0 | BH51: =SUM(BX50:CE50) -> 0 | BI51: =SUM(BY50:CF50) -> 0 | BJ51: =SUM(BZ50:CG50) -> 0
B52: 1/2'' Backing Marine plywood | C52: 0.6 | D52: =C52*$L$23 -> 0.66 | E52: sq.m | F52: ='Material and Labor Cost'!$D$23 -> 330 | G52: ='Material and Labor Cost'!$F$23 -> 165 | H52: =SUM(F52:G52) -> 495 | I52: =H52*D52 -> 326.7 | L52: 0.4 | Y52: =SUM(AI52:AP52) -> 0 | Z52: =D52*AG52 -> 0.528 | AA52: =SUM(Y52:Z52) -> 0.528 | AB52: =D52-AA52 -> 0.132 | AC52: =SUM(AR51:AY51) -> 0 | AD52: =AG52*I52 -> 261.36 | AE52: =SUM(AC52:AD52) -> 261.36 | AF52: =I52-AE52 -> 65.34 | AG52: =BA52 -> 0.8 | AI52: 0 | BA52: 0.8 | BC52: =SUM(BS51:BZ51) -> 0 | BD52: =SUM(BN51:BT51) -> 0 | BE52: =SUM(BU51:CB51) -> 0 | BF52: =SUM(BV51:CC51) -> 0 | BG52: =SUM(BW51:CD51) -> 0 | BH52: =SUM(BX51:CE51) -> 0 | BI52: =SUM(BY51:CF51) -> 0 | BJ52: =SUM(BZ51:CG51) -> 0
B53: Ducco Finish | C53: 3.56 | D53: =C53*$L$23 -> 3.916 | E53: sq.m | F53: ='Material and Labor Cost'!$D$25 -> 555 | G53: ='Material and Labor Cost'!$F$25 -> 275 | H53: =SUM(F53:G53) -> 830 | I53: =H53*D53 -> 3250.28 | Y53: =SUM(AI53:AP53) -> 0 | Z53: =D53*AG53 -> 0.7832 | AA53: =SUM(Y53:Z53) -> 0.7832 | AB53: =D53-AA53 -> 3.1328 | AC53: =SUM(AR52:AY52) -> 0 | AD53: =AG53*I53 -> 650.056 | AE53: =SUM(AC53:AD53) -> 650.056 | AF53: =I53-AE53 -> 2600.224 | AG53: =BA53 -> 0.2 | AI53: 0 | BA53: 0.2 | BC53: =SUM(BS52:BZ52) -> 0 | BD53: =SUM(BN52:BT52) -> 0 | BE53: =SUM(BU52:CB52) -> 0 | BF53: =SUM(BV52:CC52) -> 0 | BG53: =SUM(BW52:CD52) -> 0 | BH53: =SUM(BX52:CE52) -> 0 | BI53: =SUM(BY52:CF52) -> 0 | BJ53: =SUM(BZ52:CG52) -> 0
B54: Quartz White sintered stone | C54: 0.45 | D54: =C54*$L$23 -> 0.495 | E54: sq.m | F54: ='Material and Labor Cost'!$D$27 -> 6600 | G54: ='Material and Labor Cost'!$F$27 -> 3300 | H54: =SUM(F54:G54) -> 9900 | I54: =H54*D54 -> 4900.5 | Y54: =SUM(AI54:AP54) -> 0 | Z54: =D54*AG54 -> 0.099 | AA54: =SUM(Y54:Z54) -> 0.099 | AB54: =D54-AA54 -> 0.396 | AC54: =SUM(AR53:AY53) -> 0 | AD54: =AG54*I54 -> 980.1 | AE54: =SUM(AC54:AD54) -> 980.1 | AF54: =I54-AE54 -> 3920.4 | AG54: =BA54 -> 0.2 | AI54: 0 | BA54: 0.2 | BC54: =SUM(BS53:BZ53) -> 0 | BD54: =SUM(BN53:BT53) -> 0 | BE54: =SUM(BU53:CB53) -> 0 | BF54: =SUM(BV53:CC53) -> 0 | BG54: =SUM(BW53:CD53) -> 0 | BH54: =SUM(BX53:CE53) -> 0 | BI54: =SUM(BY53:CF53) -> 0 | BJ54: =SUM(BZ53:CG53) -> 0
B55: Miscellaneous and other Consumables | D55: 1 | E55: lot | I55: =SUM(I51:I54)*$L$52 -> 5110.0544 | Y55: =SUM(AI55:AP55) -> 0 | Z55: =D55*AG55 -> 0.6 | AA55: =SUM(Y55:Z55) -> 0.6 | AB55: =D55-AA55 -> 0.4 | AC55: =SUM(AR54:AY54) -> 0 | AD55: =AG55*I55 -> 3066.0326 | AE55: =SUM(AC55:AD55) -> 3066.0326 | AF55: =I55-AE55 -> 2044.0218 | AG55: =BA55 -> 0.6 | AI55: 0 | BA55: 0.6 | BC55: =SUM(BS54:BZ54) -> 0 | BD55: =SUM(BN54:BT54) -> 0 | BE55: =SUM(BU54:CB54) -> 0 | BF55: =SUM(BV54:CC54) -> 0 | BG55: =SUM(BW54:CD54) -> 0 | BH55: =SUM(BX54:CE54) -> 0 | BI55: =SUM(BY54:CF54) -> 0 | BJ55: =SUM(BZ54:CG54) -> 0
B56: Powder Room Sub-total: | I56: =SUM(I51:I55) -> 17885.19 | Y56: =SUM(Y51:Y55) -> 0 | Z56: =SUM(Z51:Z55) -> 5.935 | AA56: =SUM(AA51:AA55) -> 5.935 | AB56: =SUM(AB51:AB55) -> 5.042 | AC56: =SUM(AC51:AC55) -> 0 | AD56: =SUM(AD51:AD55) -> 8395.6734 | AE56: =SUM(AE51:AE55) -> 8395.6734 | AF56: =SUM(AF51:AF55) -> 9489.517 | AG56: =BA56 -> 0.52 | AI56: 0 | BA56: =SUM(BA51:BA55)/COUNT(BA51:BA55) -> 0.52 | BC56: =SUM(BC51:BC55)/COUNT(BC51:BC55) -> 0 | BD56: =SUM(BD51:BD55)/COUNT(BD51:BD55) -> 0 | BE56: =SUM(BE51:BE55)/COUNT(BE51:BE55) -> 0 | BF56: =SUM(BF51:BF55)/COUNT(BF51:BF55) -> 0 | BG56: =SUM(BG51:BG55)/COUNT(BG51:BG55) -> 0 | BH56: =SUM(BH51:BH55)/COUNT(BH51:BH55) -> 0 | BI56: =SUM(BI51:BI55)/COUNT(BI51:BI55) -> 0 | BJ56: =SUM(BJ51:BJ55)/COUNT(BJ51:BJ55) -> 0
B57: Office (Shelves with Cabinets and table) | AG57: =BA57 -> 0
B58: 1''x1''x2.0mm Tubular Steel | C58: 12 | D58: =C58*$L$23 -> 13.2 | E58: l.m | F58: ='Material and Labor Cost'!$D$30 -> 70.18 | G58: ='Material and Labor Cost'!$F$30 -> 35.09 | H58: =SUM(F58:G58) -> 105.27 | I58: =H58*D58 -> 1389.564 | Y58: =SUM(AI58:AP58) -> 0 | Z58: =D58*AG58 -> 5.28 | AA58: =SUM(Y58:Z58) -> 5.28 | AB58: =D58-AA58 -> 7.92 | AC58: =SUM(AR57:AY57) -> 0 | AD58: =AG58*I58 -> 555.8256 | AE58: =SUM(AC58:AD58) -> 555.8256 | AF58: =I58-AE58 -> 833.7384 | AG58: =BA58 -> 0.4 | AI58: 0 | BA58: 0.4 | BC58: =SUM(BS57:BZ57) -> 0 | BD58: =SUM(BN57:BT57) -> 0 | BE58: =SUM(BU57:CB57) -> 0 | BF58: =SUM(BV57:CC57) -> 0 | BG58: =SUM(BW57:CD57) -> 0 | BH58: =SUM(BX57:CE57) -> 0 | BI58: =SUM(BY57:CF57) -> 0 | BJ58: =SUM(BZ57:CG57) -> 0
B59: 3/4'' Marine Plywood | C59: 11.18 | D59: =C59*$L$23 -> 12.298 | E59: sq.m | F59: ='Material and Labor Cost'!$D$21 -> 576 | G59: ='Material and Labor Cost'!$F$21 -> 300 | H59: =SUM(F59:G59) -> 876 | I59: =H59*D59 -> 10773.048 | Y59: =SUM(AI59:AP59) -> 0 | Z59: =D59*AG59 -> 4.9192 | AA59: =SUM(Y59:Z59) -> 4.9192 | AB59: =D59-AA59 -> 7.3788 | AC59: =SUM(AR58:AY58) -> 0 | AD59: =AG59*I59 -> 4309.2192 | AE59: =SUM(AC59:AD59) -> 4309.2192 | AF59: =I59-AE59 -> 6463.8288 | AG59: =BA59 -> 0.4 | AI59: 0 | BA59: 0.4 | BC59: =SUM(BS58:BZ58) -> 0 | BD59: =SUM(BN58:BT58) -> 0 | BE59: =SUM(BU58:CB58) -> 0 | BF59: =SUM(BV58:CC58) -> 0 | BG59: =SUM(BW58:CD58) -> 0 | BH59: =SUM(BX58:CE58) -> 0 | BI59: =SUM(BY58:CF58) -> 0 | BJ59: =SUM(BZ58:CG58) -> 0
B60: 1/2'' Backing Marine plywood | C60: 1.1 | D60: =C60*$L$23 -> 1.21 | E60: sq.m | F60: ='Material and Labor Cost'!$D$23 -> 330 | G60: ='Material and Labor Cost'!$F$23 -> 165 | H60: =SUM(F60:G60) -> 495 | I60: =H60*D60 -> 598.95 | Y60: =SUM(AI60:AP60) -> 0 | Z60: =D60*AG60 -> 0.484 | AA60: =SUM(Y60:Z60) -> 0.484 | AB60: =D60-AA60 -> 0.726 | AC60: =SUM(AR59:AY59) -> 0 | AD60: =AG60*I60 -> 239.58 | AE60: =SUM(AC60:AD60) -> 239.58 | AF60: =I60-AE60 -> 359.37 | AG60: =BA60 -> 0.4 | AI60: 0 | BA60: 0.4 | BC60: =SUM(BS59:BZ59) -> 0 | BD60: =SUM(BN59:BT59) -> 0 | BE60: =SUM(BU59:CB59) -> 0 | BF60: =SUM(BV59:CC59) -> 0 | BG60: =SUM(BW59:CD59) -> 0 | BH60: =SUM(BX59:CE59) -> 0 | BI60: =SUM(BY59:CF59) -> 0 | BJ60: =SUM(BZ59:CG59) -> 0
B61: PVC Board | C61: 1.58 | D61: =C61*$L$23 -> 1.738 | E61: sq.m | F61: ='Material and Labor Cost'!$D$29 -> 748 | G61: ='Material and Labor Cost'!$F$29 -> 380 | H61: =SUM(F61:G61) -> 1128 | I61: =H61*D61 -> 1960.464 | Y61: =SUM(AI61:AP61) -> 0 | Z61: =D61*AG61 -> 0.6952 | AA61: =SUM(Y61:Z61) -> 0.6952 | AB61: =D61-AA61 -> 1.0428 | AC61: =SUM(AR60:AY60) -> 0 | AD61: =AG61*I61 -> 784.1856 | AE61: =SUM(AC61:AD61) -> 784.1856 | AF61: =I61-AE61 -> 1176.2784 | AG61: =BA61 -> 0.4 | AI61: 0 | BA61: 0.4 | BC61: =SUM(BS60:BZ60) -> 0 | BD61: =SUM(BN60:BT60) -> 0 | BE61: =SUM(BU60:CB60) -> 0 | BF61: =SUM(BV60:CC60) -> 0 | BG61: =SUM(BW60:CD60) -> 0 | BH61: =SUM(BX60:CE60) -> 0 | BI61: =SUM(BY60:CF60) -> 0 | BJ61: =SUM(BZ60:CG60) -> 0
B62: Veneer Laminate | C62: 13 | D62: =C62*$L$23 -> 14.3 | E62: sq.m | F62: ='Material and Labor Cost'!$D$28 -> 2640 | G62: ='Material and Labor Cost'!$F$29 -> 380 | H62: =SUM(F62:G62) -> 3020 | I62: =H62*D62 -> 43186 | Y62: =SUM(AI62:AP62) -> 0 | Z62: =D62*AG62 -> 5.72 | AA62: =SUM(Y62:Z62) -> 5.72 | AB62: =D62-AA62 -> 8.58 | AC62: =SUM(AR61:AY61) -> 0 | AD62: =AG62*I62 -> 17274.4 | AE62: =SUM(AC62:AD62) -> 17274.4 | AF62: =I62-AE62 -> 25911.6 | AG62: =BA62 -> 0.4 | AI62: 0 | BA62: 0.4 | BC62: =SUM(BS61:BZ61) -> 0 | BD62: =SUM(BN61:BT61) -> 0 | BE62: =SUM(BU61:CB61) -> 0 | BF62: =SUM(BV61:CC61) -> 0 | BG62: =SUM(BW61:CD61) -> 0 | BH62: =SUM(BX61:CE61) -> 0 | BI62: =SUM(BY61:CF61) -> 0 | BJ62: =SUM(BZ61:CG61) -> 0
B63: Veneer Edge Laminate | C63: 20.02 | D63: =C63*$L$23 -> 22.022 | E63: l.m | F63: ='Material and Labor Cost'!$D$32 -> 55 | G63: ='Material and Labor Cost'!$F$32 -> 30 | H63: =SUM(F63:G63) -> 85 | I63: =H63*D63 -> 1871.87 | Y63: =SUM(AI63:AP63) -> 0 | Z63: =D63*AG63 -> 8.8088 | AA63: =SUM(Y63:Z63) -> 8.8088 | AB63: =D63-AA63 -> 13.2132 | AC63: =SUM(AR62:AY62) -> 0 | AD63: =AG63*I63 -> 748.748 | AE63: =SUM(AC63:AD63) -> 748.748 | AF63: =I63-AE63 -> 1123.122 | AG63: =BA63 -> 0.4 | AI63: 0 | BA63: 0.4 | BC63: =SUM(BS62:BZ62) -> 0 | BD63: =SUM(BN62:BT62) -> 0 | BE63: =SUM(BU62:CB62) -> 0 | BF63: =SUM(BV62:CC62) -> 0 | BG63: =SUM(BW62:CD62) -> 0 | BH63: =SUM(BX62:CE62) -> 0 | BI63: =SUM(BY62:CF62) -> 0 | BJ63: =SUM(BZ62:CG62) -> 0
B64: Coated Powder (Black) | C64: 10 | D64: =C64*$L$23 -> 11 | E64: sq.m | F64: ='Material and Labor Cost'!$D$31 -> 275 | G64: ='Material and Labor Cost'!$F$31 -> 140 | H64: =SUM(F64:G64) -> 415 | I64: =H64*D64 -> 4565 | Y64: =SUM(AI64:AP64) -> 0 | Z64: =D64*AG64 -> 0 | AA64: =SUM(Y64:Z64) -> 0 | AB64: =D64-AA64 -> 11 | AC64: =SUM(AR63:AY63) -> 0 | AD64: =AG64*I64 -> 0 | AE64: =SUM(AC64:AD64) -> 0 | AF64: =I64-AE64 -> 4565 | AG64: =BA64 -> 0 | AI64: 0 | BA64: =SUM(BK63:BQ63) -> 0 | BC64: =SUM(BS63:BZ63) -> 0 | BD64: =SUM(BN63:BT63) -> 0 | BE64: =SUM(BU63:CB63) -> 0 | BF64: =SUM(BV63:CC63) -> 0 | BG64: =SUM(BW63:CD63) -> 0 | BH64: =SUM(BX63:CE63) -> 0 | BI64: =SUM(BY63:CF63) -> 0 | BJ64: =SUM(BZ63:CG63) -> 0
B65: Warm Strip Lights | C65: 2.31 | D65: =C65*$L$23 -> 2.541 | E65: l.m | F65: ='Material and Labor Cost'!$D$24 -> 220 | G65: ='Material and Labor Cost'!$F$24 -> 110 | H65: =SUM(F65:G65) -> 330 | I65: =H65*D65 -> 838.53 | Y65: =SUM(AI65:AP65) -> 0 | Z65: =D65*AG65 -> 0 | AA65: =SUM(Y65:Z65) -> 0 | AB65: =D65-AA65 -> 2.541 | AC65: =SUM(AR64:AY64) -> 0 | AD65: =AG65*I65 -> 0 | AE65: =SUM(AC65:AD65) -> 0 | AF65: =I65-AE65 -> 838.53 | AG65: =BA65 -> 0 | AI65: 0 | BA65: =SUM(BK64:BQ64) -> 0 | BC65: =SUM(BS64:BZ64) -> 0 | BD65: =SUM(BN64:BT64) -> 0 | BE65: =SUM(BU64:CB64) -> 0 | BF65: =SUM(BV64:CC64) -> 0 | BG65: =SUM(BW64:CD64) -> 0 | BH65: =SUM(BX64:CE64) -> 0 | BI65: =SUM(BY64:CF64) -> 0 | BJ65: =SUM(BZ64:CG64) -> 0
B66: Miscellaneous and other Consumables | D66: 1 | E66: lot | I66: =SUM(I57:I65)*$L$27 -> 7822.0111 | Y66: =SUM(AI66:AP66) -> 0 | Z66: =D66*AG66 -> 0 | AA66: =SUM(Y66:Z66) -> 0 | AB66: =D66-AA66 -> 1 | AC66: =SUM(AR65:AY65) -> 0 | AD66: =AG66*I66 -> 0 | AE66: =SUM(AC66:AD66) -> 0 | AF66: =I66-AE66 -> 7822.0111 | AG66: =BA66 -> 0 | AI66: 0 | BA66: =SUM(BK65:BQ65) -> 0 | BC66: =SUM(BS65:BZ65) -> 0 | BD66: =SUM(BN65:BT65) -> 0 | BE66: =SUM(BU65:CB65) -> 0 | BF66: =SUM(BV65:CC65) -> 0 | BG66: =SUM(BW65:CD65) -> 0 | BH66: =SUM(BX65:CE65) -> 0 | BI66: =SUM(BY65:CF65) -> 0 | BJ66: =SUM(BZ65:CG65) -> 0
B67: Office (Shelves with Cabinets and table) Sub-total: | I67: =SUM(I58:I66) -> 73005.437 | Y67: =SUM(Y58:Y66) -> 0 | Z67: =SUM(Z58:Z66) -> 25.9072 | AA67: =SUM(AA58:AA66) -> 25.9072 | AB67: =SUM(AB58:AB66) -> 53.4018 | AC67: =SUM(AC58:AC66) -> 0 | AD67: =SUM(AD58:AD66) -> 23911.958 | AE67: =SUM(AE58:AE66) -> 23911.958 | AF67: =SUM(AF58:AF66) -> 49093.479 | AG67: =BA67 -> 0.26666667 | AI67: 0 | BA67: =SUM(BA58:BA66)/COUNT(BA58:BA66) -> 0.26666667 | BC67: =SUM(BC58:BC66)/COUNT(BC58:BC66) -> 0 | BD67: =SUM(BD58:BD66)/COUNT(BD58:BD66) -> 0 | BE67: =SUM(BE58:BE66)/COUNT(BE58:BE66) -> 0 | BF67: =SUM(BF58:BF66)/COUNT(BF58:BF66) -> 0 | BG67: =SUM(BG58:BG66)/COUNT(BG58:BG66) -> 0 | BH67: =SUM(BH58:BH66)/COUNT(BH58:BH66) -> 0 | BI67: =SUM(BI58:BI66)/COUNT(BI58:BI66) -> 0 | BJ67: =SUM(BJ58:BJ66)/COUNT(BJ58:BJ66) -> 0
B68: Ground Floor Cabinet's Sub-total: | I68: =SUM(I56,I49,I42,I35,I28,I67) -> 471199 | Y68: =SUM(Y28,Y35,Y42,Y49,Y56,Y67) -> 0 | Z68: =SUM(Z28,Z35,Z42,Z49,Z56,Z67) -> 82.6193 | AA68: =SUM(AA28,AA35,AA42,AA49,AA56,AA67) -> 82.6193 | AB68: =SUM(AB28,AB35,AB42,AB49,AB56,AB67) -> 328.5349 | AC68: =SUM(AC28,AC35,AC42,AC49,AC56,AC67) -> 0 | AD68: =SUM(AD28,AD35,AD42,AD49,AD56,AD67) -> 75157.742 | AE68: =SUM(AE28,AE35,AE42,AE49,AE56,AE67) -> 75157.742 | AF68: =SUM(AF28,AF35,AF42,AF49,AF56,AF67) -> 396041.25 | AG68: =BA68 -> 0.20539683 | AI68: 0 | BA68: =SUM(BA28,BA35,BA42,BA49,BA56,BA67)/6 -> 0.20539683 | BC68: =SUM(BC28,BC35,BC42,BC49,BC56,BC67)/6 -> 0 | BD68: =SUM(BD28,BD35,BD42,BD49,BD56,BD67)/6 -> 0 | BE68: =SUM(BE28,BE35,BE42,BE49,BE56,BE67)/6 -> 0 | BF68: =SUM(BF28,BF35,BF42,BF49,BF56,BF67)/6 -> 0 | BG68: =SUM(BG28,BG35,BG42,BG49,BG56,BG67)/6 -> 0 | BH68: =SUM(BH28,BH35,BH42,BH49,BH56,BH67)/6 -> 0 | BI68: =SUM(BI28,BI35,BI42,BI49,BI56,BI67)/6 -> 0 | BJ68: =SUM(BJ28,BJ35,BJ42,BJ49,BJ56,BJ67)/6 -> 0
B69: SECOND FLOOR | AG69: =BA69 -> 0
B70: Hallway (cabinets) | AG70: =BA70 -> 0
B71: 3/4'' Marine Plywood | C71: 6.77 | D71: =C71*$L$23 -> 7.447 | E71: sq.m | F71: ='Material and Labor Cost'!$D$21 -> 576 | G71: ='Material and Labor Cost'!$F$21 -> 300 | H71: =SUM(F71:G71) -> 876 | I71: =H71*D71 -> 6523.572 | L71: Miscellaneous | Y71: =SUM(AI71:AP71) -> 0 | Z71: =D71*AG71 -> 2.9788 | AA71: =SUM(Y71:Z71) -> 2.9788 | AB71: =D71-AA71 -> 4.4682 | AC71: =SUM(AR70:AY70) -> 0 | AD71: =AG71*I71 -> 2609.4288 | AE71: =SUM(AC71:AD71) -> 2609.4288 | AF71: =I71-AE71 -> 3914.1432 | AG71: =BA71 -> 0.4 | AI71: 0 | BA71: 0.4 | BC71: =SUM(BS70:BZ70) -> 0 | BD71: =SUM(BN70:BT70) -> 0 | BE71: =SUM(BU70:CB70) -> 0 | BF71: =SUM(BV70:CC70) -> 0 | BG71: =SUM(BW70:CD70) -> 0 | BH71: =SUM(BX70:CE70) -> 0 | BI71: =SUM(BY70:CF70) -> 0 | BJ71: =SUM(BZ70:CG70) -> 0
B72: 1/2'' Backing Marine plywood | C72: 1.1 | D72: =C72*$L$23 -> 1.21 | E72: sq.m | F72: ='Material and Labor Cost'!$D$23 -> 330 | G72: ='Material and Labor Cost'!$F$23 -> 165 | H72: =SUM(F72:G72) -> 495 | I72: =H72*D72 -> 598.95 | L72: 0.5 | Y72: =SUM(AI72:AP72) -> 0 | Z72: =D72*AG72 -> 0.484 | AA72: =SUM(Y72:Z72) -> 0.484 | AB72: =D72-AA72 -> 0.726 | AC72: =SUM(AR71:AY71) -> 0 | AD72: =AG72*I72 -> 239.58 | AE72: =SUM(AC72:AD72) -> 239.58 | AF72: =I72-AE72 -> 359.37 | AG72: =BA72 -> 0.4 | AI72: 0 | BA72: 0.4 | BC72: =SUM(BS71:BZ71) -> 0 | BD72: =SUM(BN71:BT71) -> 0 | BE72: =SUM(BU71:CB71) -> 0 | BF72: =SUM(BV71:CC71) -> 0 | BG72: =SUM(BW71:CD71) -> 0 | BH72: =SUM(BX71:CE71) -> 0 | BI72: =SUM(BY71:CF71) -> 0 | BJ72: =SUM(BZ71:CG71) -> 0
B73: Ducco Finish | C73: 6.77 | D73: =C73*$L$23 -> 7.447 | E73: sq.m | F73: ='Material and Labor Cost'!$D$25 -> 555 | G73: ='Material and Labor Cost'!$F$25 -> 275 | H73: =SUM(F73:G73) -> 830 | I73: =H73*D73 -> 6181.01 | Y73: =SUM(AI73:AP73) -> 0 | Z73: =D73*AG73 -> 2.9788 | AA73: =SUM(Y73:Z73) -> 2.9788 | AB73: =D73-AA73 -> 4.4682 | AC73: =SUM(AR72:AY72) -> 0 | AD73: =AG73*I73 -> 2472.404 | AE73: =SUM(AC73:AD73) -> 2472.404 | AF73: =I73-AE73 -> 3708.606 | AG73: =BA73 -> 0.4 | AI73: 0 | BA73: 0.4 | BC73: =SUM(BS72:BZ72) -> 0 | BD73: =SUM(BN72:BT72) -> 0 | BE73: =SUM(BU72:CB72) -> 0 | BF73: =SUM(BV72:CC72) -> 0 | BG73: =SUM(BW72:CD72) -> 0 | BH73: =SUM(BX72:CE72) -> 0 | BI73: =SUM(BY72:CF72) -> 0 | BJ73: =SUM(BZ72:CG72) -> 0
B74: Miscellaneous and other Consumables | D74: 1 | E74: lot | I74: =SUM(I71:I73)*$L$72 -> 6651.766 | Y74: =SUM(AI74:AP74) -> 0 | Z74: =D74*AG74 -> 0.2 | AA74: =SUM(Y74:Z74) -> 0.2 | AB74: =D74-AA74 -> 0.8 | AC74: =SUM(AR73:AY73) -> 0 | AD74: =AG74*I74 -> 1330.3532 | AE74: =SUM(AC74:AD74) -> 1330.3532 | AF74: =I74-AE74 -> 5321.4128 | AG74: =BA74 -> 0.2 | AI74: 0 | BA74: 0.2 | BC74: =SUM(BS73:BZ73) -> 0 | BD74: =SUM(BN73:BT73) -> 0 | BE74: =SUM(BU73:CB73) -> 0 | BF74: =SUM(BV73:CC73) -> 0 | BG74: =SUM(BW73:CD73) -> 0 | BH74: =SUM(BX73:CE73) -> 0 | BI74: =SUM(BY73:CF73) -> 0 | BJ74: =SUM(BZ73:CG73) -> 0
B75: Hallway (cabinets) Sub-total: | I75: =SUM(I71:I74) -> 19955.298 | Y75: =SUM(Y71:Y74) -> 0 | Z75: =SUM(Z71:Z74) -> 6.6416 | AA75: =SUM(AA71:AA74) -> 6.6416 | AB75: =SUM(AB71:AB74) -> 10.4624 | AC75: =SUM(AC71:AC74) -> 0 | AD75: =SUM(AD71:AD74) -> 6651.766 | AE75: =SUM(AE71:AE74) -> 6651.766 | AF75: =SUM(AF71:AF74) -> 13303.532 | AG75: =BA75 -> 0.35 | AI75: 0 | BA75: =SUM(BA71:BA74)/COUNT(BA71:BA74) -> 0.35 | BC75: =SUM(BC71:BC74)/COUNT(BC71:BC74) -> 0 | BD75: =SUM(BD71:BD74)/COUNT(BD71:BD74) -> 0 | BE75: =SUM(BE71:BE74)/COUNT(BE71:BE74) -> 0 | BF75: =SUM(BF71:BF74)/COUNT(BF71:BF74) -> 0 | BG75: =SUM(BG71:BG74)/COUNT(BG71:BG74) -> 0 | BH75: =SUM(BH71:BH74)/COUNT(BH71:BH74) -> 0 | BI75: =SUM(BI71:BI74)/COUNT(BI71:BI74) -> 0 | BJ75: =SUM(BJ71:BJ74)/COUNT(BJ71:BJ74) -> 0
B76: Bedroom 1 (Closets) | AG76: =BA76 -> 0
B77: 3/4'' Marine Plywood | C77: 23.4 | D77: =C77*$L$23 -> 25.74 | E77: sq.m | F77: ='Material and Labor Cost'!$D$21 -> 576 | G77: ='Material and Labor Cost'!$F$21 -> 300 | H77: =SUM(F77:G77) -> 876 | I77: =H77*D77 -> 22548.24 | Y77: =SUM(AI77:AP77) -> 0 | Z77: =D77*AG77 -> 25.74 | AA77: =SUM(Y77:Z77) -> 25.74 | AB77: =D77-AA77 -> 0 | AC77: =SUM(AR76:AY76) -> 0 | AD77: =AG77*I77 -> 22548.24 | AE77: =SUM(AC77:AD77) -> 22548.24 | AF77: =I77-AE77 -> 0 | AG77: =BA77 -> 1 | AI77: 0 | BA77: 1 | BC77: =SUM(BS76:BZ76) -> 0 | BD77: =SUM(BN76:BT76) -> 0 | BE77: =SUM(BU76:CB76) -> 0 | BF77: =SUM(BV76:CC76) -> 0 | BG77: =SUM(BW76:CD76) -> 0 | BH77: =SUM(BX76:CE76) -> 0 | BI77: =SUM(BY76:CF76) -> 0 | BJ77: =SUM(BZ76:CG76) -> 0
B78: 1/2'' Backing Marine plywood | C78: 7 | D78: =C78*$L$23 -> 7.7 | E78: sq.m | F78: ='Material and Labor Cost'!$D$23 -> 330 | G78: ='Material and Labor Cost'!$F$23 -> 165 | H78: =SUM(F78:G78) -> 495 | I78: =H78*D78 -> 3811.5 | Y78: =SUM(AI78:AP78) -> 0 | Z78: =D78*AG78 -> 7.7 | AA78: =SUM(Y78:Z78) -> 7.7 | AB78: =D78-AA78 -> 0 | AC78: =SUM(AR77:AY77) -> 0 | AD78: =AG78*I78 -> 3811.5 | AE78: =SUM(AC78:AD78) -> 3811.5 | AF78: =I78-AE78 -> 0 | AG78: =BA78 -> 1 | AI78: 0 | BA78: 1 | BC78: =SUM(BS77:BZ77) -> 0 | BD78: =SUM(BN77:BT77) -> 0 | BE78: =SUM(BU77:CB77) -> 0 | BF78: =SUM(BV77:CC77) -> 0 | BG78: =SUM(BW77:CD77) -> 0 | BH78: =SUM(BX77:CE77) -> 0 | BI78: =SUM(BY77:CF77) -> 0 | BJ78: =SUM(BZ77:CG77) -> 0
B79: Stainless Hanging Rod | C79: 4.8 | D79: =C79*$L$23 -> 5.28 | E79: l.m | F79: ='Material and Labor Cost'!$D$33 -> 330 | G79: ='Material and Labor Cost'!$F$33 -> 165 | H79: =SUM(F79:G79) -> 495 | I79: =H79*D79 -> 2613.6 | Y79: =SUM(AI79:AP79) -> 0 | Z79: =D79*AG79 -> 0 | AA79: =SUM(Y79:Z79) -> 0 | AB79: =D79-AA79 -> 5.28 | AC79: =SUM(AR78:AY78) -> 0 | AD79: =AG79*I79 -> 0 | AE79: =SUM(AC79:AD79) -> 0 | AF79: =I79-AE79 -> 2613.6 | AG79: =BA79 -> 0 | AI79: 0 | BA79: =SUM(BK78:BQ78) -> 0 | BC79: =SUM(BS78:BZ78) -> 0 | BD79: =SUM(BN78:BT78) -> 0 | BE79: =SUM(BU78:CB78) -> 0 | BF79: =SUM(BV78:CC78) -> 0 | BG79: =SUM(BW78:CD78) -> 0 | BH79: =SUM(BX78:CE78) -> 0 | BI79: =SUM(BY78:CF78) -> 0 | BJ79: =SUM(BZ78:CG78) -> 0
B80: Warm Strip Lights | C80: 2.4 | D80: =C80*$L$23 -> 2.64 | E80: l.m | F80: ='Material and Labor Cost'!$D$24 -> 220 | G80: ='Material and Labor Cost'!$F$24 -> 110 | H80: =SUM(F80:G80) -> 330 | I80: =H80*D80 -> 871.2 | Y80: =SUM(AI80:AP80) -> 0 | Z80: =D80*AG80 -> 0 | AA80: =SUM(Y80:Z80) -> 0 | AB80: =D80-AA80 -> 2.64 | AC80: =SUM(AR79:AY79) -> 0 | AD80: =AG80*I80 -> 0 | AE80: =SUM(AC80:AD80) -> 0 | AF80: =I80-AE80 -> 871.2 | AG80: =BA80 -> 0 | AI80: 0 | BA80: =SUM(BK79:BQ79) -> 0 | BC80: =SUM(BS79:BZ79) -> 0 | BD80: =SUM(BN79:BT79) -> 0 | BE80: =SUM(BU79:CB79) -> 0 | BF80: =SUM(BV79:CC79) -> 0 | BG80: =SUM(BW79:CD79) -> 0 | BH80: =SUM(BX79:CE79) -> 0 | BI80: =SUM(BY79:CF79) -> 0 | BJ80: =SUM(BZ79:CG79) -> 0
B81: Ducco Finish | C81: 21.66 | D81: =C81*$L$23 -> 23.826 | E81: sq.m | F81: ='Material and Labor Cost'!$D$25 -> 555 | G81: ='Material and Labor Cost'!$F$25 -> 275 | H81: =SUM(F81:G81) -> 830 | I81: =H81*D81 -> 19775.58 | Y81: =SUM(AI81:AP81) -> 0 | Z81: =D81*AG81 -> 7.1478 | AA81: =SUM(Y81:Z81) -> 7.1478 | AB81: =D81-AA81 -> 16.6782 | AC81: =SUM(AR80:AY80) -> 0 | AD81: =AG81*I81 -> 5932.674 | AE81: =SUM(AC81:AD81) -> 5932.674 | AF81: =I81-AE81 -> 13842.906 | AG81: =BA81 -> 0.3 | AI81: 0 | BA81: 0.3 | BC81: =SUM(BS80:BZ80) -> 0 | BD81: =SUM(BN80:BT80) -> 0 | BE81: =SUM(BU80:CB80) -> 0 | BF81: =SUM(BV80:CC80) -> 0 | BG81: =SUM(BW80:CD80) -> 0 | BH81: =SUM(BX80:CE80) -> 0 | BI81: =SUM(BY80:CF80) -> 0 | BJ81: =SUM(BZ80:CG80) -> 0
B82: Miscellaneous and other Consumables | D82: 1 | E82: lot | I82: =SUM(I77:I81)*$L$27 -> 5954.4144 | Y82: =SUM(AI82:AP82) -> 0 | Z82: =D82*AG82 -> 0.3 | AA82: =SUM(Y82:Z82) -> 0.3 | AB82: =D82-AA82 -> 0.7 | AC82: =SUM(AR81:AY81) -> 0 | AD82: =AG82*I82 -> 1786.3243 | AE82: =SUM(AC82:AD82) -> 1786.3243 | AF82: =I82-AE82 -> 4168.0901 | AG82: =BA82 -> 0.3 | AI82: 0 | BA82: 0.3 | BC82: =SUM(BS81:BZ81) -> 0 | BD82: =SUM(BN81:BT81) -> 0 | BE82: =SUM(BU81:CB81) -> 0 | BF82: =SUM(BV81:CC81) -> 0 | BG82: =SUM(BW81:CD81) -> 0 | BH82: =SUM(BX81:CE81) -> 0 | BI82: =SUM(BY81:CF81) -> 0 | BJ82: =SUM(BZ81:CG81) -> 0
B83: Bedroom 1 (Closets) Sub-total: | I83: =SUM(I77:I82) -> 55574.534 | Y83: =SUM(Y77:Y82) -> 0 | Z83: =SUM(Z77:Z82) -> 40.8878 | AA83: =SUM(AA77:AA82) -> 40.8878 | AB83: =SUM(AB77:AB82) -> 25.2982 | AC83: =SUM(AC77:AC82) -> 0 | AD83: =SUM(AD77:AD82) -> 34078.738 | AE83: =SUM(AE77:AE82) -> 34078.738 | AF83: =SUM(AF77:AF82) -> 21495.796 | AG83: =BA83 -> 0.43333333 | AI83: 0 | BA83: =SUM(BA77:BA82)/COUNT(BA77:BA82) -> 0.43333333 | BC83: =SUM(BC77:BC82)/COUNT(BC77:BC82) -> 0 | BD83: =SUM(BD77:BD82)/COUNT(BD77:BD82) -> 0 | BE83: =SUM(BE77:BE82)/COUNT(BE77:BE82) -> 0 | BF83: =SUM(BF77:BF82)/COUNT(BF77:BF82) -> 0 | BG83: =SUM(BG77:BG82)/COUNT(BG77:BG82) -> 0 | BH83: =SUM(BH77:BH82)/COUNT(BH77:BH82) -> 0 | BI83: =SUM(BI77:BI82)/COUNT(BI77:BI82) -> 0 | BJ83: =SUM(BJ77:BJ82)/COUNT(BJ77:BJ82) -> 0
B84: Bedroom 1 (Table & Top Cabinets) | AG84: =BA84 -> 0
B85: 3/4'' Marine Plywood | C85: 23.41 | D85: =C85*$L$23 -> 25.751 | E85: sq.m | F85: ='Material and Labor Cost'!$D$21 -> 576 | G85: ='Material and Labor Cost'!$F$21 -> 300 | H85: =SUM(F85:G85) -> 876 | I85: =H85*D85 -> 22557.876 | Y85: =SUM(AI85:AP85) -> 0 | Z85: =D85*AG85 -> 25.751 | AA85: =SUM(Y85:Z85) -> 25.751 | AB85: =D85-AA85 -> 0 | AC85: =SUM(AR84:AY84) -> 0 | AD85: =AG85*I85 -> 22557.876 | AE85: =SUM(AC85:AD85) -> 22557.876 | AF85: =I85-AE85 -> 0 | AG85: =BA85 -> 1 | AI85: 0 | BA85: 1 | BC85: =SUM(BS84:BZ84) -> 0 | BD85: =SUM(BN84:BT84) -> 0 | BE85: =SUM(BU84:CB84) -> 0 | BF85: =SUM(BV84:CC84) -> 0 | BG85: =SUM(BW84:CD84) -> 0 | BH85: =SUM(BX84:CE84) -> 0 | BI85: =SUM(BY84:CF84) -> 0 | BJ85: =SUM(BZ84:CG84) -> 0
B86: 1/2'' Backing Marine plywood | C86: 3.4 | D86: =C86*$L$23 -> 3.74 | E86: sq.m | F86: ='Material and Labor Cost'!$D$23 -> 330 | G86: ='Material and Labor Cost'!$F$23 -> 165 | H86: =SUM(F86:G86) -> 495 | I86: =H86*D86 -> 1851.3 | Y86: =SUM(AI86:AP86) -> 0 | Z86: =D86*AG86 -> 3.74 | AA86: =SUM(Y86:Z86) -> 3.74 | AB86: =D86-AA86 -> 0 | AC86: =SUM(AR85:AY85) -> 0 | AD86: =AG86*I86 -> 1851.3 | AE86: =SUM(AC86:AD86) -> 1851.3 | AF86: =I86-AE86 -> 0 | AG86: =BA86 -> 1 | AI86: 0 | BA86: 1 | BC86: =SUM(BS85:BZ85) -> 0 | BD86: =SUM(BN85:BT85) -> 0 | BE86: =SUM(BU85:CB85) -> 0 | BF86: =SUM(BV85:CC85) -> 0 | BG86: =SUM(BW85:CD85) -> 0 | BH86: =SUM(BX85:CE85) -> 0 | BI86: =SUM(BY85:CF85) -> 0 | BJ86: =SUM(BZ85:CG85) -> 0
B87: Vanity Lights | D87: 8 | E87: pcs | F87: ='Material and Labor Cost'!$D$24 -> 220 | G87: ='Material and Labor Cost'!$F$24 -> 110 | H87: =SUM(F87:G87) -> 330 | I87: =H87*D87 -> 2640 | Y87: =SUM(AI87:AP87) -> 0 | Z87: =D87*AG87 -> 0 | AA87: =SUM(Y87:Z87) -> 0 | AB87: =D87-AA87 -> 8 | AC87: =SUM(AR86:AY86) -> 0 | AD87: =AG87*I87 -> 0 | AE87: =SUM(AC87:AD87) -> 0 | AF87: =I87-AE87 -> 2640 | AG87: =BA87 -> 0 | AI87: 0 | BA87: =SUM(BK86:BQ86) -> 0 | BC87: =SUM(BS86:BZ86) -> 0 | BD87: =SUM(BN86:BT86) -> 0 | BE87: =SUM(BU86:CB86) -> 0 | BF87: =SUM(BV86:CC86) -> 0 | BG87: =SUM(BW86:CD86) -> 0 | BH87: =SUM(BX86:CE86) -> 0 | BI87: =SUM(BY86:CF86) -> 0 | BJ87: =SUM(BZ86:CG86) -> 0
B88: Mirror | C88: 1.22 | D88: =C88*$L$23 -> 1.342 | E88: sq.m | F88: ='Material and Labor Cost'!$D$34 -> 1265 | G88: ='Material and Labor Cost'!$F$34 -> 640 | H88: =SUM(F88:G88) -> 1905 | I88: =H88*D88 -> 2556.51 | Y88: =SUM(AI88:AP88) -> 0 | Z88: =D88*AG88 -> 0 | AA88: =SUM(Y88:Z88) -> 0 | AB88: =D88-AA88 -> 1.342 | AC88: =SUM(AR87:AY87) -> 0 | AD88: =AG88*I88 -> 0 | AE88: =SUM(AC88:AD88) -> 0 | AF88: =I88-AE88 -> 2556.51 | AG88: =BA88 -> 0 | AI88: 0 | BA88: =SUM(BK87:BQ87) -> 0 | BC88: =SUM(BS87:BZ87) -> 0 | BD88: =SUM(BN87:BT87) -> 0 | BE88: =SUM(BU87:CB87) -> 0 | BF88: =SUM(BV87:CC87) -> 0 | BG88: =SUM(BW87:CD87) -> 0 | BH88: =SUM(BX87:CE87) -> 0 | BI88: =SUM(BY87:CF87) -> 0 | BJ88: =SUM(BZ87:CG87) -> 0
B89: Ducco Finish | C89: 18.73 | D89: =C89*$L$23 -> 20.603 | E89: sq.m | F89: ='Material and Labor Cost'!$D$25 -> 555 | G89: ='Material and Labor Cost'!$F$25 -> 275 | H89: =SUM(F89:G89) -> 830 | I89: =H89*D89 -> 17100.49 | Y89: =SUM(AI89:AP89) -> 0 | Z89: =D89*AG89 -> 12.3618 | AA89: =SUM(Y89:Z89) -> 12.3618 | AB89: =D89-AA89 -> 8.2412 | AC89: =SUM(AR88:AY88) -> 0 | AD89: =AG89*I89 -> 10260.294 | AE89: =SUM(AC89:AD89) -> 10260.294 | AF89: =I89-AE89 -> 6840.196 | AG89: =BA89 -> 0.6 | AI89: 0 | BA89: 0.6 | BC89: =SUM(BS88:BZ88) -> 0 | BD89: =SUM(BN88:BT88) -> 0 | BE89: =SUM(BU88:CB88) -> 0 | BF89: =SUM(BV88:CC88) -> 0 | BG89: =SUM(BW88:CD88) -> 0 | BH89: =SUM(BX88:CE88) -> 0 | BI89: =SUM(BY88:CF88) -> 0 | BJ89: =SUM(BZ88:CG88) -> 0
B90: Miscellaneous and other Consumables | D90: 1 | E90: lot | I90: =SUM(I85:I89)*$L$27 -> 5604.7411 | Y90: =SUM(AI90:AP90) -> 0 | Z90: =D90*AG90 -> 0.6 | AA90: =SUM(Y90:Z90) -> 0.6 | AB90: =D90-AA90 -> 0.4 | AC90: =SUM(AR89:AY89) -> 0 | AD90: =AG90*I90 -> 3362.8447 | AE90: =SUM(AC90:AD90) -> 3362.8447 | AF90: =I90-AE90 -> 2241.8964 | AG90: =BA90 -> 0.6 | AI90: 0 | BA90: 0.6 | BC90: =SUM(BS89:BZ89) -> 0 | BD90: =SUM(BN89:BT89) -> 0 | BE90: =SUM(BU89:CB89) -> 0 | BF90: =SUM(BV89:CC89) -> 0 | BG90: =SUM(BW89:CD89) -> 0 | BH90: =SUM(BX89:CE89) -> 0 | BI90: =SUM(BY89:CF89) -> 0 | BJ90: =SUM(BZ89:CG89) -> 0
B91: Bedroom 1 (Table & Top Cabinets) Sub-total: | I91: =SUM(I85:I90) -> 52310.917 | Y91: =SUM(Y85:Y90) -> 0 | Z91: =SUM(Z85:Z90) -> 42.4528 | AA91: =SUM(AA85:AA90) -> 42.4528 | AB91: =SUM(AB85:AB90) -> 17.9832 | AC91: =SUM(AC85:AC90) -> 0 | AD91: =SUM(AD85:AD90) -> 38032.315 | AE91: =SUM(AE85:AE90) -> 38032.315 | AF91: =SUM(AF85:AF90) -> 14278.602 | AG91: =BA91 -> 0.53333333 | AI91: 0 | BA91: =SUM(BA85:BA90)/COUNT(BA85:BA90) -> 0.53333333 | BC91: =SUM(BC85:BC90)/COUNT(BC85:BC90) -> 0 | BD91: =SUM(BD85:BD90)/COUNT(BD85:BD90) -> 0 | BE91: =SUM(BE85:BE90)/COUNT(BE85:BE90) -> 0 | BF91: =SUM(BF85:BF90)/COUNT(BF85:BF90) -> 0 | BG91: =SUM(BG85:BG90)/COUNT(BG85:BG90) -> 0 | BH91: =SUM(BH85:BH90)/COUNT(BH85:BH90) -> 0 | BI91: =SUM(BI85:BI90)/COUNT(BI85:BI90) -> 0 | BJ91: =SUM(BJ85:BJ90)/COUNT(BJ85:BJ90) -> 0
B92: Bedroom 2 (Closets) | AG92: =BA92 -> 0
B93: 3/4'' Marine Plywood | C93: 30.24 | D93: =C93*$L$23 -> 33.264 | E93: sq.m | F93: ='Material and Labor Cost'!$D$21 -> 576 | G93: ='Material and Labor Cost'!$F$21 -> 300 | H93: =SUM(F93:G93) -> 876 | I93: =H93*D93 -> 29139.264 | Y93: =SUM(AI93:AP93) -> 0 | Z93: =D93*AG93 -> 33.264 | AA93: =SUM(Y93:Z93) -> 33.264 | AB93: =D93-AA93 -> 0 | AC93: =SUM(AR92:AY92) -> 0 | AD93: =AG93*I93 -> 29139.264 | AE93: =SUM(AC93:AD93) -> 29139.264 | AF93: =I93-AE93 -> 0 | AG93: =BA93 -> 1 | AI93: 0 | BA93: 1 | BC93: =SUM(BS92:BZ92) -> 0 | BD93: =SUM(BN92:BT92) -> 0 | BE93: =SUM(BU92:CB92) -> 0 | BF93: =SUM(BV92:CC92) -> 0 | BG93: =SUM(BW92:CD92) -> 0 | BH93: =SUM(BX92:CE92) -> 0 | BI93: =SUM(BY92:CF92) -> 0 | BJ93: =SUM(BZ92:CG92) -> 0
B94: 1/2'' Backing Marine plywood | C94: 7.8 | D94: =C94*$L$23 -> 8.58 | E94: sq.m | F94: ='Material and Labor Cost'!$D$23 -> 330 | G94: ='Material and Labor Cost'!$F$23 -> 165 | H94: =SUM(F94:G94) -> 495 | I94: =H94*D94 -> 4247.1 | Y94: =SUM(AI94:AP94) -> 0 | Z94: =D94*AG94 -> 8.58 | AA94: =SUM(Y94:Z94) -> 8.58 | AB94: =D94-AA94 -> 0 | AC94: =SUM(AR93:AY93) -> 0 | AD94: =AG94*I94 -> 4247.1 | AE94: =SUM(AC94:AD94) -> 4247.1 | AF94: =I94-AE94 -> 0 | AG94: =BA94 -> 1 | AI94: 0 | BA94: 1 | BC94: =SUM(BS93:BZ93) -> 0 | BD94: =SUM(BN93:BT93) -> 0 | BE94: =SUM(BU93:CB93) -> 0 | BF94: =SUM(BV93:CC93) -> 0 | BG94: =SUM(BW93:CD93) -> 0 | BH94: =SUM(BX93:CE93) -> 0 | BI94: =SUM(BY93:CF93) -> 0 | BJ94: =SUM(BZ93:CG93) -> 0
B95: Stainless Hanging Rod | C95: 4.4 | D95: =C95*$L$23 -> 4.84 | E95: l.m | F95: ='Material and Labor Cost'!$D$33 -> 330 | G95: ='Material and Labor Cost'!$F$33 -> 165 | H95: =SUM(F95:G95) -> 495 | I95: =H95*D95 -> 2395.8 | Y95: =SUM(AI95:AP95) -> 0 | Z95: =D95*AG95 -> 0 | AA95: =SUM(Y95:Z95) -> 0 | AB95: =D95-AA95 -> 4.84 | AC95: =SUM(AR94:AY94) -> 0 | AD95: =AG95*I95 -> 0 | AE95: =SUM(AC95:AD95) -> 0 | AF95: =I95-AE95 -> 2395.8 | AG95: =BA95 -> 0 | AI95: 0 | BA95: =SUM(BK94:BQ94) -> 0 | BC95: =SUM(BS94:BZ94) -> 0 | BD95: =SUM(BN94:BT94) -> 0 | BE95: =SUM(BU94:CB94) -> 0 | BF95: =SUM(BV94:CC94) -> 0 | BG95: =SUM(BW94:CD94) -> 0 | BH95: =SUM(BX94:CE94) -> 0 | BI95: =SUM(BY94:CF94) -> 0 | BJ95: =SUM(BZ94:CG94) -> 0
B96: Warm Strip Lights | C96: 2.7 | D96: =C96*$L$23 -> 2.97 | E96: l.m | F96: ='Material and Labor Cost'!$D$24 -> 220 | G96: ='Material and Labor Cost'!$F$24 -> 110 | H96: =SUM(F96:G96) -> 330 | I96: =H96*D96 -> 980.1 | Y96: =SUM(AI96:AP96) -> 0 | Z96: =D96*AG96 -> 0 | AA96: =SUM(Y96:Z96) -> 0 | AB96: =D96-AA96 -> 2.97 | AC96: =SUM(AR95:AY95) -> 0 | AD96: =AG96*I96 -> 0 | AE96: =SUM(AC96:AD96) -> 0 | AF96: =I96-AE96 -> 980.1 | AG96: =BA96 -> 0 | AI96: 0 | BA96: =SUM(BK95:BQ95) -> 0 | BC96: =SUM(BS95:BZ95) -> 0 | BD96: =SUM(BN95:BT95) -> 0 | BE96: =SUM(BU95:CB95) -> 0 | BF96: =SUM(BV95:CC95) -> 0 | BG96: =SUM(BW95:CD95) -> 0 | BH96: =SUM(BX95:CE95) -> 0 | BI96: =SUM(BY95:CF95) -> 0 | BJ96: =SUM(BZ95:CG95) -> 0
B97: Ducco Finish | C97: 22 | D97: =C97*$L$23 -> 24.2 | E97: sq.m | F97: ='Material and Labor Cost'!$D$25 -> 555 | G97: ='Material and Labor Cost'!$F$25 -> 275 | H97: =SUM(F97:G97) -> 830 | I97: =H97*D97 -> 20086 | Y97: =SUM(AI97:AP97) -> 0 | Z97: =D97*AG97 -> 14.52 | AA97: =SUM(Y97:Z97) -> 14.52 | AB97: =D97-AA97 -> 9.68 | AC97: =SUM(AR96:AY96) -> 0 | AD97: =AG97*I97 -> 12051.6 | AE97: =SUM(AC97:AD97) -> 12051.6 | AF97: =I97-AE97 -> 8034.4 | AG97: =BA97 -> 0.6 | AI97: 0 | BA97: 0.6 | BC97: =SUM(BS96:BZ96) -> 0 | BD97: =SUM(BN96:BT96) -> 0 | BE97: =SUM(BU96:CB96) -> 0 | BF97: =SUM(BV96:CC96) -> 0 | BG97: =SUM(BW96:CD96) -> 0 | BH97: =SUM(BX96:CE96) -> 0 | BI97: =SUM(BY96:CF96) -> 0 | BJ97: =SUM(BZ96:CG96) -> 0
B98: Miscellaneous and other Consumables | D98: 1 | E98: lot | I98: =SUM(I93:I97)*$L$27 -> 6821.7917 | Y98: =SUM(AI98:AP98) -> 0 | Z98: =D98*AG98 -> 0.6 | AA98: =SUM(Y98:Z98) -> 0.6 | AB98: =D98-AA98 -> 0.4 | AC98: =SUM(AR97:AY97) -> 0 | AD98: =AG98*I98 -> 4093.075 | AE98: =SUM(AC98:AD98) -> 4093.075 | AF98: =I98-AE98 -> 2728.7167 | AG98: =BA98 -> 0.6 | AI98: 0 | BA98: 0.6 | BC98: =SUM(BS97:BZ97) -> 0 | BD98: =SUM(BN97:BT97) -> 0 | BE98: =SUM(BU97:CB97) -> 0 | BF98: =SUM(BV97:CC97) -> 0 | BG98: =SUM(BW97:CD97) -> 0 | BH98: =SUM(BX97:CE97) -> 0 | BI98: =SUM(BY97:CF97) -> 0 | BJ98: =SUM(BZ97:CG97) -> 0
B99: Bedroom 2 (Closets) Sub-total: | I99: =SUM(I93:I98) -> 63670.056 | Y99: =SUM(Y93:Y98) -> 0 | Z99: =SUM(Z93:Z98) -> 56.964 | AA99: =SUM(AA93:AA98) -> 56.964 | AB99: =SUM(AB93:AB98) -> 17.89 | AC99: =SUM(AC93:AC98) -> 0 | AD99: =SUM(AD93:AD98) -> 49531.039 | AE99: =SUM(AE93:AE98) -> 49531.039 | AF99: =SUM(AF93:AF98) -> 14139.017 | AG99: =BA99 -> 0.53333333 | AI99: 0 | BA99: =SUM(BA93:BA98)/COUNT(BA93:BA98) -> 0.53333333 | BC99: =SUM(BC93:BC98)/COUNT(BC93:BC98) -> 0 | BD99: =SUM(BD93:BD98)/COUNT(BD93:BD98) -> 0 | BE99: =SUM(BE93:BE98)/COUNT(BE93:BE98) -> 0 | BF99: =SUM(BF93:BF98)/COUNT(BF93:BF98) -> 0 | BG99: =SUM(BG93:BG98)/COUNT(BG93:BG98) -> 0 | BH99: =SUM(BH93:BH98)/COUNT(BH93:BH98) -> 0 | BI99: =SUM(BI93:BI98)/COUNT(BI93:BI98) -> 0 | BJ99: =SUM(BJ93:BJ98)/COUNT(BJ93:BJ98) -> 0
B100: Bedroom 2 (Table & Top Cabinets) | AG100: =BA100 -> 0
B101: 3/4'' Marine Plywood | C101: 10.3992 | D101: =C101*$L$23 -> 11.43912 | E101: sq.m | F101: ='Material and Labor Cost'!$D$21 -> 576 | G101: ='Material and Labor Cost'!$F$21 -> 300 | H101: =SUM(F101:G101) -> 876 | I101: =H101*D101 -> 10020.669 | Y101: =SUM(AI101:AP101) -> 0 | Z101: =D101*AG101 -> 11.43912 | AA101: =SUM(Y101:Z101) -> 11.43912 | AB101: =D101-AA101 -> 0 | AC101: =SUM(AR100:AY100) -> 0 | AD101: =AG101*I101 -> 10020.669 | AE101: =SUM(AC101:AD101) -> 10020.669 | AF101: =I101-AE101 -> 0 | AG101: =BA101 -> 1 | AI101: 0 | BA101: 1 | BC101: =SUM(BS100:BZ100) -> 0 | BD101: =SUM(BN100:BT100) -> 0 | BE101: =SUM(BU100:CB100) -> 0 | BF101: =SUM(BV100:CC100) -> 0 | BG101: =SUM(BW100:CD100) -> 0 | BH101: =SUM(BX100:CE100) -> 0 | BI101: =SUM(BY100:CF100) -> 0 | BJ101: =SUM(BZ100:CG100) -> 0
B102: 1/2'' Backing Marine plywood | C102: 2.4 | D102: =C102*$L$23 -> 2.64 | E102: sq.m | F102: ='Material and Labor Cost'!$D$23 -> 330 | G102: ='Material and Labor Cost'!$F$23 -> 165 | H102: =SUM(F102:G102) -> 495 | I102: =H102*D102 -> 1306.8 | Y102: =SUM(AI102:AP102) -> 0 | Z102: =D102*AG102 -> 2.64 | AA102: =SUM(Y102:Z102) -> 2.64 | AB102: =D102-AA102 -> 0 | AC102: =SUM(AR101:AY101) -> 0 | AD102: =AG102*I102 -> 1306.8 | AE102: =SUM(AC102:AD102) -> 1306.8 | AF102: =I102-AE102 -> 0 | AG102: =BA102 -> 1 | AI102: 0 | BA102: 1 | BC102: =SUM(BS101:BZ101) -> 0 | BD102: =SUM(BN101:BT101) -> 0 | BE102: =SUM(BU101:CB101) -> 0 | BF102: =SUM(BV101:CC101) -> 0 | BG102: =SUM(BW101:CD101) -> 0 | BH102: =SUM(BX101:CE101) -> 0 | BI102: =SUM(BY101:CF101) -> 0 | BJ102: =SUM(BZ101:CG101) -> 0
B103: 2''x1''x2.0mm Tubular Steel | C103: 2.2 | D103: =C103*$L$23 -> 2.42 | E103: l.m | F103: ='Material and Labor Cost'!$D$35 -> 70.18 | G103: ='Material and Labor Cost'!$F$35 -> 35.09 | H103: =SUM(F103:G103) -> 105.27 | I103: =H103*D103 -> 254.7534 | Y103: =SUM(AI103:AP103) -> 0 | Z103: =D103*AG103 -> 0.484 | AA103: =SUM(Y103:Z103) -> 0.484 | AB103: =D103-AA103 -> 1.936 | AC103: =SUM(AR102:AY102) -> 0 | AD103: =AG103*I103 -> 50.95068 | AE103: =SUM(AC103:AD103) -> 50.95068 | AF103: =I103-AE103 -> 203.80272 | AG103: =BA103 -> 0.2 | AI103: 0 | BA103: 0.2 | BC103: =SUM(BS102:BZ102) -> 0 | BD103: =SUM(BN102:BT102) -> 0 | BE103: =SUM(BU102:CB102) -> 0 | BF103: =SUM(BV102:CC102) -> 0 | BG103: =SUM(BW102:CD102) -> 0 | BH103: =SUM(BX102:CE102) -> 0 | BI103: =SUM(BY102:CF102) -> 0 | BJ103: =SUM(BZ102:CG102) -> 0
B104: Warm Strip Lights | C104: 1.62 | D104: =C104*$L$23 -> 1.782 | E104: l.m | F104: ='Material and Labor Cost'!$D$24 -> 220 | G104: ='Material and Labor Cost'!$F$24 -> 110 | H104: =SUM(F104:G104) -> 330 | I104: =H104*D104 -> 588.06 | Y104: =SUM(AI104:AP104) -> 0 | Z104: =D104*AG104 -> 0.3564 | AA104: =SUM(Y104:Z104) -> 0.3564 | AB104: =D104-AA104 -> 1.4256 | AC104: =SUM(AR103:AY103) -> 0 | AD104: =AG104*I104 -> 117.612 | AE104: =SUM(AC104:AD104) -> 117.612 | AF104: =I104-AE104 -> 470.448 | AG104: =BA104 -> 0.2 | AI104: 0 | BA104: 0.2 | BC104: =SUM(BS103:BZ103) -> 0 | BD104: =SUM(BN103:BT103) -> 0 | BE104: =SUM(BU103:CB103) -> 0 | BF104: =SUM(BV103:CC103) -> 0 | BG104: =SUM(BW103:CD103) -> 0 | BH104: =SUM(BX103:CE103) -> 0 | BI104: =SUM(BY103:CF103) -> 0 | BJ104: =SUM(BZ103:CG103) -> 0
B105: Ducco Finish | C105: 7.28 | D105: =C105*$L$23 -> 8.008 | E105: sq.m | F105: ='Material and Labor Cost'!$D$25 -> 555 | G105: ='Material and Labor Cost'!$F$25 -> 275 | H105: =SUM(F105:G105) -> 830 | I105: =H105*D105 -> 6646.64 | Y105: =SUM(AI105:AP105) -> 0 | Z105: =D105*AG105 -> 4.8048 | AA105: =SUM(Y105:Z105) -> 4.8048 | AB105: =D105-AA105 -> 3.2032 | AC105: =SUM(AR104:AY104) -> 0 | AD105: =AG105*I105 -> 3987.984 | AE105: =SUM(AC105:AD105) -> 3987.984 | AF105: =I105-AE105 -> 2658.656 | AG105: =BA105 -> 0.6 | AI105: 0 | BA105: 0.6 | BC105: =SUM(BS104:BZ104) -> 0 | BD105: =SUM(BN104:BT104) -> 0 | BE105: =SUM(BU104:CB104) -> 0 | BF105: =SUM(BV104:CC104) -> 0 | BG105: =SUM(BW104:CD104) -> 0 | BH105: =SUM(BX104:CE104) -> 0 | BI105: =SUM(BY104:CF104) -> 0 | BJ105: =SUM(BZ104:CG104) -> 0
B106: Miscellaneous and other Consumables | D106: 1 | E106: lot | I106: =SUM(I101:I105)*L72 -> 9408.4613 | Y106: =SUM(AI106:AP106) -> 0 | Z106: =D106*AG106 -> 0.6 | AA106: =SUM(Y106:Z106) -> 0.6 | AB106: =D106-AA106 -> 0.4 | AC106: =SUM(AR105:AY105) -> 0 | AD106: =AG106*I106 -> 5645.0768 | AE106: =SUM(AC106:AD106) -> 5645.0768 | AF106: =I106-AE106 -> 3763.3845 | AG106: =BA106 -> 0.6 | AI106: 0 | BA106: 0.6 | BC106: =SUM(BS105:BZ105) -> 0 | BD106: =SUM(BN105:BT105) -> 0 | BE106: =SUM(BU105:CB105) -> 0 | BF106: =SUM(BV105:CC105) -> 0 | BG106: =SUM(BW105:CD105) -> 0 | BH106: =SUM(BX105:CE105) -> 0 | BI106: =SUM(BY105:CF105) -> 0 | BJ106: =SUM(BZ105:CG105) -> 0
B107: Bedroom 2 (Table & Top Cabinets) Sub-total: | I107: =SUM(I101:I106) -> 28225.384 | Y107: =SUM(Y101:Y106) -> 0 | Z107: =SUM(Z101:Z106) -> 20.32432 | AA107: =SUM(AA101:AA106) -> 20.32432 | AB107: =SUM(AB101:AB106) -> 6.9648 | AC107: =SUM(AC101:AC106) -> 0 | AD107: =SUM(AD101:AD106) -> 21129.093 | AE107: =SUM(AE101:AE106) -> 21129.093 | AF107: =SUM(AF101:AF106) -> 7096.2912 | AG107: =BA107 -> 0.6 | AI107: 0 | BA107: =SUM(BA101:BA106)/COUNT(BA101:BA106) -> 0.6 | BC107: =SUM(BC101:BC106)/COUNT(BC101:BC106) -> 0 | BD107: =SUM(BD101:BD106)/COUNT(BD101:BD106) -> 0 | BE107: =SUM(BE101:BE106)/COUNT(BE101:BE106) -> 0 | BF107: =SUM(BF101:BF106)/COUNT(BF101:BF106) -> 0 | BG107: =SUM(BG101:BG106)/COUNT(BG101:BG106) -> 0 | BH107: =SUM(BH101:BH106)/COUNT(BH101:BH106) -> 0 | BI107: =SUM(BI101:BI106)/COUNT(BI101:BI106) -> 0 | BJ107: =SUM(BJ101:BJ106)/COUNT(BJ101:BJ106) -> 0
B108: Bedroom 3 (Closets) | AG108: =BA108 -> 0
B109: 3/4'' Marine Plywood | C109: 24.72 | D109: =C109*$L$23 -> 27.192 | E109: sq.m | F109: ='Material and Labor Cost'!$D$21 -> 576 | G109: ='Material and Labor Cost'!$F$21 -> 300 | H109: =SUM(F109:G109) -> 876 | I109: =H109*D109 -> 23820.192 | Y109: =SUM(AI109:AP109) -> 0 | Z109: =D109*AG109 -> 27.192 | AA109: =SUM(Y109:Z109) -> 27.192 | AB109: =D109-AA109 -> 0 | AC109: =SUM(AR108:AY108) -> 0 | AD109: =AG109*I109 -> 23820.192 | AE109: =SUM(AC109:AD109) -> 23820.192 | AF109: =I109-AE109 -> 0 | AG109: =BA109 -> 1 | AI109: 0 | BA109: 1 | BC109: =SUM(BS108:BZ108) -> 0 | BD109: =SUM(BN108:BT108) -> 0 | BE109: =SUM(BU108:CB108) -> 0 | BF109: =SUM(BV108:CC108) -> 0 | BG109: =SUM(BW108:CD108) -> 0 | BH109: =SUM(BX108:CE108) -> 0 | BI109: =SUM(BY108:CF108) -> 0 | BJ109: =SUM(BZ108:CG108) -> 0
B110: 1/2'' Backing Marine plywood | C110: 6.4 | D110: =C110*$L$23 -> 7.04 | E110: sq.m | F110: ='Material and Labor Cost'!$D$23 -> 330 | G110: ='Material and Labor Cost'!$F$23 -> 165 | H110: =SUM(F110:G110) -> 495 | I110: =H110*D110 -> 3484.8 | Y110: =SUM(AI110:AP110) -> 0 | Z110: =D110*AG110 -> 7.04 | AA110: =SUM(Y110:Z110) -> 7.04 | AB110: =D110-AA110 -> 0 | AC110: =SUM(AR109:AY109) -> 0 | AD110: =AG110*I110 -> 3484.8 | AE110: =SUM(AC110:AD110) -> 3484.8 | AF110: =I110-AE110 -> 0 | AG110: =BA110 -> 1 | AI110: 0 | BA110: 1 | BC110: =SUM(BS109:BZ109) -> 0 | BD110: =SUM(BN109:BT109) -> 0 | BE110: =SUM(BU109:CB109) -> 0 | BF110: =SUM(BV109:CC109) -> 0 | BG110: =SUM(BW109:CD109) -> 0 | BH110: =SUM(BX109:CE109) -> 0 | BI110: =SUM(BY109:CF109) -> 0 | BJ110: =SUM(BZ109:CG109) -> 0
B111: Stainless Hanging Rod | C111: 4.6 | D111: =C111*$L$23 -> 5.06 | E111: l.m | F111: ='Material and Labor Cost'!$D$33 -> 330 | G111: ='Material and Labor Cost'!$F$33 -> 165 | H111: =SUM(F111:G111) -> 495 | I111: =H111*D111 -> 2504.7 | Y111: =SUM(AI111:AP111) -> 0 | Z111: =D111*AG111 -> 0 | AA111: =SUM(Y111:Z111) -> 0 | AB111: =D111-AA111 -> 5.06 | AC111: =SUM(AR110:AY110) -> 0 | AD111: =AG111*I111 -> 0 | AE111: =SUM(AC111:AD111) -> 0 | AF111: =I111-AE111 -> 2504.7 | AG111: =BA111 -> 0 | AI111: 0 | BA111: =SUM(BK110:BQ110) -> 0 | BC111: =SUM(BS110:BZ110) -> 0 | BD111: =SUM(BN110:BT110) -> 0 | BE111: =SUM(BU110:CB110) -> 0 | BF111: =SUM(BV110:CC110) -> 0 | BG111: =SUM(BW110:CD110) -> 0 | BH111: =SUM(BX110:CE110) -> 0 | BI111: =SUM(BY110:CF110) -> 0 | BJ111: =SUM(BZ110:CG110) -> 0
B112: Warm Strip Lights | C112: 2.3 | D112: =C112*$L$23 -> 2.53 | E112: l.m | F112: ='Material and Labor Cost'!$D$24 -> 220 | G112: ='Material and Labor Cost'!$F$24 -> 110 | H112: =SUM(F112:G112) -> 330 | I112: =H112*D112 -> 834.9 | Y112: =SUM(AI112:AP112) -> 0 | Z112: =D112*AG112 -> 0 | AA112: =SUM(Y112:Z112) -> 0 | AB112: =D112-AA112 -> 2.53 | AC112: =SUM(AR111:AY111) -> 0 | AD112: =AG112*I112 -> 0 | AE112: =SUM(AC112:AD112) -> 0 | AF112: =I112-AE112 -> 834.9 | AG112: =BA112 -> 0 | AI112: 0 | BA112: =SUM(BK111:BQ111) -> 0 | BC112: =SUM(BS111:BZ111) -> 0 | BD112: =SUM(BN111:BT111) -> 0 | BE112: =SUM(BU111:CB111) -> 0 | BF112: =SUM(BV111:CC111) -> 0 | BG112: =SUM(BW111:CD111) -> 0 | BH112: =SUM(BX111:CE111) -> 0 | BI112: =SUM(BY111:CF111) -> 0 | BJ112: =SUM(BZ111:CG111) -> 0
...

Sheet DOORS & WINDOW, PLUMBING, WOODE
A13: Project name : | B13: PROPOSED THREE STORY RESIDENCE
A14: Location : | B14: GRAND CENTENIAL HOMES KAWIT CAVITE
A15: Date : | B15: =TODAY() -> 46251
T16: QUANTITY | AC16: AMOUNT | AL16: ACCOMPLISHMENT | AN16: PREVIOUS ACCOMPLISHMENT
A17: ITEM NO | B17: Description | C17: QUANTITY | D17: UNIT | E17: Material Cost Php/unit | F17: Labor and Equipment Cost Php/unit | G17: Total Cost Php/Unit | H17: Total Amount Php | J17: QUANTITY | N17: AMOUNT | R17: PERCENTAGE | T17: BILLING 1 | U17: BILLING 2 | V17: BILLING 3 | W17: BILLING 4 | X17: BILLING 5 | Y17: BILLING 6 | Z17: BILLING 7 | AA17: BILLING 8 | AC17: BILLING 1 | AD17: BILLING 2 | AE17: BILLING 3 | AF17: BILLING 4 | AG17: BILLING 5 | AH17: BILLING 6 | AI17: BILLING 7 | AJ17: BILLING 8 | AL17: BILLING | AN17: BILLING 1 | AO17: BILLING 2 | AP17: BILLING 3 | AQ17: BILLING 4 | AR17: BILLING 5 | AS17: BILLING 6 | AT17: BILLING 7 | AU17: BILLING 8
B18: DOORS ( Door Jamb included) | J18: PREVIOUS | K18: THIS DATE | L18: TO DATE | M18: BALANCE | N18: PREVIOUS | O18: THIS DATE | P18: TO DATE | Q18: BALANCE | R18: Accomplishment
A19: D1 | B19: 1.20X2.40 ( MAIN DOOR ) MAHOGANY WOOD PANEL DOOR WITH PIVOT HINGE MECHANISM | C19: 1 | D19: sets | E19: ='Materials labor doors and windo'!$D$4 -> 25300 | F19: ='Materials labor doors and windo'!$F$4 -> 13300 | G19: =SUM(E19,F19) -> 38600 | H19: =C19*G19 -> 38600 | J19: =SUM(T19:AA19) -> 0 | K19: =C19*R19 -> 0 | L19: =SUM(J19:K19) -> 0 | M19: =C19-L19 -> 1 | N19: =SUM(AC19:AJ19) -> 0 | O19: =R19*H19 -> 0 | P19: =SUM(N19:O19) -> 0 | Q19: =H19-P19 -> 38600 | R19: =SUM(AL19) -> 0 | AN19: 0 | AO19: 0 | AP19: 0 | AQ19: 0 | AR19: 0 | AS19: 0 | AT19: 0 | AU19: 0
A20: D2 | B20: 1.26x2.40 (2ND FLR HALLWAY) MAHOGANY WOOD PANEL DOOR AND FIXED WINDOW WITH 2"X6" DOOR JAMB | C20: 1 | D20: sets | E20: ='Materials labor doors and windo'!$D$5 -> 25300 | F20: ='Materials labor doors and windo'!$F$5 -> 13300 | G20: =SUM(E20,F20) -> 38600 | H20: =C20*G20 -> 38600 | J20: =SUM(T20:AA20) -> 0 | K20: =C20*R20 -> 0 | L20: =SUM(J20:K20) -> 0 | M20: =C20-L20 -> 1 | N20: =SUM(AC20:AJ20) -> 0 | O20: =R20*H20 -> 0 | P20: =SUM(N20:O20) -> 0 | Q20: =H20-P20 -> 38600 | R20: =SUM(AL20) -> 0 | AO20: 0
A21: D3 | B21: 0.80x2.40 (MASTER'S BEDROOM, BEDROOM 1,2,3,4, & ROOF DECK) MAHOGANY WOOD PANEL DOOR WITH 2"X6" DOOR JAMB | C21: 6 | D21: sets | E21: FREE | F21: FREE
A22: D4 | B22: 0.70x2.40 (OFFICE, T ANDB ,&POWDER ROOM) MAHOGANY WOOD PANEL DOOR WITH 2"X6" DOOR JAMB | C22: 5 | D22: sets | E22: ='Materials labor doors and windo'!$D$7 -> 23100 | F22: ='Materials labor doors and windo'!$F$7 -> 12130 | G22: =SUM(E22,F22) -> 35230 | H22: =C22*G22 -> 176150 | J22: =SUM(T22:AA22) -> 0 | K22: =C22*R22 -> 2.5 | L22: =SUM(J22:K22) -> 2.5 | M22: =C22-L22 -> 2.5 | N22: =SUM(AC22:AJ22) -> 0 | O22: =R22*H22 -> 88075 | P22: =SUM(N22:O22) -> 88075 | Q22: =H22-P22 -> 88075 | R22: =SUM(AL22) -> 0.5 | AL22: 0.5 | AO22: 0.5
A23: DK1 | B23: Digital Door Knob | C23: 1 | D23: sets | E23: ='Materials labor doors and windo'!$D$8 -> 37400 | F23: ='Materials labor doors and windo'!$F$8 -> 19640 | G23: =SUM(E23,F23) -> 57040 | H23: =C23*G23 -> 57040 | J23: =SUM(T23:AA23) -> 0 | K23: =C23*R23 -> 0.5 | L23: =SUM(J23:K23) -> 0.5 | M23: =C23-L23 -> 0.5 | N23: =SUM(AC23:AJ23) -> 0 | O23: =R23*H23 -> 28520 | P23: =SUM(N23:O23) -> 28520 | Q23: =H23-P23 -> 28520 | R23: =SUM(AL23) -> 0.5 | AL23: 0.5 | AO23: 0
A24: DK2 | B24: Door Knob | C24: 12 | D24: sets | E24: ='Materials labor doors and windo'!$D$9 -> 9130 | F24: ='Materials labor doors and windo'!$F$9 -> 4800 | G24: =SUM(E24,F24) -> 13930 | H24: =C24*G24 -> 167160 | J24: =SUM(T24:AA24) -> 0 | K24: =C24*R24 -> 6 | L24: =SUM(J24:K24) -> 6 | M24: =C24-L24 -> 6 | N24: =SUM(AC24:AJ24) -> 0 | O24: =R24*H24 -> 83580 | P24: =SUM(N24:O24) -> 83580 | Q24: =H24-P24 -> 83580 | R24: =SUM(AL24) -> 0.5 | AL24: 0.5 | AO24: 0
A25: D5 | B25: 1.20x2.40 (KITCHEN AREA, 2ND AND 3RD FLR BALCONY) ALUMINUM FRAMED 6MM THK. ANNEALED GLASS DOOR | C25: 3 | D25: sets | E25: ='Materials labor doors and windo'!$D$10 -> 18220 | F25: ='Materials labor doors and windo'!$F$10 -> 9572.4 | G25: =SUM(E25,F25) -> 27792.4 | H25: =C25*G25 -> 83377.2 | J25: =SUM(T25:AA25) -> 0 | K25: =C25*R25 -> 1.5 | L25: =SUM(J25:K25) -> 1.5 | M25: =C25-L25 -> 1.5 | N25: =SUM(AC25:AJ25) -> 0 | O25: =R25*H25 -> 41688.6 | P25: =SUM(N25:O25) -> 41688.6 | Q25: =H25-P25 -> 41688.6 | R25: =SUM(AL25) -> 0.5 | AL25: 0.5 | AO25: 0.5
A26: SD1 | B26: 3.20x2.40 (LIVING AND DINING AREA) ALUMINUM FRAMED 6MM THK. ANNEALED SLIDING GLASS DOOR | C26: 3 | D26: sets | E26: ='Materials labor doors and windo'!$D$11 -> 50100 | F26: ='Materials labor doors and windo'!$F$11 -> 26312 | G26: =SUM(E26,F26) -> 76412 | H26: =C26*G26 -> 229236 | J26: =SUM(T26:AA26) -> 0 | K26: =C26*R26 -> 0 | L26: =SUM(J26:K26) -> 0 | M26: =C26-L26 -> 3 | N26: =SUM(AC26:AJ26) -> 0 | O26: =R26*H26 -> 0 | P26: =SUM(N26:O26) -> 0 | Q26: =H26-P26 -> 229236 | R26: =SUM(AL26) -> 0 | AL26: 0 | AO26: 1
A27: SD2 | B27: 2.65x2.40 (DINING AREA) ALUMINUM FRAMED 6MM THK. ANNEALED SLIDING GLASS DOOR | C27: 1 | D27: sets | E27: ='Materials labor doors and windo'!$D$12 -> 48700 | F27: ='Materials labor doors and windo'!$F$12 -> 25574 | G27: =SUM(E27,F27) -> 74274 | H27: =C27*G27 -> 74274 | J27: =SUM(T27:AA27) -> 0 | K27: =C27*R27 -> 0 | L27: =SUM(J27:K27) -> 0 | M27: =C27-L27 -> 1 | N27: =SUM(AC27:AJ27) -> 0 | O27: =R27*H27 -> 0 | P27: =SUM(N27:O27) -> 0 | Q27: =H27-P27 -> 74274 | R27: =SUM(AL27) -> 0 | AL27: 0 | AO27: 1
A28: SD3 | B28: 2.00x2.40 (OFFICE ROOM) ALUMINUM FRAMED 6MM THK. ANNEALED FIXED AND SWING GLASS DOOR | C28: 1 | D28: sets | E28: ='Materials labor doors and windo'!$D$13 -> 33300 | F28: ='Materials labor doors and windo'!$F$13 -> 17486 | G28: =SUM(E28,F28) -> 50786 | H28: =C28*G28 -> 50786 | J28: =SUM(T28:AA28) -> 0 | K28: =C28*R28 -> 0 | L28: =SUM(J28:K28) -> 0 | M28: =C28-L28 -> 1 | N28: =SUM(AC28:AJ28) -> 0 | O28: =R28*H28 -> 0 | P28: =SUM(N28:O28) -> 0 | Q28: =H28-P28 -> 50786 | R28: =SUM(AL28) -> 0 | AL28: 0 | AO28: 1
A29: SD4 | B29: 1.80x2.40 (BEDROOM 1 AND 2) ALUMINUM FRAMED 6MM THK. ANNEALED SLIDING GLASS DOOR | C29: 2 | D29: sets | E29: ='Materials labor doors and windo'!$D$14 -> 27330 | F29: ='Materials labor doors and windo'!$F$14 -> 14348.6 | G29: =SUM(E29,F29) -> 41678.6 | H29: =C29*G29 -> 83357.2 | J29: =SUM(T29:AA29) -> 0 | K29: =C29*R29 -> 0 | L29: =SUM(J29:K29) -> 0 | M29: =C29-L29 -> 2 | N29: =SUM(AC29:AJ29) -> 0 | O29: =R29*H29 -> 0 | P29: =SUM(N29:O29) -> 0 | Q29: =H29-P29 -> 83357.2 | R29: =SUM(AL29) -> 0 | AL29: 0 | AO29: 1
A30: SD5 | B30: 2.80x2.80 (BEDROOM 4) ALUMINUM FRAMED 6MM THK. ANNEALED SLIDING GLASS DOOR | C30: 1 | D30: sets | E30: ='Materials labor doors and windo'!$D$15 -> 51480 | F30: ='Materials labor doors and windo'!$F$15 -> 27031.6 | G30: =SUM(E30,F30) -> 78511.6 | H30: =C30*G30 -> 78511.6 | J30: =SUM(T30:AA30) -> 0 | K30: =C30*R30 -> 0 | L30: =SUM(J30:K30) -> 0 | M30: =C30-L30 -> 1 | N30: =SUM(AC30:AJ30) -> 0 | O30: =R30*H30 -> 0 | P30: =SUM(N30:O30) -> 0 | Q30: =H30-P30 -> 78511.6 | R30: =SUM(AL30) -> 0 | AL30: 0 | AO30: 1
A31: SD6 | B31: 3.15x2.40 (WALK-IN CLOSET) ALUMINUM FRAMED 6MM THK. ANNEALED SLIDING MIRROR GLASS DOOR | C31: 1 | D31: sets | E31: ='Materials labor doors and windo'!$D$16 -> 47820 | F31: ='Materials labor doors and windo'!$F$16 -> 25109.4 | G31: =SUM(E31,F31) -> 72929.4 | H31: =C31*G31 -> 72929.4 | J31: =SUM(T31:AA31) -> 0 | K31: =C31*R31 -> 0 | L31: =SUM(J31:K31) -> 0 | M31: =C31-L31 -> 1 | N31: =SUM(AC31:AJ31) -> 0 | O31: =R31*H31 -> 0 | P31: =SUM(N31:O31) -> 0 | Q31: =H31-P31 -> 72929.4 | R31: =SUM(AL31) -> 0 | AL31: 0 | AO31: 1
A32: SD7 | B32: 3.00x2.40 (MASTER'S BEDROOM) ALUMINUM FRAMED 6MM THK. ANNEALED SLIDING GLASS DOOR | C32: 1 | D32: sets | E32: ='Materials labor doors and windo'!$D$17 -> 45540 | F32: ='Materials labor doors and windo'!$F$17 -> 23916.8 | G32: =SUM(E32,F32) -> 69456.8 | H32: =C32*G32 -> 69456.8 | J32: =SUM(T32:AA32) -> 0 | K32: =C32*R32 -> 0 | L32: =SUM(J32:K32) -> 0 | M32: =C32-L32 -> 1 | N32: =SUM(AC32:AJ32) -> 0 | O32: =R32*H32 -> 0 | P32: =SUM(N32:O32) -> 0 | Q32: =H32-P32 -> 69456.8 | R32: =SUM(AL32) -> 0 | AL32: 0 | AO32: 1
A33: SD8 | B33: 2.27x2.40 (MEMORABILIA) ALUMINUM FRAMED 6MM THK. ANNEALED SLIDING GLASS DOOR | C33: 1 | D33: sets | E33: ='Materials labor doors and windo'!$D$18 -> 34160 | F33: ='Materials labor doors and windo'!$F$18 -> 17937.2 | G33: =SUM(E33,F33) -> 52097.2 | H33: =C33*G33 -> 52097.2 | J33: =SUM(T33:AA33) -> 0 | K33: =C33*R33 -> 0 | L33: =SUM(J33:K33) -> 0 | M33: =C33-L33 -> 1 | N33: =SUM(AC33:AJ33) -> 0 | O33: =R33*H33 -> 0 | P33: =SUM(N33:O33) -> 0 | Q33: =H33-P33 -> 52097.2 | R33: =SUM(AL33) -> 0 | AL33: 0 | AO33: 1
B34: Sub-Total For Doors | H34: =SUM(H19:H33) -> 1271575.4 | J34: =SUM(J19:J33) -> 0 | K34: =SUM(K19:K33) -> 10.5 | L34: =SUM(L19:L33) -> 10.5 | M34: =SUM(M19:M33) -> 23.5 | N34: =SUM(N19:N33) -> 0 | O34: =SUM(O19:O33) -> 241863.6 | P34: =SUM(P19:P33) -> 241863.6 | Q34: =SUM(Q19:Q33) -> 1029711.8 | R34: =(SUM(R19:R33)/COUNT(R19:R33)) -> 0.14285714 | AN34: =(SUM(AN19:AN33)/COUNT(AN19:AN33)) -> 0 | AO34: =(SUM(AO19:AO33)/COUNT(AO19:AO33)) -> 0.64285714 | AP34: =(SUM(AP19:AP33)/COUNT(AP19:AP33)) -> 0 | AQ34: =(SUM(AQ19:AQ33)/COUNT(AQ19:AQ33)) -> 0 | AR34: =(SUM(AR19:AR33)/COUNT(AR19:AR33)) -> 0 | AS34: =(SUM(AS19:AS33)/COUNT(AS19:AS33)) -> 0 | AT34: =(SUM(AT19:AT33)/COUNT(AT19:AT33)) -> 0 | AU34: =(SUM(AU19:AU33)/COUNT(AU19:AU33)) -> 0
B35: WINDOWS
A36: W1 | B36: 2.40X2.40 (FOYER) ALUMINUM FRAMED 6MM THK. ANNEALED FIXED WINDOW | C36: 1 | D36: sets | E36: ='Materials labor doors and windo'!$D$21 -> 24290 | F36: ='Materials labor doors and windo'!$F$21 -> 12761.8 | G36: =SUM(E36,F36) -> 37051.8 | H36: =C36*G36 -> 37051.8 | J36: =SUM(T36:AA36) -> 0 | K36: =C36*R36 -> 0 | L36: =SUM(J36:K36) -> 0 | M36: =C36-L36 -> 1 | N36: =SUM(AC36:AJ36) -> 0 | O36: =R36*H36 -> 0 | P36: =SUM(N36:O36) -> 0 | Q36: =H36-P36 -> 37051.8 | R36: =SUM(AL36) -> 0 | AL36: 0 | AO36: 1
A37: W2 | B37: 2.00x2.40 (OFFICE ROOM) ALUMINUM FRAMED 6MM THK. ANNEALED FIXED WINDOW | C37: 1 | D37: sets | E37: ='Materials labor doors and windo'!$D$22 -> 21260 | F37: ='Materials labor doors and windo'!$F$22 -> 11169.2 | G37: =SUM(E37,F37) -> 32429.2 | H37: =C37*G37 -> 32429.2 | J37: =SUM(T37:AA37) -> 0 | K37: =C37*R37 -> 0 | L37: =SUM(J37:K37) -> 0 | M37: =C37-L37 -> 1 | N37: =SUM(AC37:AJ37) -> 0 | O37: =R37*H37 -> 0 | P37: =SUM(N37:O37) -> 0 | Q37: =H37-P37 -> 32429.2 | R37: =SUM(AL37) -> 0 | AL37: 0 | AO37: 1
A38: W3 | B38: 0.60x1.80 {BEDROOM 1,2,4 And Master's BEDROOM) ALUMINUM FRAMED 6MM THK. ANNEALED FIXED WINDOW WITH AWNING WINDOW | C38: 5 | D38: sets | E38: ='Materials labor doors and windo'!$D$23 -> 6380 | F38: ='Materials labor doors and windo'!$F$23 -> 3349.6 | G38: =SUM(E38,F38) -> 9729.6 | H38: =C38*G38 -> 48648 | J38: =SUM(T38:AA38) -> 0 | K38: =C38*R38 -> 0 | L38: =SUM(J38:K38) -> 0 | M38: =C38-L38 -> 5 | N38: =SUM(AC38:AJ38) -> 0 | O38: =R38*H38 -> 0 | P38: =SUM(N38:O38) -> 0 | Q38: =H38-P38 -> 48648 | R38: =SUM(AL38) -> 0 | AL38: 0 | AN38: 0 | AO38: 1 | AP38: 0 | AQ38: 0 | AR38: 0 | AS38: 0 | AT38: 0 | AU38: 0
A39: W4 | B39: 0.60x0.60 (BEDROOM 2 T AND B, MASTER'S T & B) ALUMINUM FRAMED 6MM THK. ANNEALED AWNING WINDOW | C39: 2 | D39: sets | E39: ='Materials labor doors and windo'!$D$24 -> 2750 | F39: ='Materials labor doors and windo'!$F$24 -> 1445 | G39: =SUM(E39,F39) -> 4195 | H39: =C39*G39 -> 8390 | J39: =SUM(T39:AA39) -> 0 | K39: =C39*R39 -> 0 | L39: =SUM(J39:K39) -> 0 | M39: =C39-L39 -> 2 | N39: =SUM(AC39:AJ39) -> 0 | O39: =R39*H39 -> 0 | P39: =SUM(N39:O39) -> 0 | Q39: =H39-P39 -> 8390 | R39: =SUM(AL39) -> 0 | AL39: 0 | AO39: 1
A40: W5 | B40: 0.90x1.50(2ND FLR COMMON T AND B) ALUMINUM FRAMED 6MM THK. ANNEALED FIXED WINDOW | C40: 1 | D40: sets | E40: ='Materials labor doors and windo'!$D$25 -> 5720 | F40: ='Materials labor doors and windo'!$F$25 -> 3012.4 | G40: =SUM(E40,F40) -> 8732.4 | H40: =C40*G40 -> 8732.4 | J40: =SUM(T40:AA40) -> 0 | K40: =C40*R40 -> 0 | L40: =SUM(J40:K40) -> 0 | M40: =C40-L40 -> 1 | N40: =SUM(AC40:AJ40) -> 0 | O40: =R40*H40 -> 0 | P40: =SUM(N40:O40) -> 0 | Q40: =H40-P40 -> 8732.4 | R40: =SUM(AL40) -> 0 | AL40: 0 | AO40: 1
A41: W6 | B41: 1.80x1.50 (BEDROOM 3) ALUMINUM FRAMED 6MM THK. ANNEALED SLIDING WINDOW | C41: 1 | D41: sets | E41: ='Materials labor doors and windo'!$D$26 -> 13750 | F41: ='Materials labor doors and windo'!$F$26 -> 7225 | G41: =SUM(E41,F41) -> 20975 | H41: =C41*G41 -> 20975 | J41: =SUM(T41:AA41) -> 0 | K41: =C41*R41 -> 0 | L41: =SUM(J41:K41) -> 0 | M41: =C41-L41 -> 1 | N41: =SUM(AC41:AJ41) -> 0 | O41: =R41*H41 -> 0 | P41: =SUM(N41:O41) -> 0 | Q41: =H41-P41 -> 20975 | R41: =SUM(AL41) -> 0 | AL41: 0 | AO41: 1
A42: W7 | B42: 1.00x1.80 (MASTER'S BEDROOM) ALUMINUM FRAMED 6MM THK. ANNEALED FIXED WINDOW | C42: 1 | D42: sets | E42: ='Materials labor doors and windo'!$D$27 -> 9350 | F42: ='Materials labor doors and windo'!$F$27 -> 4917 | G42: =SUM(E42,F42) -> 14267 | H42: =C42*G42 -> 14267 | J42: =SUM(T42:AA42) -> 0 | K42: =C42*R42 -> 0 | L42: =SUM(J42:K42) -> 0 | M42: =C42-L42 -> 1 | N42: =SUM(AC42:AJ42) -> 0 | O42: =R42*H42 -> 0 | P42: =SUM(N42:O42) -> 0 | Q42: =H42-P42 -> 14267 | R42: =SUM(AL42) -> 0 | AL42: 0 | AO42: 1
A43: W8 | B43: 2.70x1.43 (MASTER'S TOILET AND BATH) ALUMINUM FRAMED 6MM THK. ANNEALED FIXED WINDOW | C43: 1 | D43: sets | E43: ='Materials labor doors and windo'!$D$28 -> 20020 | F43: ='Materials labor doors and windo'!$F$28 -> 10518.4 | G43: =SUM(E43,F43) -> 30538.4 | H43: =C43*G43 -> 30538.4 | J43: =SUM(T43:AA43) -> 0 | K43: =C43*R43 -> 0 | L43: =SUM(J43:K43) -> 0 | M43: =C43-L43 -> 1 | N43: =SUM(AC43:AJ43) -> 0 | O43: =R43*H43 -> 0 | P43: =SUM(N43:O43) -> 0 | Q43: =H43-P43 -> 30538.4 | R43: =SUM(AL43) -> 0 | AL43: 0 | AO43: 1
B44: Sub --Total For Window | H44: =SUM(H36:H43) -> 201031.8 | J44: =SUM(J36:J43) -> 0 | K44: =SUM(K36:K43) -> 0 | L44: =SUM(L36:L43) -> 0 | M44: =SUM(M36:M43) -> 13 | N44: =SUM(N36:N43) -> 0 | O44: =SUM(O36:O43) -> 0 | P44: =SUM(P36:P43) -> 0 | Q44: =SUM(Q36:Q43) -> 201031.8 | R44: =(SUM(R36:R43)/COUNT(R36:R43)) -> 0 | AN44: =(SUM(AN36:AN43)/COUNT(AN36:AN43)) -> 0 | AO44: =(SUM(AO36:AO43)/COUNT(AO36:AO43)) -> 1 | AP44: =(SUM(AP36:AP43)/COUNT(AP36:AP43)) -> 0 | AQ44: =(SUM(AQ36:AQ43)/COUNT(AQ36:AQ43)) -> 0 | AR44: =(SUM(AR36:AR43)/COUNT(AR36:AR43)) -> 0 | AS44: =(SUM(AS36:AS43)/COUNT(AS36:AS43)) -> 0 | AT44: =(SUM(AT36:AT43)/COUNT(AT36:AT43)) -> 0 | AU44: =(SUM(AU36:AU43)/COUNT(AU36:AU43)) -> 0
B45: SHOWER ENCLOSURE
A46: SD9 | B46: 2.82X2.40 (MASTER'S TOILET AND BATH SHOWER ENCLOSURE) 6MM THK TEMPERED GLASS | C46: 1 | D46: sets | E46: ='Materials labor doors and windo'!$D$30 -> 6600 | F46: ='Materials labor doors and windo'!$F$30 -> 3300 | G46: =SUM(E46,F46) -> 9900 | H46: =G46*C46 -> 9900 | J46: =SUM(T46:AA46) -> 0 | K46: =C46*R46 -> 0 | L46: =SUM(J46:K46) -> 0 | M46: =C46-L46 -> 1 | N46: =SUM(AC46:AJ46) -> 0 | O46: =R46*H46 -> 0 | P46: =SUM(N46:O46) -> 0 | Q46: =H46-P46 -> 9900 | R46: =SUM(AL46) -> 0
A47: SD10 | B47: 1.37x2.18 (BEDROOM 2 (T & B SHOWER ENCLOSURE) GOLD ALUMINUM FRAMED 6MM THK. FIXED AND SLIDING GLASS | C47: 1 | D47: sets | E47: ='Materials labor doors and windo'!$D$31 -> 6600 | F47: ='Materials labor doors and windo'!$F$31 -> 3300 | G47: =SUM(E47,F47) -> 9900 | H47: =G47*C47 -> 9900 | J47: =SUM(T47:AA47) -> 0 | K47: =C47*R47 -> 0 | L47: =SUM(J47:K47) -> 0 | M47: =C47-L47 -> 1 | N47: =SUM(AC47:AJ47) -> 0 | O47: =R47*H47 -> 0 | P47: =SUM(N47:O47) -> 0 | Q47: =H47-P47 -> 9900 | R47: =SUM(AL47) -> 0
A48: M1 | B48: 0.45x1.15 (BEDROOM 2 (T & B)) 6MM THK MIRROR GLASS | C48: 1 | D48: sets | E48: ='Materials labor doors and windo'!$D$32 -> 6600 | F48: ='Materials labor doors and windo'!$F$32 -> 3300 | G48: =SUM(E48,F48) -> 9900 | H48: =G48*C48 -> 9900 | J48: =SUM(T48:AA48) -> 0 | K48: =C48*R48 -> 0 | L48: =SUM(J48:K48) -> 0 | M48: =C48-L48 -> 1 | N48: =SUM(AC48:AJ48) -> 0 | O48: =R48*H48 -> 0 | P48: =SUM(N48:O48) -> 0 | Q48: =H48-P48 -> 9900 | R48: =SUM(AL48) -> 0
A49: M2 | B49: 1.47x1.22 (MASTER'S TOILET AND BATH) 6MM THK MIRROR GLASS | C49: 1 | D49: sets | E49: ='Materials labor doors and windo'!$D$33 -> 6600 | F49: ='Materials labor doors and windo'!$F$33 -> 3300 | G49: =SUM(E49,F49) -> 9900 | H49: =G49*C49 -> 9900 | J49: =SUM(T49:AA49) -> 0 | K49: =C49*R49 -> 0 | L49: =SUM(J49:K49) -> 0 | M49: =C49-L49 -> 1 | N49: =SUM(AC49:AJ49) -> 0 | O49: =R49*H49 -> 0 | P49: =SUM(N49:O49) -> 0 | Q49: =H49-P49 -> 9900 | R49: =SUM(AL49) -> 0
A50: M3 | B50: 1.00x1.30(WALK-IN CLOSET) 6MM THK MIRROR GLASS WITH STRIP LIGHT | C50: 1 | D50: sets | E50: ='Materials labor doors and windo'!$D$34 -> 6600 | F50: ='Materials labor doors and windo'!$F$34 -> 3300 | G50: =SUM(E50,F50) -> 9900 | H50: =G50*C50 -> 9900 | J50: =SUM(T50:AA50) -> 0 | K50: =C50*R50 -> 0 | L50: =SUM(J50:K50) -> 0 | M50: =C50-L50 -> 1 | N50: =SUM(AC50:AJ50) -> 0 | O50: =R50*H50 -> 0 | P50: =SUM(N50:O50) -> 0 | Q50: =H50-P50 -> 9900 | R50: =SUM(AL50) -> 0
A51: M4 | B51: 1.35x0.90 (BEDROOM 1) 6MM THK MIRROR GLASS | C51: 1 | D51: sets | E51: ='Materials labor doors and windo'!$D$35 -> 6600 | F51: ='Materials labor doors and windo'!$F$35 -> 3300 | G51: =SUM(E51,F51) -> 9900 | H51: =G51*C51 -> 9900 | J51: =SUM(T51:AA51) -> 0 | K51: =C51*R51 -> 0 | L51: =SUM(J51:K51) -> 0 | M51: =C51-L51 -> 1 | N51: =SUM(AC51:AJ51) -> 0 | O51: =R51*H51 -> 0 | P51: =SUM(N51:O51) -> 0 | Q51: =H51-P51 -> 9900 | R51: =SUM(AL51) -> 0
A52: M5 | B52: 1.60x0.90 (BEDROOM 3) 6MM THK MIRROR GLASS | C52: 1 | D52: sets | E52: ='Materials labor doors and windo'!$D$36 -> 6600 | F52: ='Materials labor doors and windo'!$F$36 -> 3300 | G52: =SUM(E52,F52) -> 9900 | H52: =G52*C52 -> 9900 | J52: =SUM(T52:AA52) -> 0 | K52: =C52*R52 -> 0 | L52: =SUM(J52:K52) -> 0 | M52: =C52-L52 -> 1 | N52: =SUM(AC52:AJ52) -> 0 | O52: =R52*H52 -> 0 | P52: =SUM(N52:O52) -> 0 | Q52: =H52-P52 -> 9900 | R52: =SUM(AL52) -> 0
A53: M6 | B53: 2.00x0.90 (BEDROOM 4) 6MM THK MIRROR GLASS | C53: 1 | D53: sets | E53: ='Materials labor doors and windo'!$D$37 -> 6600 | F53: ='Materials labor doors and windo'!$F$37 -> 3300 | G53: =SUM(E53,F53) -> 9900 | H53: =G53*C53 -> 9900 | J53: =SUM(T53:AA53) -> 0 | K53: =C53*R53 -> 0 | L53: =SUM(J53:K53) -> 0 | M53: =C53-L53 -> 1 | N53: =SUM(AC53:AJ53) -> 0 | O53: =R53*H53 -> 0 | P53: =SUM(N53:O53) -> 0 | Q53: =H53-P53 -> 9900 | R53: =SUM(AL53) -> 0
A54: M7 | B54: 0.80x2.70 (FOYER) 6MM THK MIRROR GLASS | C54: 1 | D54: sets | E54: ='Materials labor doors and windo'!$D$38 -> 6600 | F54: ='Materials labor doors and windo'!$F$38 -> 3300 | G54: =SUM(E54,F54) -> 9900 | H54: =G54*C54 -> 9900 | J54: =SUM(T54:AA54) -> 0 | K54: =C54*R54 -> 0 | L54: =SUM(J54:K54) -> 0 | M54: =C54-L54 -> 1 | N54: =SUM(AC54:AJ54) -> 0 | O54: =R54*H54 -> 0 | P54: =SUM(N54:O54) -> 0 | Q54: =H54-P54 -> 9900 | R54: =SUM(AL54) -> 0
B55: Sub-total for Shower Enclosure | H55: =SUM(H46:H54) -> 89100 | J55: =SUM(J46:J54) -> 0 | K55: =SUM(K46:K54) -> 0 | L55: =SUM(L46:L54) -> 0 | M55: =SUM(M46:M54) -> 9 | N55: =SUM(N46:N54) -> 0 | O55: =SUM(O46:O54) -> 0 | P55: =SUM(P46:P54) -> 0 | Q55: =SUM(Q46:Q54) -> 89100 | R55: =(SUM(R46:R54)/COUNT(R46:R54)) -> 0
B56: Total for doors and window: | H56: =SUM(H34,H44,H55) -> 1561707.2 | J56: =SUM(J55,J44,J34) -> 0 | K56: =SUM(K55,K44,K34) -> 10.5 | L56: =SUM(L55,L44,L34) -> 10.5 | M56: =SUM(M55,M44,M34) -> 45.5 | N56: =SUM(N55,N44,N34) -> 0 | O56: =SUM(O55,O44,O34) -> 241863.6 | P56: =SUM(P55,P44,P34) -> 241863.6 | Q56: =SUM(Q55,Q44,Q34) -> 1319843.6 | R56: =SUM(R55,R44,R34)/3 -> 0.047619048 | AN56: =SUM(AN55,AN44,AN34)/3 -> 0 | AO56: =SUM(AO55,AO44,AO34)/3 -> 0.54761905 | AP56: =SUM(AP55,AP44,AP34)/3 -> 0 | AQ56: =SUM(AQ55,AQ44,AQ34)/3 -> 0 | AR56: =SUM(AR55,AR44,AR34)/3 -> 0 | AS56: =SUM(AS55,AS44,AS34)/3 -> 0 | AT56: =SUM(AT55,AT44,AT34)/3 -> 0 | AU56: =SUM(AU55,AU44,AU34)/3 -> 0
A57: C | B57: PLUMBING FIIXTURES
A58: WC | B58: Water Closet | C58: 4 | D58: sets | E58: OSM | F58: 1500 | G58: =SUM(E58,F58) -> 1500 | H58: =G58*C58 -> 6000 | J58: =SUM(T58:AA58) -> 0 | K58: =C58*R58 -> 0 | L58: =SUM(J58:K58) -> 0 | M58: =C58-L58 -> 4 | N58: =SUM(AC58:AJ58) -> 0 | O58: =R58*H58 -> 0 | P58: =SUM(N58:O58) -> 0 | Q58: =H58-P58 -> 6000 | R58: =SUM(AL58) -> 0
A59: LS | B59: Lavatory/Sink | C59: 6 | D59: sets | E59: OSM | F59: 3000 | G59: =SUM(E59,F59) -> 3000 | H59: =G59*C59 -> 18000 | J59: =SUM(T59:AA59) -> 0 | K59: =C59*R59 -> 0 | L59: =SUM(J59:K59) -> 0 | M59: =C59-L59 -> 6 | N59: =SUM(AC59:AJ59) -> 0 | O59: =R59*H59 -> 0 | P59: =SUM(N59:O59) -> 0 | Q59: =H59-P59 -> 18000 | R59: =SUM(AL59) -> 0
A60: BT | B60: Bathtub | C60: 2 | D60: sets | E60: OSM | F60: 4000 | G60: =SUM(E60,F60) -> 4000 | H60: =G60*C60 -> 8000 | J60: =SUM(T60:AA60) -> 0 | K60: =C60*R60 -> 0 | L60: =SUM(J60:K60) -> 0 | M60: =C60-L60 -> 2 | N60: =SUM(AC60:AJ60) -> 0 | O60: =R60*H60 -> 0 | P60: =SUM(N60:O60) -> 0 | Q60: =H60-P60 -> 8000 | R60: =SUM(AL60) -> 0 | AN60: 0 | AO60: 0 | AP60: 0 | AQ60: 0 | AR60: 0 | AS60: 0 | AT60: 0 | AU60: 0
A61: SS | B61: Shower Set | C61: 2 | D61: sets | E61: OSM | F61: 2000 | G61: =SUM(E61,F61) -> 2000 | H61: =G61*C61 -> 4000 | J61: =SUM(T61:AA61) -> 0 | K61: =C61*R61 -> 0 | L61: =SUM(J61:K61) -> 0 | M61: =C61-L61 -> 2 | N61: =SUM(AC61:AJ61) -> 0 | O61: =R61*H61 -> 0 | P61: =SUM(N61:O61) -> 0 | Q61: =H61-P61 -> 4000 | R61: =SUM(AL61) -> 0
A62: B | B62: Bidet | C62: 4 | D62: sets | E62: OSM | F62: 500 | G62: =SUM(E62,F62) -> 500 | H62: =G62*C62 -> 2000 | J62: =SUM(T62:AA62) -> 0 | K62: =C62*R62 -> 0 | L62: =SUM(J62:K62) -> 0 | M62: =C62-L62 -> 4 | N62: =SUM(AC62:AJ62) -> 0 | O62: =R62*H62 -> 0 | P62: =SUM(N62:O62) -> 0 | Q62: =H62-P62 -> 2000 | R62: =SUM(AL62) -> 0
A63: FD | B63: Floor Drain | C63: 5 | D63: sets | E63: OSM | F63: 500 | G63: =SUM(E63,F63) -> 500 | H63: =G63*C63 -> 2500 | J63: =SUM(T63:AA63) -> 0 | K63: =C63*R63 -> 0 | L63: =SUM(J63:K63) -> 0 | M63: =C63-L63 -> 5 | N63: =SUM(AC63:AJ63) -> 0 | O63: =R63*H63 -> 0 | P63: =SUM(N63:O63) -> 0 | Q63: =H63-P63 -> 2500 | R63: =SUM(AL63) -> 0
A64: KS | B64: Kitchen Sink | C64: 2 | D64: sets | E64: OSM | F64: 500 | G64: =SUM(E64,F64) -> 500 | H64: =G64*C64 -> 1000 | J64: =SUM(T64:AA64) -> 0 | K64: =C64*R64 -> 0 | L64: =SUM(J64:K64) -> 0 | M64: =C64-L64 -> 2 | N64: =SUM(AC64:AJ64) -> 0 | O64: =R64*H64 -> 0 | P64: =SUM(N64:O64) -> 0 | Q64: =H64-P64 -> 1000 | R64: =SUM(AL64) -> 0
A65: F | B65: Faucet | C65: 10 | D65: sets | E65: OSM | F65: 1500 | G65: =SUM(E65,F65) -> 1500 | H65: =G65*C65 -> 15000 | J65: =SUM(T65:AA65) -> 0 | K65: =C65*R65 -> 0 | L65: =SUM(J65:K65) -> 0 | M65: =C65-L65 -> 10 | N65: =SUM(AC65:AJ65) -> 0 | O65: =R65*H65 -> 0 | P65: =SUM(N65:O65) -> 0 | Q65: =H65-P65 -> 15000 | R65: =SUM(AL65) -> 0
B66: Plumbing Fixtures Sub-Total: | H66: =SUM(H58:H65) -> 56500 | J66: =SUM(J58:J65) -> 0 | K66: =SUM(K58:K65) -> 0 | L66: =SUM(L58:L65) -> 0 | M66: =SUM(M58:M65) -> 35 | N66: =SUM(N58:N65) -> 0 | O66: =SUM(O58:O65) -> 0 | P66: =SUM(P58:P65) -> 0 | Q66: =SUM(Q58:Q65) -> 56500 | R66: =SUM(R58:R65)/COUNT(R58:R65) -> 0 | AN66: =SUM(AN58:AN65)/COUNT(AN58:AN65) -> 0 | AO66: =SUM(AO58:AO65)/COUNT(AO58:AO65) -> 0 | AP66: =SUM(AP58:AP65)/COUNT(AP58:AP65) -> 0 | AQ66: =SUM(AQ58:AQ65)/COUNT(AQ58:AQ65) -> 0 | AR66: =SUM(AR58:AR65)/COUNT(AR58:AR65) -> 0 | AS66: =SUM(AS58:AS65)/COUNT(AS58:AS65) -> 0 | AT66: =SUM(AT58:AT65)/COUNT(AT58:AT65) -> 0 | AU66: =SUM(AU58:AU65)/COUNT(AU58:AU65) -> 0

Sheet ELECTRICAL
A14: Project name : | B14: PROPOSED THREE STORY RESIDENCE
A15: Location : | B15: GRAND CENTENIAL HOMES KAWIT CAVITE
A16: Date : | B16: =TODAY() -> 46251
AE17: QUANTITY | AN17: AMOUNT
A18: ITEM NO | B18: Description | C18: QUANTITY | D18: QUANTITY | E18: UNIT | F18: Material Cost Php/unit | G18: Labor and Equipment Cost Php/unit | H18: Total Cost Php/Unit | I18: Total Amount Php | U18: QUANTITY | Y18: AMOUNT | AC18: PERCENTAGE | AE18: BILLING 1 | AF18: BILLING 2 | AG18: BILLING 3 | AH18: BILLING 4 | AI18: BILLING 5 | AJ18: BILLING 6 | AK18: BILLING 7 | AL18: BILLING 8 | AN18: BILLING 1 | AO18: BILLING 2 | AP18: BILLING 3 | AQ18: BILLING 4 | AR18: BILLING 5 | AS18: BILLING 6 | AT18: BILLING 7 | AU18: BILLING 8 | AW18: ACCOMPLISHMENT | AY18: PREVIOUS ACCOMPLISHMENT
A19: D | B19: ELECTRICAL WORKS | U19: PREVIOUS | V19: THIS DATE | W19: TO DATE | X19: BALANCE | Y19: PREVIOUS | Z19: THIS DATE | AA19: TO DATE | AB19: BALANCE | AC19: Accomplishment | AW19: BILLING | AY19: BILLING 1 | AZ19: BILLING 2 | BA19: BILLING 3 | BB19: BILLING 4 | BC19: BILLING 5 | BD19: BILLING 6 | BE19: BILLING 7 | BF19: BILLING 8
B20: Lighting Fixtures, Outlets and Switches
B21: Outlets | L21: 1.1 | M21: QUANTITY
B22: Motor Outlets | C22: 9 | D22: =ROUNDUP(C22*$L$21,0) -> 10 | E22: pcs | F22: ='electrical labor and materials'!D18 -> 275 | G22: ='electrical labor and materials'!F18 -> 550 | H22: =SUM(F22:G22) -> 825 | I22: =H22*D22 -> 8250 | L22: 0.08 | M22: MISCELLANEOUS | U22: =SUM(AE22:AL22) -> 0 | V22: =D22*AC22 -> 4 | W22: =SUM(U22:V22) -> 4 | X22: =D22-W22 -> 6 | Y22: =SUM(AN22:AU22) -> 0 | Z22: =AC22*I22 -> 3300 | AA22: =SUM(Y22:Z22) -> 3300 | AB22: =I22-AA22 -> 4950 | AC22: =SUM(AW22:AX22) -> 0.4 | AW22: 0.4 | AY22: =SUM(BS22:BT22) -> 0 | AZ22: =SUM(BT22:BU22) -> 0 | BA22: =SUM(BU22:BV22) -> 0 | BB22: =SUM(BV22:BW22) -> 0 | BC22: =SUM(BW22:BX22) -> 0 | BD22: =SUM(BX22:BY22) -> 0 | BE22: =SUM(BY22:BZ22) -> 0 | BF22: =SUM(BZ22:CA22) -> 0
B23: Convinience Outlets | C23: 64 | D23: =ROUNDUP(C23*$L$21,0) -> 71 | E23: pcs | F23: ='electrical labor and materials'!D19 -> 275 | G23: ='electrical labor and materials'!F19 -> 550 | H23: =SUM(F23:G23) -> 825 | I23: =H23*D23 -> 58575 | U23: =SUM(AE23:AL23) -> 0 | V23: =D23*AC23 -> 28.4 | W23: =SUM(U23:V23) -> 28.4 | X23: =D23-W23 -> 42.6 | Y23: =SUM(AN23:AU23) -> 0 | Z23: =AC23*I23 -> 23430 | AA23: =SUM(Y23:Z23) -> 23430 | AB23: =I23-AA23 -> 35145 | AC23: =SUM(AW23:AX23) -> 0.4 | AW23: 0.4 | AY23: =SUM(BS23:BT23) -> 0 | AZ23: =SUM(BT23:BU23) -> 0 | BA23: =SUM(BU23:BV23) -> 0 | BB23: =SUM(BV23:BW23) -> 0 | BC23: =SUM(BW23:BX23) -> 0 | BD23: =SUM(BX23:BY23) -> 0 | BE23: =SUM(BY23:BZ23) -> 0 | BF23: =SUM(BZ23:CA23) -> 0
B24: Outlets Sub-total: | I24: =SUM(I22:I23) -> 66825 | U24: =SUM(U22:U23) -> 0 | V24: =SUM(V22:V23) -> 32.4 | W24: =SUM(W22:W23) -> 32.4 | X24: =SUM(X22:X23) -> 48.6 | Y24: =SUM(Y22:Y23) -> 0 | Z24: =SUM(Z22:Z23) -> 26730 | AA24: =SUM(AA22:AA23) -> 26730 | AB24: =SUM(AB22:AB23) -> 40095 | AC24: =SUM(AC22:AC23)/COUNT(AC22:AC23) -> 0.4 | AY24: =SUM(AY22:AY23)/COUNT(AY22:AY23) -> 0 | AZ24: =SUM(AZ22:AZ23)/COUNT(AZ22:AZ23) -> 0 | BA24: =SUM(BA22:BA23)/COUNT(BA22:BA23) -> 0 | BB24: =SUM(BB22:BB23)/COUNT(BB22:BB23) -> 0 | BC24: =SUM(BC22:BC23)/COUNT(BC22:BC23) -> 0 | BD24: =SUM(BD22:BD23)/COUNT(BD22:BD23) -> 0 | BE24: =SUM(BE22:BE23)/COUNT(BE22:BE23) -> 0 | BF24: =SUM(BF22:BF23)/COUNT(BF22:BF23) -> 0
B25: Switches
B26: 1 gang | C26: 15 | D26: =ROUNDUP(C26*$L$21,0) -> 17 | E26: pcs | F26: ='electrical labor and materials'!D21 -> 176 | G26: ='electrical labor and materials'!F21 -> 550 | H26: =SUM(F26:G26) -> 726 | I26: =H26*D26 -> 12342 | U26: =SUM(AE26:AL26) -> 0 | V26: =D26*AC26 -> 5.95 | W26: =SUM(U26:V26) -> 5.95 | X26: =D26-W26 -> 11.05 | Y26: =SUM(AN26:AU26) -> 0 | Z26: =AC26*I26 -> 4319.7 | AA26: =SUM(Y26:Z26) -> 4319.7 | AB26: =I26-AA26 -> 8022.3 | AC26: =SUM(AW26:AX26) -> 0.35 | AW26: 0.35 | AY26: =SUM(BS26:BT26) -> 0 | AZ26: =SUM(BT26:BU26) -> 0 | BA26: =SUM(BU26:BV26) -> 0 | BB26: =SUM(BV26:BW26) -> 0 | BC26: =SUM(BW26:BX26) -> 0 | BD26: =SUM(BX26:BY26) -> 0 | BE26: =SUM(BY26:BZ26) -> 0 | BF26: =SUM(BZ26:CA26) -> 0
B27: 2 gang | C27: 11 | D27: =ROUNDUP(C27*$L$21,0) -> 13 | E27: pcs | F27: ='electrical labor and materials'!D22 -> 297 | G27: ='electrical labor and materials'!F22 -> 550 | H27: =SUM(F27:G27) -> 847 | I27: =H27*D27 -> 11011 | U27: =SUM(AE27:AL27) -> 0 | V27: =D27*AC27 -> 4.55 | W27: =SUM(U27:V27) -> 4.55 | X27: =D27-W27 -> 8.45 | Y27: =SUM(AN27:AU27) -> 0 | Z27: =AC27*I27 -> 3853.85 | AA27: =SUM(Y27:Z27) -> 3853.85 | AB27: =I27-AA27 -> 7157.15 | AC27: =SUM(AW27:AX27) -> 0.35 | AW27: 0.35 | AY27: =SUM(BS27:BT27) -> 0 | AZ27: =SUM(BT27:BU27) -> 0 | BA27: =SUM(BU27:BV27) -> 0 | BB27: =SUM(BV27:BW27) -> 0 | BC27: =SUM(BW27:BX27) -> 0 | BD27: =SUM(BX27:BY27) -> 0 | BE27: =SUM(BY27:BZ27) -> 0 | BF27: =SUM(BZ27:CA27) -> 0
B28: 3 gang | C28: 14 | D28: =ROUNDUP(C28*$L$21,0) -> 16 | E28: pcs | F28: ='electrical labor and materials'!D23 -> 418 | G28: ='electrical labor and materials'!F23 -> 550 | H28: =SUM(F28:G28) -> 968 | I28: =H28*D28 -> 15488 | U28: =SUM(AE28:AL28) -> 0 | V28: =D28*AC28 -> 6.4 | W28: =SUM(U28:V28) -> 6.4 | X28: =D28-W28 -> 9.6 | Y28: =SUM(AN28:AU28) -> 0 | Z28: =AC28*I28 -> 6195.2 | AA28: =SUM(Y28:Z28) -> 6195.2 | AB28: =I28-AA28 -> 9292.8 | AC28: =SUM(AW28:AX28) -> 0.4 | AW28: 0.4 | AY28: =SUM(BS28:BT28) -> 0 | AZ28: =SUM(BT28:BU28) -> 0 | BA28: =SUM(BU28:BV28) -> 0 | BB28: =SUM(BV28:BW28) -> 0 | BC28: =SUM(BW28:BX28) -> 0 | BD28: =SUM(BX28:BY28) -> 0 | BE28: =SUM(BY28:BZ28) -> 0 | BF28: =SUM(BZ28:CA28) -> 0
B29: Switches Sub-total: | I29: =SUM(I26:I28) -> 38841 | U29: =SUM(U26:U28) -> 0 | V29: =SUM(V26:V28) -> 16.9 | W29: =SUM(W26:W28) -> 16.9 | X29: =SUM(X26:X28) -> 29.1 | Y29: =SUM(Y26:Y28) -> 0 | Z29: =SUM(Z26:Z28) -> 14368.75 | AA29: =SUM(AA26:AA28) -> 14368.75 | AB29: =SUM(AB26:AB28) -> 24472.25 | AC29: =SUM(AC26:AC28)/COUNT(AC26:AC28) -> 0.36666667 | AY29: =SUM(AY26:AY28)/COUNT(AY26:AY28) -> 0 | AZ29: =SUM(AZ26:AZ28)/COUNT(AZ26:AZ28) -> 0 | BA29: =SUM(BA26:BA28)/COUNT(BA26:BA28) -> 0 | BB29: =SUM(BB26:BB28)/COUNT(BB26:BB28) -> 0 | BC29: =SUM(BC26:BC28)/COUNT(BC26:BC28) -> 0 | BD29: =SUM(BD26:BD28)/COUNT(BD26:BD28) -> 0 | BE29: =SUM(BE26:BE28)/COUNT(BE26:BE28) -> 0 | BF29: =SUM(BF26:BF28)/COUNT(BF26:BF28) -> 0
B30: Lighting Fixtures
B31: Pinlights | C31: 94 | D31: =ROUNDUP(C31*$L$21,0) -> 104 | E31: pcs | F31: ='electrical labor and materials'!D25 -> 440 | G31: ='electrical labor and materials'!F25 -> 550 | H31: =SUM(F31:G31) -> 990 | I31: =H31*D31 -> 102960 | U31: =SUM(AE31:AL31) -> 0 | V31: =D31*AC31 -> 20.8 | W31: =SUM(U31:V31) -> 20.8 | X31: =D31-W31 -> 83.2 | Y31: =SUM(AN31:AU31) -> 0 | Z31: =AC31*I31 -> 20592 | AA31: =SUM(Y31:Z31) -> 20592 | AB31: =I31-AA31 -> 82368 | AC31: =SUM(AW31:AX31) -> 0.2 | AW31: 0.2 | AY31: =SUM(BS31:BT31) -> 0 | AZ31: =SUM(BT31:BU31) -> 0 | BA31: =SUM(BU31:BV31) -> 0 | BB31: =SUM(BV31:BW31) -> 0 | BC31: =SUM(BW31:BX31) -> 0 | BD31: =SUM(BX31:BY31) -> 0 | BE31: =SUM(BY31:BZ31) -> 0 | BF31: =SUM(BZ31:CA31) -> 0
B32: Twin Pin Lights | C32: 18 | D32: 18 | E32: pcs | F32: ='electrical labor and materials'!D24 -> 730 | G32: ='electrical labor and materials'!F24 -> 550 | H32: =SUM(F32:G32) -> 1280 | I32: =H32*D32 -> 23040 | M32: For 387 sq.m residential (3-storey, almost luxury): | U32: =SUM(AE32:AL32) -> 0 | V32: =D32*AC32 -> 3.6 | W32: =SUM(U32:V32) -> 3.6 | X32: =D32-W32 -> 14.4 | Y32: =SUM(AN32:AU32) -> 0 | Z32: =AC32*I32 -> 4608 | AA32: =SUM(Y32:Z32) -> 4608 | AB32: =I32-AA32 -> 18432 | AC32: =SUM(AW32:AX32) -> 0.2 | AW32: 0.2 | AY32: =SUM(BS32:BT32) -> 0 | AZ32: =SUM(BT32:BU32) -> 0 | BA32: =SUM(BU32:BV32) -> 0 | BB32: =SUM(BV32:BW32) -> 0 | BC32: =SUM(BW32:BX32) -> 0 | BD32: =SUM(BX32:BY32) -> 0 | BE32: =SUM(BY32:BZ32) -> 0 | BF32: =SUM(BZ32:CA32) -> 0
B33: Strip Lights (3500K) | C33: 120 | D33: =ROUNDUP(C33*$L$21,0) -> 132 | E33: Im | F33: ='electrical labor and materials'!D26 -> 132 | G33: ='electrical labor and materials'!F26 -> 550 | H33: =SUM(F33:G33) -> 682 | I33: =H33*D33 -> 90024 | U33: =SUM(AE33:AL33) -> 0 | V33: =D33*AC33 -> 26.4 | W33: =SUM(U33:V33) -> 26.4 | X33: =D33-W33 -> 105.6 | Y33: =SUM(AN33:AU33) -> 0 | Z33: =AC33*I33 -> 18004.8 | AA33: =SUM(Y33:Z33) -> 18004.8 | AB33: =I33-AA33 -> 72019.2 | AC33: =SUM(AW33:AX33) -> 0.2 | AW33: 0.2 | AY33: =SUM(BS33:BT33) -> 0 | AZ33: =SUM(BT33:BU33) -> 0 | BA33: =SUM(BU33:BV33) -> 0 | BB33: =SUM(BV33:BW33) -> 0 | BC33: =SUM(BW33:BX33) -> 0 | BD33: =SUM(BX33:BY33) -> 0 | BE33: =SUM(BY33:BZ33) -> 0 | BF33: =SUM(BZ33:CA33) -> 0
B34: Round Center Lights | D34: 5 | E34: pcs | F34: ='electrical labor and materials'!D27 -> 1100 | G34: ='electrical labor and materials'!F27 -> 550 | H34: =SUM(F34:G34) -> 1650 | I34: =H34*D34 -> 8250 | U34: =SUM(AE34:AL34) -> 0 | V34: =D34*AC34 -> 1 | W34: =SUM(U34:V34) -> 1 | X34: =D34-W34 -> 4 | Y34: =SUM(AN34:AU34) -> 0 | Z34: =AC34*I34 -> 1650 | AA34: =SUM(Y34:Z34) -> 1650 | AB34: =I34-AA34 -> 6600 | AC34: =SUM(AW34:AX34) -> 0.2 | AW34: 0.2 | AY34: =SUM(BS34:BT34) -> 0 | AZ34: =SUM(BT34:BU34) -> 0 | BA34: =SUM(BU34:BV34) -> 0 | BB34: =SUM(BV34:BW34) -> 0 | BC34: =SUM(BW34:BX34) -> 0 | BD34: =SUM(BX34:BY34) -> 0 | BE34: =SUM(BY34:BZ34) -> 0 | BF34: =SUM(BZ34:CA34) -> 0
B35: Accent Lights | D35: 3 | E35: pcs | F35: ='electrical labor and materials'!D28 -> 1100 | G35: ='electrical labor and materials'!F28 -> 550 | H35: =SUM(F35:G35) -> 1650 | I35: =H35*D35 -> 4950 | M35: 387 | N35: sq.m | O35: actual wires | U35: =SUM(AE35:AL35) -> 0 | V35: =D35*AC35 -> 0.6 | W35: =SUM(U35:V35) -> 0.6 | X35: =D35-W35 -> 2.4 | Y35: =SUM(AN35:AU35) -> 0 | Z35: =AC35*I35 -> 990 | AA35: =SUM(Y35:Z35) -> 990 | AB35: =I35-AA35 -> 3960 | AC35: =SUM(AW35:AX35) -> 0.2 | AW35: 0.2 | AY35: =SUM(BS35:BT35) -> 0 | AZ35: =SUM(BT35:BU35) -> 0 | BA35: =SUM(BU35:BV35) -> 0 | BB35: =SUM(BV35:BW35) -> 0 | BC35: =SUM(BW35:BX35) -> 0 | BD35: =SUM(BX35:BY35) -> 0 | BE35: =SUM(BY35:BZ35) -> 0 | BF35: =SUM(BZ35:CA35) -> 0
B36: Pendant Lights | C36: 15 | D36: 12 | E36: pcs | F36: ='electrical labor and materials'!D29 -> 7700 | G36: ='electrical labor and materials'!F29 -> 550 | H36: =SUM(F36:G36) -> 8250 | I36: =H36*D36 -> 99000 | M36: Lighting (2.0 mm²): ~2.5–3.5 lm per sqm | N36: =M35*3 -> 1161 | O36: =D47 -> 1098.02 | P36: =IF(O36>N36,"OVERKILL",IF(N36>O36,"Good")) -> Good | U36: =SUM(AE36:AL36) -> 0 | V36: =D36*AC36 -> 2.4 | W36: =SUM(U36:V36) -> 2.4 | X36: =D36-W36 -> 9.6 | Y36: =SUM(AN36:AU36) -> 0 | Z36: =AC36*I36 -> 19800 | AA36: =SUM(Y36:Z36) -> 19800 | AB36: =I36-AA36 -> 79200 | AC36: =SUM(AW36:AX36) -> 0.2 | AW36: 0.2 | AY36: =SUM(BS36:BT36) -> 0 | AZ36: =SUM(BT36:BU36) -> 0 | BA36: =SUM(BU36:BV36) -> 0 | BB36: =SUM(BV36:BW36) -> 0 | BC36: =SUM(BW36:BX36) -> 0 | BD36: =SUM(BX36:BY36) -> 0 | BE36: =SUM(BY36:BZ36) -> 0 | BF36: =SUM(BZ36:CA36) -> 0
B37: Chandelier | D37: 1 | E37: pcs | F37: ='electrical labor and materials'!D30 -> 140250 | G37: ='electrical labor and materials'!F30 -> 7700 | H37: =SUM(F37:G37) -> 147950 | I37: =H37*D37 -> 147950 | M37: Convenience outlets (3.5 mm²): ~0.8–1.2 lm per sqm | N37: =M35*1 -> 387 | O37: =D44 -> 381.7 | P37: =IF(O37>N37,"OVERKILL",IF(N37>O37,"Good")) -> Good | U37: =SUM(AE37:AL37) -> 0 | V37: =D37*AC37 -> 0.2 | W37: =SUM(U37:V37) -> 0.2 | X37: =D37-W37 -> 0.8 | Y37: =SUM(AN37:AU37) -> 0 | Z37: =AC37*I37 -> 29590 | AA37: =SUM(Y37:Z37) -> 29590 | AB37: =I37-AA37 -> 118360 | AC37: =SUM(AW37:AX37) -> 0.2 | AW37: 0.2 | AY37: =SUM(BS37:BT37) -> 0 | AZ37: =SUM(BT37:BU37) -> 0 | BA37: =SUM(BU37:BV37) -> 0 | BB37: =SUM(BV37:BW37) -> 0 | BC37: =SUM(BW37:BX37) -> 0 | BD37: =SUM(BX37:BY37) -> 0 | BE37: =SUM(BY37:BZ37) -> 0 | BF37: =SUM(BZ37:CA37) -> 0
B38: Wall Lamps | D38: 5 | E38: pcs | F38: ='electrical labor and materials'!D31 -> 5500 | G38: ='electrical labor and materials'!F31 -> 550 | H38: =SUM(F38:G38) -> 6050 | I38: =H38*D38 -> 30250 | M38: Higher loads / AC / kitchen (5.5 mm²): ~0.5–0.8 lm per sqm | N38: =M35*0.65 -> 251.55 | O38: =D45 -> 247.5 | P38: =IF(O38>N38,"OVERKILL",IF(N38>O38,"Good")) -> Good | U38: =SUM(AE38:AL38) -> 0 | V38: =D38*AC38 -> 1 | W38: =SUM(U38:V38) -> 1 | X38: =D38-W38 -> 4 | Y38: =SUM(AN38:AU38) -> 0 | Z38: =AC38*I38 -> 6050 | AA38: =SUM(Y38:Z38) -> 6050 | AB38: =I38-AA38 -> 24200 | AC38: =SUM(AW38:AX38) -> 0.2 | AW38: 0.2 | AY38: =SUM(BS38:BT38) -> 0 | AZ38: =SUM(BT38:BU38) -> 0 | BA38: =SUM(BU38:BV38) -> 0 | BB38: =SUM(BV38:BW38) -> 0 | BC38: =SUM(BW38:BX38) -> 0 | BD38: =SUM(BX38:BY38) -> 0 | BE38: =SUM(BY38:BZ38) -> 0 | BF38: =SUM(BZ38:CA38) -> 0
B39: Integrated fan light | D39: 3 | E39: pcs | F39: ='electrical labor and materials'!D32 -> 11000 | G39: ='electrical labor and materials'!F32 -> 550 | H39: =SUM(F39:G39) -> 11550 | I39: =H39*D39 -> 34650 | U39: =SUM(AE39:AL39) -> 0 | V39: =D39*AC39 -> 0.6 | W39: =SUM(U39:V39) -> 0.6 | X39: =D39-W39 -> 2.4 | Y39: =SUM(AN39:AU39) -> 0 | Z39: =AC39*I39 -> 6930 | AA39: =SUM(Y39:Z39) -> 6930 | AB39: =I39-AA39 -> 27720 | AC39: =SUM(AW39:AX39) -> 0.2 | AW39: 0.2 | AY39: =SUM(BS39:BT39) -> 0 | AZ39: =SUM(BT39:BU39) -> 0 | BA39: =SUM(BU39:BV39) -> 0 | BB39: =SUM(BV39:BW39) -> 0 | BC39: =SUM(BW39:BX39) -> 0 | BD39: =SUM(BX39:BY39) -> 0 | BE39: =SUM(BY39:BZ39) -> 0 | BF39: =SUM(BZ39:CA39) -> 0
B40: Magnetic Track light | C40: 9.4 | D40: =ROUNDUP(C40*$L$21,0) -> 11 | E40: l.m | F40: ='electrical labor and materials'!D33 -> 5500 | G40: ='electrical labor and materials'!F33 -> 550 | H40: =SUM(F40:G40) -> 6050 | I40: =H40*D40 -> 66550 | U40: =SUM(AE40:AL40) -> 0 | V40: =D40*AC40 -> 2.2 | W40: =SUM(U40:V40) -> 2.2 | X40: =D40-W40 -> 8.8 | Y40: =SUM(AN40:AU40) -> 0 | Z40: =AC40*I40 -> 13310 | AA40: =SUM(Y40:Z40) -> 13310 | AB40: =I40-AA40 -> 53240 | AC40: =SUM(AW40:AX40) -> 0.2 | AW40: 0.2 | AY40: =SUM(BS40:BT40) -> 0 | AZ40: =SUM(BT40:BU40) -> 0 | BA40: =SUM(BU40:BV40) -> 0 | BB40: =SUM(BV40:BW40) -> 0 | BC40: =SUM(BW40:BX40) -> 0 | BD40: =SUM(BX40:BY40) -> 0 | BE40: =SUM(BY40:BZ40) -> 0 | BF40: =SUM(BZ40:CA40) -> 0
B41: Lighting Fixtures Sub-total: | I41: =SUM(I31:I40) -> 607624 | K41: 0.05 | L41: miscellaneous | U41: =SUM(U31:U40) -> 0 | V41: =SUM(V31:V40) -> 58.8 | W41: =SUM(W31:W40) -> 58.8 | X41: =SUM(X31:X40) -> 235.2 | Y41: =SUM(Y31:Y40) -> 0 | Z41: =SUM(Z31:Z40) -> 121524.8 | AA41: =SUM(AA31:AA40) -> 121524.8 | AB41: =SUM(AB31:AB40) -> 486099.2 | AC41: =SUM(AC31:AC40)/COUNT(AC31:AC40) -> 0.2 | AY41: =SUM(AY31:AY40)/COUNT(AY31:AY40) -> 0 | AZ41: =SUM(AZ31:AZ40)/COUNT(AZ31:AZ40) -> 0 | BA41: =SUM(BA31:BA40)/COUNT(BA31:BA40) -> 0 | BB41: =SUM(BB31:BB40)/COUNT(BB31:BB40) -> 0 | BC41: =SUM(BC31:BC40)/COUNT(BC31:BC40) -> 0 | BD41: =SUM(BD31:BD40)/COUNT(BD31:BD40) -> 0 | BE41: =SUM(BE31:BE40)/COUNT(BE31:BE40) -> 0 | BF41: =SUM(BF31:BF40)/COUNT(BF31:BF40) -> 0
B42: Wires
B43: OUTLETS | P43: STRIP LIGHTS
B44: 3.5 mm | C44: 347 | D44: =C44*$K$44 -> 381.7 | E44: l.m | F44: ='electrical labor and materials'!D36 -> 41.36 | G44: ='electrical labor and materials'!F36 -> 165 | H44: =SUM(F44:G44) -> 206.36 | I44: =H44*D44 -> 78767.612 | K44: 1.1 | L44: QUANTITY | O44: 8.6 | P44: =O44*4 -> 34.4 | U44: =SUM(AE44:AL44) -> 0 | V44: =D44*AC44 -> 76.34 | W44: =SUM(U44:V44) -> 76.34 | X44: =D44-W44 -> 305.36 | Y44: =SUM(AN44:AU44) -> 0 | Z44: =AC44*I44 -> 15753.522 | AA44: =SUM(Y44:Z44) -> 15753.522 | AB44: =I44-AA44 -> 63014.09 | AC44: =SUM(AW44:AX44) -> 0.2 | AW44: 0.2 | AY44: 0.5 | AZ44: 0.3 | BA44: 0 | BB44: 0 | BC44: 0 | BD44: 0 | BE44: 0 | BF44: 0
B45: 5.5 mm | C45: 225 | D45: =C45*$K$44 -> 247.5 | E45: l.m | F45: ='electrical labor and materials'!D37 -> 58.52 | G45: ='electrical labor and materials'!F37 -> 165 | H45: =SUM(F45:G45) -> 223.52 | I45: =H45*D45 -> 55321.2 | P45: =4.8*2 -> 9.6 | U45: =SUM(AE45:AL45) -> 0 | V45: =D45*AC45 -> 49.5 | W45: =SUM(U45:V45) -> 49.5 | X45: =D45-W45 -> 198 | Y45: =SUM(AN45:AU45) -> 0 | Z45: =AC45*I45 -> 11064.24 | AA45: =SUM(Y45:Z45) -> 11064.24 | AB45: =I45-AA45 -> 44256.96 | AC45: =SUM(AW45:AX45) -> 0.2 | AW45: 0.2 | AY45: 0.4 | AZ45: 0.4
B46: LIGHTING | P46: 25.9
B47: 2.0mm | C47: 998.2 | D47: =C47*K47 -> 1098.02 | E47: l.m | F47: ='electrical labor and materials'!D39 -> 38.5 | G47: ='electrical labor and materials'!F39 -> 165 | H47: =SUM(F47:G47) -> 203.5 | I47: =H47*D47 -> 223447.07 | K47: 1.1 | P47: 68.2 | U47: =SUM(AE47:AL47) -> 0 | V47: =D47*AC47 -> 329.406 | W47: =SUM(U47:V47) -> 329.406 | X47: =D47-W47 -> 768.614 | Y47: =SUM(AN47:AU47) -> 0 | Z47: =AC47*I47 -> 67034.121 | AA47: =SUM(Y47:Z47) -> 67034.121 | AB47: =I47-AA47 -> 156412.95 | AC47: =SUM(AW47:AX47) -> 0.3 | AW47: 0.3 | AY47: 0.2 | AZ47: 0.2
B48: Miscellaneuos and Other accessories | D48: 1 | E48: lot | I48: =SUM(I43:I47)*K41 -> 17876.794 | U48: =SUM(AE48:AL48) -> 0 | V48: =D48*AC48 -> 0.15 | W48: =SUM(U48:V48) -> 0.15 | X48: =D48-W48 -> 0.85 | Y48: =SUM(AN48:AU48) -> 0 | Z48: =AC48*I48 -> 2681.5191 | AA48: =SUM(Y48:Z48) -> 2681.5191 | AB48: =I48-AA48 -> 15195.275 | AC48: =SUM(AW48:AX48) -> 0.15 | AW48: 0.15 | AY48: 0.49 | AZ48: 0.3
B49: Wires Sub-total: | I49: =SUM(I44:I48) -> 375412.68 | U49: =SUM(U44:U48) -> 0 | V49: =SUM(V44:V48) -> 455.396 | W49: =SUM(W44:W48) -> 455.396 | X49: =SUM(X44:X48) -> 1272.824 | Y49: =SUM(Y44:Y48) -> 0 | Z49: =SUM(Z44:Z48) -> 96533.403 | AA49: =SUM(AA44:AA48) -> 96533.403 | AB49: =SUM(AB44:AB48) -> 278879.27 | AC49: =SUM(AC44:AC48)/COUNT(AC44:AC48) -> 0.2125 | AY49: =SUM(AY44:AY48)/COUNT(AY44:AY48) -> 0.3975 | AZ49: =SUM(AZ44:AZ48)/COUNT(AZ44:AZ48) -> 0.3 | BA49: =SUM(BA44:BA48)/COUNT(BA44:BA48) -> 0 | BB49: =SUM(BB44:BB48)/COUNT(BB44:BB48) -> 0 | BC49: =SUM(BC44:BC48)/COUNT(BC44:BC48) -> 0 | BD49: =SUM(BD44:BD48)/COUNT(BD44:BD48) -> 0 | BE49: =SUM(BE44:BE48)/COUNT(BE44:BE48) -> 0 | BF49: =SUM(BF44:BF48)/COUNT(BF44:BF48) -> 0
B50: Panel Board
B51: Feeder Line
B52: 80mm | C52: 30 | D52: =C52*$K$44 -> 33 | E52: l.m | F52: ='electrical labor and materials'!D51 -> 661 | G52: ='electrical labor and materials'!F51 -> 350 | H52: =SUM(F52:G52) -> 1011 | I52: =H52*D52 -> 33363 | U52: =SUM(AE52:AL52) -> 0 | V52: =D52*AC52 -> 6.6 | W52: =SUM(U52:V52) -> 6.6 | X52: =D52-W52 -> 26.4 | Y52: =SUM(AN52:AU52) -> 0 | Z52: =AC52*I52 -> 6672.6 | AA52: =SUM(Y52:Z52) -> 6672.6 | AB52: =I52-AA52 -> 26690.4 | AC52: =SUM(AW52:AX52) -> 0.2 | AW52: 0.2 | AY52: =SUM(BS52:BT52) -> 0 | AZ52: =SUM(BT52:BU52) -> 0 | BA52: =SUM(BU52:BV52) -> 0 | BB52: =SUM(BV52:BW52) -> 0 | BC52: =SUM(BW52:BX52) -> 0 | BD52: =SUM(BX52:BY52) -> 0 | BE52: =SUM(BY52:BZ52) -> 0 | BF52: =SUM(BZ52:CA52) -> 0
B53: 14mm | C53: 15 | D53: =C53*$K$44 -> 16.5 | E53: l.m | F53: ='electrical labor and materials'!D52 -> 132 | G53: ='electrical labor and materials'!F52 -> 275 | H53: =SUM(F53:G53) -> 407 | I53: =H53*D53 -> 6715.5 | U53: =SUM(AE53:AL53) -> 0 | V53: =D53*AC53 -> 3.3 | W53: =SUM(U53:V53) -> 3.3 | X53: =D53-W53 -> 13.2 | Y53: =SUM(AN53:AU53) -> 0 | Z53: =AC53*I53 -> 1343.1 | AA53: =SUM(Y53:Z53) -> 1343.1 | AB53: =I53-AA53 -> 5372.4 | AC53: =SUM(AW53:AX53) -> 0.2 | AW53: 0.2 | AY53: =SUM(BS53:BT53) -> 0 | AZ53: =SUM(BT53:BU53) -> 0 | BA53: =SUM(BU53:BV53) -> 0 | BB53: =SUM(BV53:BW53) -> 0 | BC53: =SUM(BW53:BX53) -> 0 | BD53: =SUM(BX53:BY53) -> 0 | BE53: =SUM(BY53:BZ53) -> 0 | BF53: =SUM(BZ53:CA53) -> 0
B55: Circuit Breaker's (schneider)
B56: PANEL BOARD 26BRS MAIN: EZC 200A, 2P(MCCB) | D56: 1 | E56: set's | F56: ='electrical labor and materials'!D54 -> 35200 | G56: ='electrical labor and materials'!F54 -> 19360 | H56: =SUM(F56:G56) -> 54560 | I56: =H56*D56 -> 54560 | U56: =SUM(AE56:AL56) -> 0 | V56: =D56*AC56 -> 0.1 | W56: =SUM(U56:V56) -> 0.1 | X56: =D56-W56 -> 0.9 | Y56: =SUM(AN56:AU56) -> 0 | Z56: =AC56*I56 -> 5456 | AA56: =SUM(Y56:Z56) -> 5456 | AB56: =I56-AA56 -> 49104 | AC56: =SUM(AW56:AX56) -> 0.1 | AW56: 0.1 | AY56: =SUM(BS56:BT56) -> 0 | AZ56: =SUM(BT56:BU56) -> 0 | BA56: =SUM(BU56:BV56) -> 0 | BB56: =SUM(BV56:BW56) -> 0 | BC56: =SUM(BW56:BX56) -> 0 | BD56: =SUM(BX56:BY56) -> 0 | BE56: =SUM(BY56:BZ56) -> 0 | BF56: =SUM(BZ56:CA56) -> 0
B58: IC60N 15A, 2P(MCB)
B59: IC60N 20A, 2P(MCB)
B60: IC60N 30A, 2P(MCB)
B61: IC60N 40A, 2P(MCB)
B62: W/GROUNDING BUSBAR | K62: 0.2 | L62: miscellaneous
P63: 27340
B64: Conduits | C64: 45 | D64: =C64*$K$44 -> 49.5 | E64: l.m | F64: ='electrical labor and materials'!D49 -> 154 | G64: =F64*0.3 -> 46.2 | H64: =SUM(F64:G64) -> 200.2 | I64: =H64*D64 -> 9909.9 | P64: =#REF!/P63 -> #REF! | U64: =SUM(AE64:AL64) -> 0 | V64: =D64*AC64 -> 0 | W64: =SUM(U64:V64) -> 0 | X64: =D64-W64 -> 49.5 | Y64: =SUM(AN64:AU64) -> 0 | Z64: =AC64*I64 -> 0 | AA64: =SUM(Y64:Z64) -> 0 | AB64: =I64-AA64 -> 9909.9 | AC64: =SUM(AW64:AX64) -> 0 | AY64: =SUM(BS64:BT64) -> 0 | AZ64: =SUM(BT64:BU64) -> 0 | BA64: =SUM(BU64:BV64) -> 0 | BB64: =SUM(BV64:BW64) -> 0 | BC64: =SUM(BW64:BX64) -> 0 | BD64: =SUM(BX64:BY64) -> 0 | BE64: =SUM(BY64:BZ64) -> 0 | BF64: =SUM(BZ64:CA64) -> 0
